Workbook
Name Slicer_SECTOR1: #N/A

Sheet Dashboard

Sheet RAW All_India_Index_Upto_April2
A1: Sector | B1: Year | C1: Month | D1: Time frame | E1: Cereals and products | F1: Meat and fish | G1: Egg | H1: Milk and products | I1: Oils and fats | J1: Fruits | K1: Vegetables | L1: Pulses and products | M1: Sugar and Confectionery | N1: Spices | O1: Non-alcoholic beverages | P1: Prepared meals, snacks, sweets etc. | Q1: Food and beverages | R1: Pan, tobacco and intoxicants | S1: Clothing | T1: Footwear | U1: Clothing and footwear | V1: Housing | W1: Fuel and light | X1: Household goods and services | Y1: Health | Z1: Transport and communication | AA1: Recreation and amusement | AB1: Education | AC1: Personal care and effects | AD1: Miscellaneous | AE1: General index
A2: Rural | B2: 2013 | C2: January | D2: =B2&" "&C2 -> 2013 January | E2: 107.5 | F2: 106.3 | G2: 108.1 | H2: 104.9 | I2: 106.1 | J2: 103.9 | K2: 101.9 | L2: 106.1 | M2: 106.8 | N2: 103.1 | O2: 104.8 | P2: 106.7 | Q2: 105.5 | R2: 105.1 | S2: 106.5 | T2: 105.8 | U2: 106.4 | V2: NA | W2: 105.5 | X2: 104.8 | Y2: 104 | Z2: 103.3 | AA2: 103.4 | AB2: 103.8 | AC2: 104.7 | AD2: 104 | AE2: 105.1
A3: Urban | B3: 2013 | C3: January | D3: =B3&" "&C3 -> 2013 January | E3: 110.5 | F3: 109.1 | G3: 113 | H3: 103.6 | I3: 103.4 | J3: 102.3 | K3: 102.9 | L3: 105.8 | M3: 105.1 | N3: 101.8 | O3: 105.1 | P3: 107.9 | Q3: 105.9 | R3: 105.2 | S3: 105.9 | T3: 105 | U3: 105.8 | V3: 100.3 | W3: 105.4 | X3: 104.8 | Y3: 104.1 | Z3: 103.2 | AA3: 102.9 | AB3: 103.5 | AC3: 104.3 | AD3: 103.7 | AE3: 104
A4: Rural+Urban | B4: 2013 | C4: January | D4: =B4&" "&C4 -> 2013 January | E4: 108.4 | F4: 107.3 | G4: 110 | H4: 104.4 | I4: 105.1 | J4: 103.2 | K4: 102.2 | L4: 106 | M4: 106.2 | N4: 102.7 | O4: 104.9 | P4: 107.3 | Q4: 105.6 | R4: 105.1 | S4: 106.3 | T4: 105.5 | U4: 106.2 | V4: 100.3 | W4: 105.5 | X4: 104.8 | Y4: 104 | Z4: 103.2 | AA4: 103.1 | AB4: 103.6 | AC4: 104.5 | AD4: 103.9 | AE4: 104.6
A5: Rural | B5: 2013 | C5: February | D5: =B5&" "&C5 -> 2013 February | E5: 109.2 | F5: 108.7 | G5: 110.2 | H5: 105.4 | I5: 106.7 | J5: 104 | K5: 102.4 | L5: 105.9 | M5: 105.7 | N5: 103.1 | O5: 105.1 | P5: 107.7 | Q5: 106.3 | R5: 105.6 | S5: 107.1 | T5: 106.3 | U5: 107 | V5: NA | W5: 106.2 | X5: 105.2 | Y5: 104.4 | Z5: 103.9 | AA5: 104 | AB5: 104.1 | AC5: 104.6 | AD5: 104.4 | AE5: 105.8
A6: Urban | B6: 2013 | C6: February | D6: =B6&" "&C6 -> 2013 February | E6: 112.9 | F6: 112.9 | G6: 116.9 | H6: 104 | I6: 103.5 | J6: 103.1 | K6: 104.9 | L6: 104.1 | M6: 103.8 | N6: 102.3 | O6: 106 | P6: 109 | Q6: 107.2 | R6: 106 | S6: 106.6 | T6: 105.5 | U6: 106.4 | V6: 100.4 | W6: 105.7 | X6: 105.2 | Y6: 104.7 | Z6: 104.4 | AA6: 103.3 | AB6: 103.7 | AC6: 104.3 | AD6: 104.3 | AE6: 104.7
A7: Rural+Urban | B7: 2013 | C7: February | D7: =B7&" "&C7 -> 2013 February | E7: 110.4 | F7: 110.2 | G7: 112.8 | H7: 104.9 | I7: 105.5 | J7: 103.6 | K7: 103.2 | L7: 105.3 | M7: 105.1 | N7: 102.8 | O7: 105.5 | P7: 108.3 | Q7: 106.6 | R7: 105.7 | S7: 106.9 | T7: 106 | U7: 106.8 | V7: 100.4 | W7: 106 | X7: 105.2 | Y7: 104.5 | Z7: 104.2 | AA7: 103.6 | AB7: 103.9 | AC7: 104.5 | AD7: 104.4 | AE7: 105.3
A8: Rural | B8: 2013 | C8: March | D8: =B8&" "&C8 -> 2013 March | E8: 110.2 | F8: 108.8 | G8: 109.9 | H8: 105.6 | I8: 106.2 | J8: 105.7 | K8: 101.4 | L8: 105.7 | M8: 105 | N8: 103.3 | O8: 105.6 | P8: 108.2 | Q8: 106.6 | R8: 106.5 | S8: 107.6 | T8: 106.8 | U8: 107.5 | V8: NA | W8: 106.1 | X8: 105.6 | Y8: 104.7 | Z8: 104.6 | AA8: 104 | AB8: 104.3 | AC8: 104.3 | AD8: 104.6 | AE8: 106
A9: Urban | B9: 2013 | C9: March | D9: =B9&" "&C9 -> 2013 March | E9: 113.9 | F9: 111.4 | G9: 113.2 | H9: 104.3 | I9: 102.7 | J9: 104.9 | K9: 103.8 | L9: 103.5 | M9: 102.6 | N9: 102.4 | O9: 107 | P9: 109.8 | Q9: 107.3 | R9: 106.8 | S9: 107.2 | T9: 106 | U9: 107 | V9: 100.4 | W9: 106 | X9: 105.7 | Y9: 105.2 | Z9: 105.5 | AA9: 103.5 | AB9: 103.8 | AC9: 104.2 | AD9: 104.9 | AE9: 105
A10: Rural+Urban | B10: 2013 | C10: March | D10: =B10&" "&C10 -> 2013 March | E10: 111.4 | F10: 109.7 | G10: 111.2 | H10: 105.1 | I10: 104.9 | J10: 105.3 | K10: 102.2 | L10: 105 | M10: 104.2 | N10: 103 | O10: 106.2 | P10: 108.9 | Q10: 106.9 | R10: 106.6 | S10: 107.4 | T10: 106.5 | U10: 107.3 | V10: 100.4 | W10: 106.1 | X10: 105.6 | Y10: 104.9 | Z10: 105.1 | AA10: 103.7 | AB10: 104 | AC10: 104.3 | AD10: 104.7 | AE10: 105.5
A11: Rural | B11: 2013 | C11: April | D11: =B11&" "&C11 -> 2013 April | E11: 110.2 | F11: 109.5 | G11: 106.9 | H11: 106.3 | I11: 105.7 | J11: 108.3 | K11: 103.4 | L11: 105.7 | M11: 104.2 | N11: 103.2 | O11: 106.5 | P11: 108.8 | Q11: 107.1 | R11: 107.1 | S11: 108.1 | T11: 107.4 | U11: 108 | V11: NA | W11: 106.5 | X11: 106.1 | Y11: 105.1 | Z11: 104.4 | AA11: 104.5 | AB11: 104.8 | AC11: 102.7 | AD11: 104.6 | AE11: 106.4
A12: Urban | B12: 2013 | C12: April | D12: =B12&" "&C12 -> 2013 April | E12: 114.6 | F12: 113.4 | G12: 106 | H12: 104.7 | I12: 102.1 | J12: 109.5 | K12: 109.7 | L12: 104.6 | M12: 102 | N12: 103.5 | O12: 108.2 | P12: 110.6 | Q12: 108.8 | R12: 108.5 | S12: 107.9 | T12: 106.4 | U12: 107.7 | V12: 100.5 | W12: 106.4 | X12: 106.5 | Y12: 105.7 | Z12: 105 | AA12: 104 | AB12: 105.2 | AC12: 103.2 | AD12: 105.1 | AE12: 105.7
A13: Rural+Urban | B13: 2013 | C13: April | D13: =B13&" "&C13 -> 2013 April | E13: 111.6 | F13: 110.9 | G13: 106.6 | H13: 105.7 | I13: 104.4 | J13: 108.9 | K13: 105.5 | L13: 105.3 | M13: 103.5 | N13: 103.3 | O13: 107.2 | P13: 109.6 | Q13: 107.7 | R13: 107.5 | S13: 108 | T13: 107 | U13: 107.9 | V13: 100.5 | W13: 106.5 | X13: 106.3 | Y13: 105.3 | Z13: 104.7 | AA13: 104.2 | AB13: 105 | AC13: 102.9 | AD13: 104.8 | AE13: 106.1
A14: Rural | B14: 2013 | C14: May | D14: =B14&" "&C14 -> 2013 May | E14: 110.9 | F14: 109.8 | G14: 105.9 | H14: 107.5 | I14: 105.3 | J14: 108.1 | K14: 107.3 | L14: 106.1 | M14: 103.7 | N14: 104 | O14: 107.4 | P14: 109.9 | Q14: 108.1 | R14: 108.1 | S14: 108.8 | T14: 107.9 | U14: 108.6 | V14: NA | W14: 107.5 | X14: 106.8 | Y14: 105.7 | Z14: 104.1 | AA14: 105 | AB14: 105.5 | AC14: 102.1 | AD14: 104.8 | AE14: 107.2
A15: Urban | B15: 2013 | C15: May | D15: =B15&" "&C15 -> 2013 May | E15: 115.4 | F15: 114.2 | G15: 102.7 | H15: 105.5 | I15: 101.5 | J15: 110.6 | K15: 123.7 | L15: 105.2 | M15: 101.9 | N15: 105 | O15: 109.1 | P15: 111.3 | Q15: 111.1 | R15: 109.8 | S15: 108.5 | T15: 106.7 | U15: 108.3 | V15: 100.5 | W15: 107.2 | X15: 107.1 | Y15: 106.2 | Z15: 103.9 | AA15: 104.6 | AB15: 105.7 | AC15: 102.6 | AD15: 104.9 | AE15: 106.6
A16: Rural+Urban | B16: 2013 | C16: May | D16: =B16&" "&C16 -> 2013 May | E16: 112.3 | F16: 111.3 | G16: 104.7 | H16: 106.8 | I16: 103.9 | J16: 109.3 | K16: 112.9 | L16: 105.8 | M16: 103.1 | N16: 104.3 | O16: 108.1 | P16: 110.5 | Q16: 109.2 | R16: 108.6 | S16: 108.7 | T16: 107.4 | U16: 108.5 | V16: 100.5 | W16: 107.4 | X16: 106.9 | Y16: 105.9 | Z16: 104 | AA16: 104.8 | AB16: 105.6 | AC16: 102.3 | AD16: 104.8 | AE16: 106.9
A17: Rural | B17: 2013 | C17: June | D17: =B17&" "&C17 -> 2013 June | E17: 112.3 | F17: 112.1 | G17: 108.1 | H17: 108.3 | I17: 105.9 | J17: 109.2 | K17: 118 | L17: 106.8 | M17: 104.1 | N17: 105.4 | O17: 108.2 | P17: 111 | Q17: 110.6 | R17: 109 | S17: 109.7 | T17: 108.8 | U17: 109.5 | V17: NA | W17: 108.5 | X17: 107.5 | Y17: 106.3 | Z17: 105 | AA17: 105.6 | AB17: 106.5 | AC17: 102.5 | AD17: 105.5 | AE17: 108.9
A18: Urban | B18: 2013 | C18: June | D18: =B18&" "&C18 -> 2013 June | E18: 117 | F18: 120.1 | G18: 112.5 | H18: 107.3 | I18: 101.3 | J18: 112.4 | K18: 143.6 | L18: 105.4 | M18: 101.4 | N18: 106.4 | O18: 110 | P18: 112.2 | Q18: 115 | R18: 110.9 | S18: 109.2 | T18: 107.2 | U18: 108.9 | V18: 106.6 | W18: 108 | X18: 107.7 | Y18: 106.5 | Z18: 105.2 | AA18: 105.2 | AB18: 108.1 | AC18: 103.3 | AD18: 106.1 | AE18: 109.7
A19: Rural+Urban | B19: 2013 | C19: June | D19: =B19&" "&C19 -> 2013 June | E19: 113.8 | F19: 114.9 | G19: 109.8 | H19: 107.9 | I19: 104.2 | J19: 110.7 | K19: 126.7 | L19: 106.3 | M19: 103.2 | N19: 105.7 | O19: 109 | P19: 111.6 | Q19: 112.2 | R19: 109.5 | S19: 109.5 | T19: 108.1 | U19: 109.3 | V19: 106.6 | W19: 108.3 | X19: 107.6 | Y19: 106.4 | Z19: 105.1 | AA19: 105.4 | AB19: 107.4 | AC19: 102.8 | AD19: 105.8 | AE19: 109.3
A20: Rural | B20: 2013 | C20: July | D20: =B20&" "&C20 -> 2013 July | E20: 113.4 | F20: 114.9 | G20: 110.5 | H20: 109.3 | I20: 106.2 | J20: 110.3 | K20: 129.2 | L20: 107.1 | M20: 104.3 | N20: 106.4 | O20: 109.1 | P20: 112.1 | Q20: 113.1 | R20: 109.8 | S20: 110.5 | T20: 109.5 | U20: 110.3 | V20: NA | W20: 109.5 | X20: 108.3 | Y20: 106.9 | Z20: 106.8 | AA20: 106.4 | AB20: 107.8 | AC20: 102.5 | AD20: 106.5 | AE20: 110.7
A21: Urban | B21: 2013 | C21: July | D21: =B21&" "&C21 -> 2013 July | E21: 117.8 | F21: 119.2 | G21: 114 | H21: 108.3 | I21: 101.1 | J21: 113.2 | K21: 160.9 | L21: 105.1 | M21: 101.3 | N21: 107.5 | O21: 110.4 | P21: 113.1 | Q21: 117.5 | R21: 111.7 | S21: 109.8 | T21: 107.8 | U21: 109.5 | V21: 107.7 | W21: 108.6 | X21: 108.1 | Y21: 107.1 | Z21: 107.3 | AA21: 105.9 | AB21: 110.1 | AC21: 103.2 | AD21: 107.3 | AE21: 111.4
A22: Rural+Urban | B22: 2013 | C22: July | D22: =B22&" "&C22 -> 2013 July | E22: 114.8 | F22: 116.4 | G22: 111.9 | H22: 108.9 | I22: 104.3 | J22: 111.7 | K22: 140 | L22: 106.4 | M22: 103.3 | N22: 106.8 | O22: 109.6 | P22: 112.6 | Q22: 114.7 | R22: 110.3 | S22: 110.2 | T22: 108.8 | U22: 110 | V22: 107.7 | W22: 109.2 | X22: 108.2 | Y22: 107 | Z22: 107.1 | AA22: 106.1 | AB22: 109.1 | AC22: 102.8 | AD22: 106.9 | AE22: 111
A23: Rural | B23: 2013 | C23: August | D23: =B23&" "&C23 -> 2013 August | E23: 114.3 | F23: 115.4 | G23: 111.1 | H23: 110 | I23: 106.4 | J23: 110.8 | K23: 138.9 | L23: 107.4 | M23: 104.1 | N23: 106.9 | O23: 109.7 | P23: 112.6 | Q23: 114.9 | R23: 110.7 | S23: 111.3 | T23: 110.2 | U23: 111.1 | V23: NA | W23: 109.9 | X23: 108.7 | Y23: 107.5 | Z23: 107.8 | AA23: 106.8 | AB23: 108.7 | AC23: 105 | AD23: 107.5 | AE23: 112.1
A24: Urban | B24: 2013 | C24: August | D24: =B24&" "&C24 -> 2013 August | E24: 118.3 | F24: 120.4 | G24: 112.7 | H24: 108.9 | I24: 101.1 | J24: 108.7 | K24: 177 | L24: 104.7 | M24: 101 | N24: 108.5 | O24: 110.9 | P24: 114.3 | Q24: 119.6 | R24: 112.4 | S24: 110.6 | T24: 108.3 | U24: 110.2 | V24: 108.9 | W24: 109.3 | X24: 108.7 | Y24: 107.6 | Z24: 108.1 | AA24: 106.5 | AB24: 110.8 | AC24: 106 | AD24: 108.3 | AE24: 112.7
A25: Rural+Urban | B25: 2013 | C25: August | D25: =B25&" "&C25 -> 2013 August | E25: 115.6 | F25: 117.2 | G25: 111.7 | H25: 109.6 | I25: 104.5 | J25: 109.8 | K25: 151.8 | L25: 106.5 | M25: 103.1 | N25: 107.4 | O25: 110.2 | P25: 113.4 | Q25: 116.6 | R25: 111.2 | S25: 111 | T25: 109.4 | U25: 110.7 | V25: 108.9 | W25: 109.7 | X25: 108.7 | Y25: 107.5 | Z25: 108 | AA25: 106.6 | AB25: 109.9 | AC25: 105.4 | AD25: 107.9 | AE25: 112.4
A26: Rural | B26: 2013 | C26: September | D26: =B26&" "&C26 -> 2013 September | E26: 115.4 | F26: 115.7 | G26: 111.7 | H26: 111 | I26: 107.4 | J26: 110.9 | K26: 154 | L26: 108.1 | M26: 104.2 | N26: 107.9 | O26: 110.4 | P26: 114 | Q26: 117.8 | R26: 111.7 | S26: 112.7 | T26: 111.4 | U26: 112.5 | V26: NA | W26: 111.1 | X26: 109.6 | Y26: 108.3 | Z26: 109.3 | AA26: 107.7 | AB26: 109.8 | AC26: 106.7 | AD26: 108.7 | AE26: 114.2
A27: Urban | B27: 2013 | C27: September | D27: =B27&" "&C27 -> 2013 September | E27: 118.6 | F27: 119.1 | G27: 113.2 | H27: 109.6 | I27: 101.7 | J27: 103.2 | K27: 174.3 | L27: 105.1 | M27: 100.8 | N27: 109.1 | O27: 111.1 | P27: 115.4 | Q27: 119.2 | R27: 112.9 | S27: 111.4 | T27: 109 | U27: 111.1 | V27: 109.7 | W27: 109.5 | X27: 109.6 | Y27: 107.9 | Z27: 110.4 | AA27: 107.4 | AB27: 111.2 | AC27: 106.9 | AD27: 109.4 | AE27: 113.2
A28: Rural+Urban | B28: 2013 | C28: September | D28: =B28&" "&C28 -> 2013 September | E28: 116.4 | F28: 116.9 | G28: 112.3 | H28: 110.5 | I28: 105.3 | J28: 107.3 | K28: 160.9 | L28: 107.1 | M28: 103.1 | N28: 108.3 | O28: 110.7 | P28: 114.6 | Q28: 118.3 | R28: 112 | S28: 112.2 | T28: 110.4 | U28: 111.9 | V28: 109.7 | W28: 110.5 | X28: 109.6 | Y28: 108.1 | Z28: 109.9 | AA28: 107.5 | AB28: 110.6 | AC28: 106.8 | AD28: 109 | AE28: 113.7
A29: Rural | B29: 2013 | C29: October | D29: =B29&" "&C29 -> 2013 October | E29: 116.3 | F29: 115.4 | G29: 112.6 | H29: 111.7 | I29: 107.7 | J29: 113.2 | K29: 164.9 | L29: 108.3 | M29: 103.9 | N29: 108.2 | O29: 111.1 | P29: 114.9 | Q29: 119.8 | R29: 112.2 | S29: 113.6 | T29: 112.3 | U29: 113.4 | V29: NA | W29: 111.6 | X29: 110.4 | Y29: 108.9 | Z29: 109.3 | AA29: 108.3 | AB29: 110.2 | AC29: 107.5 | AD29: 109.1 | AE29: 115.5
A30: Urban | B30: 2013 | C30: October | D30: =B30&" "&C30 -> 2013 October | E30: 118.9 | F30: 118.1 | G30: 114.5 | H30: 110.4 | I30: 102.3 | J30: 106.2 | K30: 183.5 | L30: 105.3 | M30: 100.2 | N30: 109.6 | O30: 111.4 | P30: 116 | Q30: 120.8 | R30: 113.5 | S30: 112.5 | T30: 109.7 | U30: 112 | V30: 110.5 | W30: 109.7 | X30: 110.2 | Y30: 108.2 | Z30: 109.7 | AA30: 108 | AB30: 111.3 | AC30: 107.3 | AD30: 109.4 | AE30: 114
A31: Rural+Urban | B31: 2013 | C31: October | D31: =B31&" "&C31 -> 2013 October | E31: 117.1 | F31: 116.3 | G31: 113.3 | H31: 111.2 | I31: 105.7 | J31: 109.9 | K31: 171.2 | L31: 107.3 | M31: 102.7 | N31: 108.7 | O31: 111.2 | P31: 115.4 | Q31: 120.2 | R31: 112.5 | S31: 113.2 | T31: 111.2 | U31: 112.8 | V31: 110.5 | W31: 110.9 | X31: 110.3 | Y31: 108.6 | Z31: 109.5 | AA31: 108.1 | AB31: 110.8 | AC31: 107.4 | AD31: 109.2 | AE31: 114.8
A32: Rural | B32: 2013 | C32: November | D32: =B32&" "&C32 -> 2013 November | E32: 117.3 | F32: 114.9 | G32: 116.2 | H32: 112.8 | I32: 108.9 | J32: 116.6 | K32: 178.1 | L32: 109.1 | M32: 103.6 | N32: 109 | O32: 111.8 | P32: 116 | Q32: 122.5 | R32: 112.8 | S32: 114.6 | T32: 113.1 | U32: 114.4 | V32: NA | W32: 112.6 | X32: 111.3 | Y32: 109.7 | Z32: 109.6 | AA32: 108.7 | AB32: 111 | AC32: 108.2 | AD32: 109.8 | AE32: 117.4
A33: Urban | B33: 2013 | C33: November | D33: =B33&" "&C33 -> 2013 November | E33: 119.8 | F33: 116.3 | G33: 122.6 | H33: 112 | I33: 103.2 | J33: 110 | K33: 192.8 | L33: 106.3 | M33: 99.5 | N33: 110.3 | O33: 111.8 | P33: 117.1 | Q33: 122.9 | R33: 114.1 | S33: 113.5 | T33: 110.3 | U33: 113 | V33: 111.1 | W33: 110 | X33: 110.9 | Y33: 108.6 | Z33: 109.5 | AA33: 108.5 | AB33: 111.3 | AC33: 107.9 | AD33: 109.6 | AE33: 115
A34: Rural+Urban | B34: 2013 | C34: November | D34: =B34&" "&C34 -> 2013 November | E34: 118.1 | F34: 115.4 | G34: 118.7 | H34: 112.5 | I34: 106.8 | J34: 113.5 | K34: 183.1 | L34: 108.2 | M34: 102.2 | N34: 109.4 | O34: 111.8 | P34: 116.5 | Q34: 122.6 | R34: 113.1 | S34: 114.2 | T34: 111.9 | U34: 113.8 | V34: 111.1 | W34: 111.6 | X34: 111.1 | Y34: 109.3 | Z34: 109.5 | AA34: 108.6 | AB34: 111.2 | AC34: 108.1 | AD34: 109.7 | AE34: 116.3
A35: Rural | B35: 2013 | C35: December | D35: =B35&" "&C35 -> 2013 December | E35: 118.4 | F35: 115.9 | G35: 120.4 | H35: 113.8 | I35: 109.5 | J35: 115.5 | K35: 145.7 | L35: 109.5 | M35: 102.9 | N35: 109.8 | O35: 112.1 | P35: 116.8 | Q35: 118.7 | R35: 113.6 | S35: 115.8 | T35: 114 | U35: 115.5 | V35: NA | W35: 112.8 | X35: 112.1 | Y35: 110.1 | Z35: 109.9 | AA35: 109.2 | AB35: 111.6 | AC35: 108.1 | AD35: 110.1 | AE35: 115.5
A36: Urban | B36: 2013 | C36: December | D36: =B36&" "&C36 -> 2013 December | E36: 120.5 | F36: 118.1 | G36: 128.5 | H36: 112.8 | I36: 103.4 | J36: 110.7 | K36: 144.8 | L36: 107.1 | M36: 98.6 | N36: 111.9 | O36: 112.1 | P36: 118.1 | Q36: 117.8 | R36: 115 | S36: 114.2 | T36: 110.9 | U36: 113.7 | V36: 110.7 | W36: 110.4 | X36: 111.3 | Y36: 109 | Z36: 109.7 | AA36: 108.9 | AB36: 111.4 | AC36: 107.7 | AD36: 109.8 | AE36: 113.3
A37: Rural+Urban | B37: 2013 | C37: December | D37: =B37&" "&C37 -> 2013 December | E37: 119.1 | F37: 116.7 | G37: 123.5 | H37: 113.4 | I37: 107.3 | J37: 113.3 | K37: 145.4 | L37: 108.7 | M37: 101.5 | N37: 110.5 | O37: 112.1 | P37: 117.4 | Q37: 118.4 | R37: 114 | S37: 115.2 | T37: 112.7 | U37: 114.8 | V37: 110.7 | W37: 111.9 | X37: 111.7 | Y37: 109.7 | Z37: 109.8 | AA37: 109 | AB37: 111.5 | AC37: 107.9 | AD37: 110 | AE37: 114.5
A38: Rural | B38: 2014 | C38: January | D38: =B38&" "&C38 -> 2014 January | E38: 118.9 | F38: 117.1 | G38: 120.5 | H38: 114.4 | I38: 109 | J38: 115.5 | K38: 123.9 | L38: 109.6 | M38: 101.8 | N38: 110.2 | O38: 112.4 | P38: 117.3 | Q38: 116 | R38: 114 | S38: 116.5 | T38: 114.5 | U38: 116.2 | V38: NA | W38: 113 | X38: 112.6 | Y38: 110.6 | Z38: 110.5 | AA38: 109.6 | AB38: 111.8 | AC38: 108.3 | AD38: 110.6 | AE38: 114.2
A39: Urban | B39: 2014 | C39: January | D39: =B39&" "&C39 -> 2014 January | E39: 121.2 | F39: 122 | G39: 129.9 | H39: 113.6 | I39: 102.9 | J39: 112.1 | K39: 118.9 | L39: 107.5 | M39: 96.9 | N39: 112.7 | O39: 112.1 | P39: 119 | Q39: 115.5 | R39: 115.7 | S39: 114.8 | T39: 111.3 | U39: 114.3 | V39: 111.6 | W39: 111 | X39: 111.9 | Y39: 109.7 | Z39: 110.8 | AA39: 109.8 | AB39: 111.5 | AC39: 108 | AD39: 110.5 | AE39: 112.9
A40: Rural+Urban | B40: 2014 | C40: January | D40: =B40&" "&C40 -> 2014 January | E40: 119.6 | F40: 118.8 | G40: 124.1 | H40: 114.1 | I40: 106.8 | J40: 113.9 | K40: 122.2 | L40: 108.9 | M40: 100.2 | N40: 111 | O40: 112.3 | P40: 118.1 | Q40: 115.8 | R40: 114.5 | S40: 115.8 | T40: 113.2 | U40: 115.4 | V40: 111.6 | W40: 112.2 | X40: 112.3 | Y40: 110.3 | Z40: 110.7 | AA40: 109.7 | AB40: 111.6 | AC40: 108.2 | AD40: 110.6 | AE40: 113.6
A41: Rural | B41: 2014 | C41: February | D41: =B41&" "&C41 -> 2014 February | E41: 119.4 | F41: 117.7 | G41: 121.2 | H41: 115 | I41: 109 | J41: 116.6 | K41: 116 | L41: 109.8 | M41: 101.1 | N41: 110.4 | O41: 112.9 | P41: 117.8 | Q41: 115.3 | R41: 114.2 | S41: 117.1 | T41: 114.5 | U41: 116.7 | V41: NA | W41: 113.2 | X41: 112.9 | Y41: 110.9 | Z41: 110.8 | AA41: 109.9 | AB41: 112 | AC41: 108.7 | AD41: 110.9 | AE41: 114
A42: Urban | B42: 2014 | C42: February | D42: =B42&" "&C42 -> 2014 February | E42: 121.9 | F42: 122 | G42: 124.5 | H42: 115.2 | I42: 102.5 | J42: 114.1 | K42: 111.5 | L42: 108.2 | M42: 95.4 | N42: 113.5 | O42: 112.1 | P42: 119.9 | Q42: 115.2 | R42: 116.2 | S42: 115.3 | T42: 111.7 | U42: 114.7 | V42: 112.5 | W42: 111.1 | X42: 112.6 | Y42: 110.4 | Z42: 111.3 | AA42: 110.3 | AB42: 111.6 | AC42: 108.7 | AD42: 111 | AE42: 113.1
A43: Rural+Urban | B43: 2014 | C43: February | D43: =B43&" "&C43 -> 2014 February | E43: 120.2 | F43: 119.2 | G43: 122.5 | H43: 115.1 | I43: 106.6 | J43: 115.4 | K43: 114.5 | L43: 109.3 | M43: 99.2 | N43: 111.4 | O43: 112.6 | P43: 118.8 | Q43: 115.3 | R43: 114.7 | S43: 116.4 | T43: 113.3 | U43: 115.9 | V43: 112.5 | W43: 112.4 | X43: 112.8 | Y43: 110.7 | Z43: 111.1 | AA43: 110.1 | AB43: 111.8 | AC43: 108.7 | AD43: 110.9 | AE43: 113.6
A44: Rural | B44: 2014 | C44: March | D44: =B44&" "&C44 -> 2014 March | E44: 120.1 | F44: 118.1 | G44: 120.7 | H44: 116.1 | I44: 109.3 | J44: 119.6 | K44: 117.9 | L44: 110.2 | M44: 101.2 | N44: 110.7 | O44: 113 | P44: 118.3 | Q44: 116.2 | R44: 114.6 | S44: 117.5 | T44: 114.9 | U44: 117.2 | V44: NA | W44: 113.4 | X44: 113.4 | Y44: 111.4 | Z44: 111.2 | AA44: 110.2 | AB44: 112.4 | AC44: 108.9 | AD44: 111.3 | AE44: 114.6
A45: Urban | B45: 2014 | C45: March | D45: =B45&" "&C45 -> 2014 March | E45: 122.1 | F45: 121.4 | G45: 121.5 | H45: 116.2 | I45: 102.8 | J45: 117.7 | K45: 113.3 | L45: 108.9 | M45: 96.3 | N45: 114.1 | O45: 112.2 | P45: 120.5 | Q45: 116 | R45: 116.7 | S45: 115.8 | T45: 112.1 | U45: 115.2 | V45: 113.2 | W45: 110.9 | X45: 113 | Y45: 110.8 | Z45: 111.6 | AA45: 110.9 | AB45: 111.8 | AC45: 109.2 | AD45: 111.4 | AE45: 113.7
A46: Rural+Urban | B46: 2014 | C46: Marcrh | D46: =B46&" "&C46 -> 2014 Marcrh | E46: 120.7 | F46: 119.3 | G46: 121 | H46: 116.1 | I46: 106.9 | J46: 118.7 | K46: 116.3 | L46: 109.8 | M46: 99.6 | N46: 111.8 | O46: 112.7 | P46: 119.3 | Q46: 116.1 | R46: 115.2 | S46: 116.8 | T46: 113.7 | U46: 116.4 | V46: 113.2 | W46: 112.5 | X46: 113.2 | Y46: 111.2 | Z46: 111.4 | AA46: 110.6 | AB46: 112 | AC46: 109 | AD46: 111.3 | AE46: 114.2
A47: Rural | B47: 2014 | C47: April | D47: =B47&" "&C47 -> 2014 April | E47: 120.2 | F47: 118.9 | G47: 118.1 | H47: 117 | I47: 109.7 | J47: 125.5 | K47: 120.5 | L47: 111 | M47: 102.6 | N47: 111.2 | O47: 113.5 | P47: 118.7 | Q47: 117.2 | R47: 115.4 | S47: 118.1 | T47: 116.1 | U47: 117.8 | V47: NA | W47: 113.4 | X47: 113.7 | Y47: 111.8 | Z47: 111.2 | AA47: 110.5 | AB47: 113 | AC47: 108.9 | AD47: 111.5 | AE47: 115.4
A48: Urban | B48: 2014 | C48: April | D48: =B48&" "&C48 -> 2014 April | E48: 122.5 | F48: 121.7 | G48: 113.3 | H48: 117 | I48: 103.1 | J48: 126.7 | K48: 121.2 | L48: 111 | M48: 100.3 | N48: 115.3 | O48: 112.7 | P48: 121 | Q48: 118.2 | R48: 117.6 | S48: 116.3 | T48: 112.5 | U48: 115.7 | V48: 113.9 | W48: 110.9 | X48: 113.4 | Y48: 111 | Z48: 111.2 | AA48: 111.2 | AB48: 112.5 | AC48: 109.1 | AD48: 111.4 | AE48: 114.7
A49: Rural+Urban | B49: 2014 | C49: April | D49: =B49&" "&C49 -> 2014 April | E49: 120.9 | F49: 119.9 | G49: 116.2 | H49: 117 | I49: 107.3 | J49: 126.1 | K49: 120.7 | L49: 111 | M49: 101.8 | N49: 112.6 | O49: 113.2 | P49: 119.8 | Q49: 117.6 | R49: 116 | S49: 117.4 | T49: 114.6 | U49: 117 | V49: 113.9 | W49: 112.5 | X49: 113.6 | Y49: 111.5 | Z49: 111.2 | AA49: 110.9 | AB49: 112.7 | AC49: 109 | AD49: 111.5 | AE49: 115.1
A50: Rural | B50: 2014 | C50: May | D50: =B50&" "&C50 -> 2014 May | E50: 120.3 | F50: 120.2 | G50: 116.9 | H50: 118 | I50: 110.1 | J50: 126.3 | K50: 123.9 | L50: 111.5 | M50: 103.5 | N50: 111.6 | O50: 114.2 | P50: 119.2 | Q50: 118.2 | R50: 116.3 | S50: 118.7 | T50: 116.8 | U50: 118.5 | V50: NA | W50: 113.4 | X50: 114.1 | Y50: 112.1 | Z50: 111.4 | AA50: 110.9 | AB50: 113.1 | AC50: 108.9 | AD50: 111.8 | AE50: 116
A51: Urban | B51: 2014 | C51: May | D51: =B51&" "&C51 -> 2014 May | E51: 122.7 | F51: 124.1 | G51: 114.2 | H51: 119.1 | I51: 103.5 | J51: 129.2 | K51: 127 | L51: 112.6 | M51: 101.3 | N51: 117 | O51: 112.9 | P51: 121.7 | Q51: 120 | R51: 118.3 | S51: 116.8 | T51: 112.9 | U51: 116.2 | V51: 114.3 | W51: 111.1 | X51: 114.1 | Y51: 111.2 | Z51: 111.3 | AA51: 111.5 | AB51: 112.9 | AC51: 109.3 | AD51: 111.7 | AE51: 115.6
A52: Rural+Urban | B52: 2014 | C52: May | D52: =B52&" "&C52 -> 2014 May | E52: 121.1 | F52: 121.6 | G52: 115.9 | H52: 118.4 | I52: 107.7 | J52: 127.7 | K52: 125 | L52: 111.9 | M52: 102.8 | N52: 113.4 | O52: 113.7 | P52: 120.4 | Q52: 118.9 | R52: 116.8 | S52: 118 | T52: 115.2 | U52: 117.6 | V52: 114.3 | W52: 112.5 | X52: 114.1 | Y52: 111.8 | Z52: 111.3 | AA52: 111.2 | AB52: 113 | AC52: 109.1 | AD52: 111.8 | AE52: 115.8
A53: Rural | B53: 2014 | C53: June | D53: =B53&" "&C53 -> 2014 June | E53: 120.7 | F53: 121.6 | G53: 116.1 | H53: 119.3 | I53: 110.3 | J53: 125.8 | K53: 129.3 | L53: 112.2 | M53: 103.6 | N53: 112.3 | O53: 114.9 | P53: 120.1 | Q53: 119.5 | R53: 117.3 | S53: 119.7 | T53: 117.3 | U53: 119.3 | V53: NA | W53: 114.4 | X53: 114.9 | Y53: 112.8 | Z53: 112.2 | AA53: 111.4 | AB53: 114.3 | AC53: 108 | AD53: 112.3 | AE53: 117
A54: Urban | B54: 2014 | C54: June | D54: =B54&" "&C54 -> 2014 June | E54: 123.1 | F54: 125.9 | G54: 115.4 | H54: 120.4 | I54: 103.4 | J54: 131.2 | K54: 137.5 | L54: 112.8 | M54: 101.4 | N54: 118.3 | O54: 113.2 | P54: 122.4 | Q54: 122 | R54: 119 | S54: 117.4 | T54: 113.2 | U54: 116.7 | V54: 113.9 | W54: 111.2 | X54: 114.3 | Y54: 111.4 | Z54: 111.5 | AA54: 111.8 | AB54: 115.1 | AC54: 108.7 | AD54: 112.2 | AE54: 116.4
A55: Rural+Urban | B55: 2014 | C55: June | D55: =B55&" "&C55 -> 2014 June | E55: 121.5 | F55: 123.1 | G55: 115.8 | H55: 119.7 | I55: 107.8 | J55: 128.3 | K55: 132.1 | L55: 112.4 | M55: 102.9 | N55: 114.3 | O55: 114.2 | P55: 121.2 | Q55: 120.4 | R55: 117.8 | S55: 118.8 | T55: 115.6 | U55: 118.3 | V55: 113.9 | W55: 113.2 | X55: 114.6 | Y55: 112.3 | Z55: 111.8 | AA55: 111.6 | AB55: 114.8 | AC55: 108.3 | AD55: 112.3 | AE55: 116.7
A56: Rural | B56: 2014 | C56: July | D56: =B56&" "&C56 -> 2014 July | E56: 121.7 | F56: 122.5 | G56: 117.7 | H56: 120.6 | I56: 110.4 | J56: 129.1 | K56: 150.1 | L56: 113.2 | M56: 104.8 | N56: 113.3 | O56: 115.6 | P56: 120.9 | Q56: 123.3 | R56: 118 | S56: 120.7 | T56: 118.3 | U56: 120.3 | V56: NA | W56: 115.3 | X56: 115.4 | Y56: 113.4 | Z56: 113.2 | AA56: 111.8 | AB56: 115.5 | AC56: 108.8 | AD56: 113.1 | AE56: 119.5
A57: Urban | B57: 2014 | C57: July | D57: =B57&" "&C57 -> 2014 July | E57: 123.8 | F57: 126.4 | G57: 118 | H57: 121.6 | I57: 103.5 | J57: 133.7 | K57: 172.4 | L57: 113.1 | M57: 102.7 | N57: 120 | O57: 113.8 | P57: 123.4 | Q57: 127.1 | R57: 121 | S57: 118 | T57: 113.6 | U57: 117.4 | V57: 114.8 | W57: 111.6 | X57: 114.9 | Y57: 111.5 | Z57: 113 | AA57: 112.4 | AB57: 117.8 | AC57: 109.7 | AD57: 113.5 | AE57: 118.9
A58: Rural+Urban | B58: 2014 | C58: July | D58: =B58&" "&C58 -> 2014 July | E58: 122.4 | F58: 123.9 | G58: 117.8 | H58: 121 | I58: 107.9 | J58: 131.2 | K58: 157.7 | L58: 113.2 | M58: 104.1 | N58: 115.5 | O58: 114.8 | P58: 122.1 | Q58: 124.7 | R58: 118.8 | S58: 119.6 | T58: 116.3 | U58: 119.1 | V58: 114.8 | W58: 113.9 | X58: 115.2 | Y58: 112.7 | Z58: 113.1 | AA58: 112.1 | AB58: 116.8 | AC58: 109.2 | AD58: 113.3 | AE58: 119.2
A59: Rural | B59: 2014 | C59: August | D59: =B59&" "&C59 -> 2014 August | E59: 121.8 | F59: 122.8 | G59: 117.8 | H59: 121.9 | I59: 110.6 | J59: 129.7 | K59: 161.1 | L59: 114.1 | M59: 105.1 | N59: 114.6 | O59: 115.8 | P59: 121.7 | Q59: 125.3 | R59: 118.8 | S59: 120.9 | T59: 118.8 | U59: 120.7 | V59: NA | W59: 115.4 | X59: 115.9 | Y59: 114 | Z59: 113.2 | AA59: 112.2 | AB59: 116.2 | AC59: 109.4 | AD59: 113.5 | AE59: 120.7
A60: Urban | B60: 2014 | C60: August | D60: =B60&" "&C60 -> 2014 August | E60: 124.8 | F60: 127.3 | G60: 116.5 | H60: 122.2 | I60: 103.6 | J60: 132.7 | K60: 181.9 | L60: 115.2 | M60: 102.7 | N60: 122.1 | O60: 114.4 | P60: 124.7 | Q60: 128.9 | R60: 123 | S60: 118.6 | T60: 114.1 | U60: 117.9 | V60: 115.5 | W60: 111.8 | X60: 115.3 | Y60: 112.2 | Z60: 112.5 | AA60: 112.9 | AB60: 119.2 | AC60: 110.5 | AD60: 113.9 | AE60: 119.9
A61: Rural+Urban | B61: 2014 | C61: August | D61: =B61&" "&C61 -> 2014 August | E61: 122.7 | F61: 124.4 | G61: 117.3 | H61: 122 | I61: 108 | J61: 131.1 | K61: 168.2 | L61: 114.5 | M61: 104.3 | N61: 117.1 | O61: 115.2 | P61: 123.1 | Q61: 126.6 | R61: 119.9 | S61: 120 | T61: 116.8 | U61: 119.6 | V61: 115.5 | W61: 114 | X61: 115.6 | Y61: 113.3 | Z61: 112.8 | AA61: 112.6 | AB61: 118 | AC61: 109.9 | AD61: 113.7 | AE61: 120.3
A62: Rural | B62: 2014 | C62: September | D62: =B62&" "&C62 -> 2014 September | E62: 122.3 | F62: 122.4 | G62: 117.8 | H62: 122.7 | I62: 110.4 | J62: 129.8 | K62: 158.8 | L62: 115 | M62: 104.7 | N62: 114.9 | O62: 116.5 | P62: 122.6 | Q62: 125.3 | R62: 119.5 | S62: 121.7 | T62: 119.2 | U62: 121.3 | V62: NA | W62: 115.8 | X62: 116.7 | Y62: 114.5 | Z62: 112.8 | AA62: 112.6 | AB62: 116.6 | AC62: 109.1 | AD62: 113.7 | AE62: 120.9
A63: Urban | B63: 2014 | C63: September | D63: =B63&" "&C63 -> 2014 September | E63: 124.2 | F63: 125.4 | G63: 116.4 | H63: 122.7 | I63: 103.5 | J63: 124.5 | K63: 168.6 | L63: 116.9 | M63: 101.9 | N63: 122.9 | O63: 114.8 | P63: 125.2 | Q63: 126.7 | R63: 124.3 | S63: 119.2 | T63: 114.5 | U63: 118.4 | V63: 116.1 | W63: 111.8 | X63: 115.5 | Y63: 112.3 | Z63: 111.2 | AA63: 113.4 | AB63: 120 | AC63: 110 | AD63: 113.6 | AE63: 119.2
A64: Rural+Urban | B64: 2014 | C64: September | D64: =B64&" "&C64 -> 2014 September | E64: 122.9 | F64: 123.5 | G64: 117.3 | H64: 122.7 | I64: 107.9 | J64: 127.3 | K64: 162.1 | L64: 115.6 | M64: 103.8 | N64: 117.6 | O64: 115.8 | P64: 123.8 | Q64: 125.8 | R64: 120.8 | S64: 120.7 | T64: 117.2 | U64: 120.1 | V64: 116.1 | W64: 114.3 | X64: 116.1 | Y64: 113.7 | Z64: 112 | AA64: 113.1 | AB64: 118.6 | AC64: 109.5 | AD64: 113.7 | AE64: 120.1
A65: Rural | B65: 2014 | C65: October | D65: =B65&" "&C65 -> 2014 October | E65: 122.6 | F65: 122.5 | G65: 118.3 | H65: 123.2 | I65: 110.5 | J65: 128.9 | K65: 155.3 | L65: 115.5 | M65: 104 | N65: 115.3 | O65: 116.8 | P65: 123.2 | Q65: 125.1 | R65: 120 | S65: 122.7 | T65: 120.3 | U65: 122.3 | V65: NA | W65: 116.4 | X65: 117.5 | Y65: 115.3 | Z65: 112.6 | AA65: 113 | AB65: 116.9 | AC65: 109.3 | AD65: 114 | AE65: 121
A66: Urban | B66: 2014 | C66: October | D66: =B66&" "&C66 -> 2014 October | E66: 124.6 | F66: 126.1 | G66: 117.8 | H66: 123.1 | I66: 103.5 | J66: 123.5 | K66: 159.6 | L66: 117.4 | M66: 101.2 | N66: 123.8 | O66: 115.2 | P66: 125.9 | Q66: 125.8 | R66: 124.3 | S66: 119.6 | T66: 114.9 | U66: 118.9 | V66: 116.7 | W66: 112 | X66: 115.8 | Y66: 112.6 | Z66: 111 | AA66: 113.6 | AB66: 120.2 | AC66: 110.1 | AD66: 113.7 | AE66: 119.1
A67: Rural+Urban | B67: 2014 | C67: October | D67: =B67&" "&C67 -> 2014 October | E67: 123.2 | F67: 123.8 | G67: 118.1 | H67: 123.2 | I67: 107.9 | J67: 126.4 | K67: 156.8 | L67: 116.1 | M67: 103.1 | N67: 118.1 | O67: 116.1 | P67: 124.5 | Q67: 125.4 | R67: 121.1 | S67: 121.5 | T67: 118.1 | U67: 121 | V67: 116.7 | W67: 114.7 | X67: 116.7 | Y67: 114.3 | Z67: 111.8 | AA67: 113.3 | AB67: 118.8 | AC67: 109.6 | AD67: 113.9 | AE67: 120.1
A68: Rural | B68: 2014 | C68: November | D68: =B68&" "&C68 -> 2014 November | E68: 122.7 | F68: 122.6 | G68: 119.9 | H68: 124 | I68: 110.5 | J68: 128.8 | K68: 152 | L68: 116.2 | M68: 103.3 | N68: 115.8 | O68: 116.8 | P68: 124.5 | Q68: 124.9 | R68: 120.8 | S68: 123.3 | T68: 120.5 | U68: 122.9 | V68: NA | W68: 117.3 | X68: 118.1 | Y68: 115.9 | Z68: 112 | AA68: 113.3 | AB68: 117.2 | AC68: 108.8 | AD68: 114.1 | AE68: 121.1
A69: Urban | B69: 2014 | C69: November | D69: =B69&" "&C69 -> 2014 November | E69: 124.5 | F69: 125.6 | G69: 122.7 | H69: 124.6 | I69: 103.2 | J69: 122.2 | K69: 153.2 | L69: 119.3 | M69: 99.8 | N69: 124.6 | O69: 115.8 | P69: 126.9 | Q69: 125.4 | R69: 125.8 | S69: 120.3 | T69: 115.4 | U69: 119.5 | V69: 117.1 | W69: 112.6 | X69: 116.4 | Y69: 113 | Z69: 109.7 | AA69: 114 | AB69: 120.3 | AC69: 109.6 | AD69: 113.4 | AE69: 119
A70: Rural+Urban | B70: 2014 | C70: November | D70: =B70&" "&C70 -> 2014 November | E70: 123.3 | F70: 123.7 | G70: 121 | H70: 124.2 | I70: 107.8 | J70: 125.7 | K70: 152.4 | L70: 117.2 | M70: 102.1 | N70: 118.7 | O70: 116.4 | P70: 125.6 | Q70: 125.1 | R70: 122.1 | S70: 122.1 | T70: 118.4 | U70: 121.6 | V70: 117.1 | W70: 115.5 | X70: 117.3 | Y70: 114.8 | Z70: 110.8 | AA70: 113.7 | AB70: 119 | AC70: 109.1 | AD70: 113.8 | AE70: 120.1
A71: Rural | B71: 2014 | C71: December | D71: =B71&" "&C71 -> 2014 December | E71: 122.4 | F71: 122.4 | G71: 121.8 | H71: 124.2 | I71: 110.2 | J71: 128.6 | K71: 140.3 | L71: 116.3 | M71: 102 | N71: 116 | O71: 117.3 | P71: 124.8 | Q71: 123.3 | R71: 121.7 | S71: 123.8 | T71: 120.6 | U71: 123.3 | V71: NA | W71: 117.4 | X71: 118.2 | Y71: 116.2 | Z71: 111.5 | AA71: 113.3 | AB71: 117.7 | AC71: 109.4 | AD71: 114.2 | AE71: 120.3
A72: Urban | B72: 2014 | C72: December | D72: =B72&" "&C72 -> 2014 December | E72: 124 | F72: 124.7 | G72: 126.3 | H72: 124.9 | I72: 103 | J72: 122.3 | K72: 141 | L72: 120.1 | M72: 97.8 | N72: 125.4 | O72: 116.1 | P72: 127.6 | Q72: 124 | R72: 126.4 | S72: 120.7 | T72: 115.8 | U72: 120 | V72: 116.5 | W72: 113 | X72: 116.8 | Y72: 113.2 | Z72: 108.8 | AA72: 114.3 | AB72: 120.7 | AC72: 110.4 | AD72: 113.4 | AE72: 118.4
A73: Rural+Urban | B73: 2014 | C73: December | D73: =B73&" "&C73 -> 2014 December | E73: 122.9 | F73: 123.2 | G73: 123.5 | H73: 124.5 | I73: 107.6 | J73: 125.7 | K73: 140.5 | L73: 117.6 | M73: 100.6 | N73: 119.1 | O73: 116.8 | P73: 126.1 | Q73: 123.6 | R73: 123 | S73: 122.6 | T73: 118.6 | U73: 122 | V73: 116.5 | W73: 115.7 | X73: 117.5 | Y73: 115.1 | Z73: 110.1 | AA73: 113.9 | AB73: 119.5 | AC73: 109.8 | AD73: 113.8 | AE73: 119.4
A74: Rural | B74: 2015 | C74: January | D74: =B74&" "&C74 -> 2015 January | E74: 123.1 | F74: 123.1 | G74: 122.1 | H74: 124.9 | I74: 111 | J74: 130.4 | K74: 132.3 | L74: 117.2 | M74: 100.5 | N74: 117.2 | O74: 117.9 | P74: 125.6 | Q74: 122.8 | R74: 122.7 | S74: 124.4 | T74: 121.6 | U74: 124 | V74: NA | W74: 118.4 | X74: 118.9 | Y74: 116.6 | Z74: 111 | AA74: 114 | AB74: 118.2 | AC74: 110.2 | AD74: 114.5 | AE74: 120.3
A75: Urban | B75: 2015 | C75: January | D75: =B75&" "&C75 -> 2015 January | E75: 124 | F75: 125.5 | G75: 126.6 | H75: 125.2 | I75: 104.3 | J75: 121.3 | K75: 134.4 | L75: 122.9 | M75: 96.1 | N75: 126.6 | O75: 116.5 | P75: 128 | Q75: 123.5 | R75: 127.4 | S75: 121 | T75: 116.1 | U75: 120.2 | V75: 117.3 | W75: 113.4 | X75: 117.2 | Y75: 113.7 | Z75: 107.9 | AA75: 114.6 | AB75: 120.8 | AC75: 111.4 | AD75: 113.4 | AE75: 118.5
A76: Rural+Urban | B76: 2015 | C76: January | D76: =B76&" "&C76 -> 2015 January | E76: 123.4 | F76: 123.9 | G76: 123.8 | H76: 125 | I76: 108.5 | J76: 126.2 | K76: 133 | L76: 119.1 | M76: 99 | N76: 120.3 | O76: 117.3 | P76: 126.7 | Q76: 123.1 | R76: 124 | S76: 123.1 | T76: 119.3 | U76: 122.5 | V76: 117.3 | W76: 116.5 | X76: 118.1 | Y76: 115.5 | Z76: 109.4 | AA76: 114.3 | AB76: 119.7 | AC76: 110.7 | AD76: 114 | AE76: 119.5
A77: Rural | B77: 2015 | C77: February | D77: =B77&" "&C77 -> 2015 February | E77: 123.4 | F77: 124.4 | G77: 122.1 | H77: 125.8 | I77: 111.5 | J77: 129.4 | K77: 128.2 | L77: 118.8 | M77: 100 | N77: 118.6 | O77: 118.8 | P77: 126.8 | Q77: 122.8 | R77: 124.2 | S77: 125.4 | T77: 122.7 | U77: 125 | V77: NA | W77: 120 | X77: 119.6 | Y77: 117.7 | Z77: 110.9 | AA77: 114.8 | AB77: 118.7 | AC77: 110.8 | AD77: 115 | AE77: 120.6
A78: Urban | B78: 2015 | C78: February | D78: =B78&" "&C78 -> 2015 February | E78: 124.3 | F78: 126.5 | G78: 119.5 | H78: 125.6 | I78: 104.9 | J78: 121.6 | K78: 131.8 | L78: 125.1 | M78: 95 | N78: 127.7 | O78: 116.8 | P78: 128.6 | Q78: 123.7 | R78: 128.1 | S78: 121.3 | T78: 116.5 | U78: 120.6 | V78: 118.1 | W78: 114 | X78: 117.7 | Y78: 114.1 | Z78: 106.8 | AA78: 114.9 | AB78: 120.4 | AC78: 111.7 | AD78: 113.2 | AE78: 118.7
A79: Rural+Urban | B79: 2015 | C79: February | D79: =B79&" "&C79 -> 2015 February | E79: 123.7 | F79: 125.1 | G79: 121.1 | H79: 125.7 | I79: 109.1 | J79: 125.8 | K79: 129.4 | L79: 120.9 | M79: 98.3 | N79: 121.6 | O79: 118 | P79: 127.6 | Q79: 123.1 | R79: 125.2 | S79: 123.8 | T79: 120.1 | U79: 123.3 | V79: 118.1 | W79: 117.7 | X79: 118.7 | Y79: 116.3 | Z79: 108.7 | AA79: 114.9 | AB79: 119.7 | AC79: 111.2 | AD79: 114.1 | AE79: 119.7
A80: Rural | B80: 2015 | C80: March | D80: =B80&" "&C80 -> 2015 March | E80: 123.3 | F80: 124.7 | G80: 118.9 | H80: 126 | I80: 111.8 | J80: 130.9 | K80: 128 | L80: 119.9 | M80: 98.9 | N80: 119.4 | O80: 118.9 | P80: 127.7 | Q80: 123.1 | R80: 124.7 | S80: 126 | T80: 122.9 | U80: 125.5 | V80: NA | W80: 120.6 | X80: 120.2 | Y80: 118.2 | Z80: 111.6 | AA80: 115.5 | AB80: 119.4 | AC80: 110.8 | AD80: 115.5 | AE80: 121.1
A81: Urban | B81: 2015 | C81: March | D81: =B81&" "&C81 -> 2015 March | E81: 124 | F81: 126.7 | G81: 113.5 | H81: 125.9 | I81: 104.8 | J81: 123.8 | K81: 131.4 | L81: 127.2 | M81: 93.2 | N81: 127.4 | O81: 117 | P81: 129.2 | Q81: 123.9 | R81: 128.8 | S81: 121.7 | T81: 116.9 | U81: 120.9 | V81: 118.6 | W81: 114.4 | X81: 118 | Y81: 114.3 | Z81: 108.4 | AA81: 115.4 | AB81: 120.6 | AC81: 111.3 | AD81: 113.8 | AE81: 119.1
A82: Rural+Urban | B82: 2015 | C82: March | D82: =B82&" "&C82 -> 2015 March | E82: 123.5 | F82: 125.4 | G82: 116.8 | H82: 126 | I82: 109.2 | J82: 127.6 | K82: 129.2 | L82: 122.4 | M82: 97 | N82: 122.1 | O82: 118.1 | P82: 128.4 | Q82: 123.4 | R82: 125.8 | S82: 124.3 | T82: 120.4 | U82: 123.7 | V82: 118.6 | W82: 118.3 | X82: 119.2 | Y82: 116.7 | Z82: 109.9 | AA82: 115.4 | AB82: 120.1 | AC82: 111 | AD82: 114.7 | AE82: 120.2
A83: Rural | B83: 2015 | C83: April | D83: =B83&" "&C83 -> 2015 April | E83: 123.3 | F83: 125.5 | G83: 117.2 | H83: 126.8 | I83: 111.9 | J83: 134.2 | K83: 127.5 | L83: 121.5 | M83: 97.8 | N83: 119.8 | O83: 119.4 | P83: 128.7 | Q83: 123.6 | R83: 125.7 | S83: 126.4 | T83: 123.3 | U83: 126 | V83: NA | W83: 121.2 | X83: 120.9 | Y83: 118.6 | Z83: 111.9 | AA83: 116.2 | AB83: 119.9 | AC83: 111.6 | AD83: 116 | AE83: 121.5
A84: Urban | B84: 2015 | C84: April | D84: =B84&" "&C84 -> 2015 April | E84: 123.8 | F84: 128.2 | G84: 110 | H84: 126.3 | I84: 104.5 | J84: 130.6 | K84: 130.8 | L84: 131.3 | M84: 91.6 | N84: 127.7 | O84: 117.2 | P84: 129.5 | Q84: 124.6 | R84: 130.1 | S84: 122.1 | T84: 117.2 | U84: 121.3 | V84: 119.2 | W84: 114.7 | X84: 118.4 | Y84: 114.6 | Z84: 108.4 | AA84: 115.6 | AB84: 121.7 | AC84: 111.8 | AD84: 114.2 | AE84: 119.7
A85: Rural+Urban | B85: 2015 | C85: April | D85: =B85&" "&C85 -> 2015 April | E85: 123.5 | F85: 126.4 | G85: 114.4 | H85: 126.6 | I85: 109.2 | J85: 132.5 | K85: 128.6 | L85: 124.8 | M85: 95.7 | N85: 122.4 | O85: 118.5 | P85: 129.1 | Q85: 124 | R85: 126.9 | S85: 124.7 | T85: 120.8 | U85: 124.1 | V85: 119.2 | W85: 118.7 | X85: 119.7 | Y85: 117.1 | Z85: 110.1 | AA85: 115.9 | AB85: 121 | AC85: 111.7 | AD85: 115.1 | AE85: 120.7
A86: Rural | B86: 2015 | C86: May | D86: =B86&" "&C86 -> 2015 May | E86: 123.5 | F86: 127.1 | G86: 117.3 | H86: 127.7 | I86: 112.5 | J86: 134.1 | K86: 128.5 | L86: 124.3 | M86: 97.6 | N86: 120.7 | O86: 120.2 | P86: 129.8 | Q86: 124.4 | R86: 126.7 | S86: 127.3 | T86: 124.1 | U86: 126.8 | V86: NA | W86: 121.9 | X86: 121.5 | Y86: 119.4 | Z86: 113.3 | AA86: 116.7 | AB86: 120.5 | AC86: 112.3 | AD86: 116.9 | AE86: 122.4
A87: Urban | B87: 2015 | C87: May | D87: =B87&" "&C87 -> 2015 May | E87: 123.8 | F87: 129.7 | G87: 111.3 | H87: 126.6 | I87: 105.2 | J87: 130.8 | K87: 135.6 | L87: 142.6 | M87: 90.8 | N87: 128.8 | O87: 117.7 | P87: 129.9 | Q87: 126.1 | R87: 131.3 | S87: 122.4 | T87: 117.4 | U87: 121.6 | V87: 119.6 | W87: 114.9 | X87: 118.7 | Y87: 114.9 | Z87: 110.8 | AA87: 116 | AB87: 122 | AC87: 112.4 | AD87: 115.2 | AE87: 120.7
A88: Rural+Urban | B88: 2015 | C88: May | D88: =B88&" "&C88 -> 2015 May | E88: 123.6 | F88: 128 | G88: 115 | H88: 127.3 | I88: 109.8 | J88: 132.6 | K88: 130.9 | L88: 130.5 | M88: 95.3 | N88: 123.4 | O88: 119.2 | P88: 129.8 | Q88: 125 | R88: 127.9 | S88: 125.4 | T88: 121.3 | U88: 124.7 | V88: 119.6 | W88: 119.2 | X88: 120.2 | Y88: 117.7 | Z88: 112 | AA88: 116.3 | AB88: 121.4 | AC88: 112.3 | AD88: 116.1 | AE88: 121.6
A89: Rural | B89: 2015 | C89: June | D89: =B89&" "&C89 -> 2015 June | E89: 124.1 | F89: 130.4 | G89: 122.1 | H89: 128.7 | I89: 114.1 | J89: 133.2 | K89: 135.2 | L89: 131.9 | M89: 96.3 | N89: 123 | O89: 121.1 | P89: 131.2 | Q89: 126.6 | R89: 128.2 | S89: 128.4 | T89: 125.1 | U89: 128 | V89: NA | W89: 122.6 | X89: 122.8 | Y89: 120.4 | Z89: 114.2 | AA89: 117.9 | AB89: 122 | AC89: 113 | AD89: 117.9 | AE89: 124.1
A90: Urban | B90: 2015 | C90: June | D90: =B90&" "&C90 -> 2015 June | E90: 123.6 | F90: 134.4 | G90: 120.9 | H90: 127.3 | I90: 106 | J90: 132.3 | K90: 146.7 | L90: 148.1 | M90: 89.8 | N90: 130.5 | O90: 118 | P90: 130.5 | Q90: 128.5 | R90: 132.1 | S90: 123.2 | T90: 117.6 | U90: 122.3 | V90: 119 | W90: 115.1 | X90: 119.2 | Y90: 115.4 | Z90: 111.7 | AA90: 116.2 | AB90: 123.8 | AC90: 112.5 | AD90: 116 | AE90: 121.7
A91: Rural+Urban | B91: 2015 | C91: June | D91: =B91&" "&C91 -> 2015 June | E91: 123.9 | F91: 131.8 | G91: 121.6 | H91: 128.2 | I91: 111.1 | J91: 132.8 | K91: 139.1 | L91: 137.4 | M91: 94.1 | N91: 125.5 | O91: 119.8 | P91: 130.9 | Q91: 127.3 | R91: 129.2 | S91: 126.4 | T91: 122 | U91: 125.7 | V91: 119 | W91: 119.8 | X91: 121.1 | Y91: 118.5 | Z91: 112.9 | AA91: 116.9 | AB91: 123.1 | AC91: 112.8 | AD91: 117 | AE91: 123
A92: Rural | B92: 2015 | C92: July | D92: =B92&" "&C92 -> 2015 July | E92: 124 | F92: 131.5 | G92: 122 | H92: 128.7 | I92: 113.5 | J92: 133.3 | K92: 140.8 | L92: 133.8 | M92: 94.1 | N92: 123.4 | O92: 121 | P92: 131.7 | Q92: 127.5 | R92: 129.4 | S92: 128.8 | T92: 125.5 | U92: 128.3 | V92: NA | W92: 123 | X92: 123 | Y92: 120.8 | Z92: 114.1 | AA92: 118 | AB92: 122.9 | AC92: 112.7 | AD92: 118.1 | AE92: 124.7
A93: Urban | B93: 2015 | C93: July | D93: =B93&" "&C93 -> 2015 July | E93: 123.2 | F93: 134.3 | G93: 119.5 | H93: 127.7 | I93: 106.3 | J93: 132.8 | K93: 153.5 | L93: 149.5 | M93: 85.7 | N93: 131.5 | O93: 118.3 | P93: 131.1 | Q93: 129.5 | R93: 133.1 | S93: 123.5 | T93: 117.9 | U93: 122.7 | V93: 119.9 | W93: 115.3 | X93: 119.5 | Y93: 116 | Z93: 111.5 | AA93: 116.6 | AB93: 125.4 | AC93: 111.7 | AD93: 116.3 | AE93: 122.4
A94: Rural+Urban | B94: 2015 | C94: July | D94: =B94&" "&C94 -> 2015 July | E94: 123.7 | F94: 132.5 | G94: 121 | H94: 128.3 | I94: 110.9 | J94: 133.1 | K94: 145.1 | L94: 139.1 | M94: 91.3 | N94: 126.1 | O94: 119.9 | P94: 131.4 | Q94: 128.2 | R94: 130.4 | S94: 126.7 | T94: 122.3 | U94: 126.1 | V94: 119.9 | W94: 120.1 | X94: 121.3 | Y94: 119 | Z94: 112.7 | AA94: 117.2 | AB94: 124.4 | AC94: 112.3 | AD94: 117.2 | AE94: 123.6
A95: Rural | B95: 2015 | C95: August | D95: =B95&" "&C95 -> 2015 August | E95: 124.7 | F95: 131.3 | G95: 121.3 | H95: 128.8 | I95: 114 | J95: 134.2 | K95: 153.6 | L95: 137.9 | M95: 93.1 | N95: 123.9 | O95: 121.5 | P95: 132.5 | Q95: 129.8 | R95: 130.1 | S95: 129.5 | T95: 126.3 | U95: 129 | V95: NA | W95: 123.8 | X95: 123.7 | Y95: 121.1 | Z95: 113.6 | AA95: 118.5 | AB95: 123.6 | AC95: 112.5 | AD95: 118.2 | AE95: 126.1
A96: Urban | B96: 2015 | C96: August | D96: =B96&" "&C96 -> 2015 August | E96: 123.1 | F96: 131.7 | G96: 118.1 | H96: 128 | I96: 106.8 | J96: 130.1 | K96: 165.5 | L96: 156 | M96: 85.3 | N96: 132.7 | O96: 118.8 | P96: 131.7 | Q96: 131.1 | R96: 134.2 | S96: 123.7 | T96: 118.2 | U96: 122.9 | V96: 120.9 | W96: 115.3 | X96: 120 | Y96: 116.6 | Z96: 109.9 | AA96: 117.2 | AB96: 126.2 | AC96: 112 | AD96: 116.2 | AE96: 123.2
A97: Rural+Urban | B97: 2015 | C97: August | D97: =B97&" "&C97 -> 2015 August | E97: 124.2 | F97: 131.4 | G97: 120.1 | H97: 128.5 | I97: 111.4 | J97: 132.3 | K97: 157.6 | L97: 144 | M97: 90.5 | N97: 126.8 | O97: 120.4 | P97: 132.1 | Q97: 130.3 | R97: 131.2 | S97: 127.2 | T97: 122.9 | U97: 126.6 | V97: 120.9 | W97: 120.6 | X97: 122 | Y97: 119.4 | Z97: 111.7 | AA97: 117.8 | AB97: 125.1 | AC97: 112.3 | AD97: 117.2 | AE97: 124.8
A98: Rural | B98: 2015 | C98: September | D98: =B98&" "&C98 -> 2015 September | E98: 125.1 | F98: 131.1 | G98: 120.7 | H98: 129.2 | I98: 114.7 | J98: 132.3 | K98: 158.9 | L98: 142.1 | M98: 92.5 | N98: 125.4 | O98: 121.9 | P98: 132.7 | Q98: 131 | R98: 131 | S98: 130.4 | T98: 126.8 | U98: 129.9 | V98: NA | W98: 123.7 | X98: 124.5 | Y98: 121.4 | Z98: 113.8 | AA98: 119.6 | AB98: 124.5 | AC98: 113.7 | AD98: 118.8 | AE98: 127
A99: Urban | B99: 2015 | C99: September | D99: =B99&" "&C99 -> 2015 September | E99: 123.4 | F99: 129 | G99: 115.6 | H99: 128.3 | I99: 107 | J99: 124 | K99: 168.5 | L99: 165.4 | M99: 86.3 | N99: 134.4 | O99: 119.1 | P99: 132.3 | Q99: 131.5 | R99: 134.7 | S99: 124 | T99: 118.6 | U99: 123.2 | V99: 121.6 | W99: 115.1 | X99: 120.4 | Y99: 117.1 | Z99: 109.1 | AA99: 117.3 | AB99: 126.5 | AC99: 112.9 | AD99: 116.2 | AE99: 123.5
A100: Rural+Urban | B100: 2015 | C100: September | D100: =B100&" "&C100 -> 2015 September | E100: 124.6 | F100: 130.4 | G100: 118.7 | H100: 128.9 | I100: 111.9 | J100: 128.4 | K100: 162.2 | L100: 150 | M100: 90.4 | N100: 128.4 | O100: 120.7 | P100: 132.5 | Q100: 131.2 | R100: 132 | S100: 127.9 | T100: 123.4 | U100: 127.2 | V100: 121.6 | W100: 120.4 | X100: 122.6 | Y100: 119.8 | Z100: 111.3 | AA100: 118.3 | AB100: 125.7 | AC100: 113.4 | AD100: 117.5 | AE100: 125.4
...

Sheet RAW DATASET COPY
A1: Sector | B1: Year | C1: Month | D1: Time frame | E1: Cereals and products | F1: Meat and fish | G1: Egg | H1: Milk and products | I1: Oils and fats | J1: Fruits | K1: Vegetables | L1: Pulses and products | M1: Sugar and Confectionery | N1: Spices | O1: Non-alcoholic beverages | P1: Prepared meals, snacks, sweets etc. | Q1: Food and beverages | R1: Pan, tobacco and intoxicants | S1: Clothing | T1: Footwear | U1: Clothing and footwear | V1: Housing | W1: Fuel and light | X1: Household goods and services | Y1: Health | Z1: Transport and communication | AA1: Recreation and amusement | AB1: Education | AC1: Personal care and effects | AD1: Miscellaneous | AE1: General index | AF1: Flag | AG1: if cpi val of fruits and veg is >150 ,then flag YES or no | AH1: COUNTYES | AI1: SPICES CPI
A2: Rural | B2: 2013 | C2: January | D2: =B2&" "&C2 -> 2013 January | E2: 107.5 | F2: 106.3 | G2: 108.1 | H2: 104.9 | I2: 106.1 | J2: 103.9 | K2: 101.9 | L2: 106.1 | M2: 106.8 | N2: 103.1 | O2: 104.8 | P2: 106.7 | Q2: 105.5 | R2: 105.1 | S2: 106.5 | T2: 105.8 | U2: 106.4 | V2: NA | W2: 105.5 | X2: 104.8 | Y2: 104 | Z2: 103.3 | AA2: 103.4 | AB2: 103.8 | AC2: 104.7 | AD2: 104 | AE2: 105.1 | AF2: =IF(AND(J2>150,K2>150),"Yes","No") -> No | AG2: AVG INFLATION val for spices cat, sector is urban and month is dec | AH2: =COUNTIF(AF2:AF373,"Yes") -> 94 | AI2: =AVERAGEIFS(N2:N374,A2:A374,"Urban",C2:C374,"December") -> 148.12 | AK2: NAME | AL2: SALARY | AM2: FLAG
A3: Urban | B3: 2013 | C3: January | D3: =B3&" "&C3 -> 2013 January | E3: 110.5 | F3: 109.1 | G3: 113 | H3: 103.6 | I3: 103.4 | J3: 102.3 | K3: 102.9 | L3: 105.8 | M3: 105.1 | N3: 101.8 | O3: 105.1 | P3: 107.9 | Q3: 105.9 | R3: 105.2 | S3: 105.9 | T3: 105 | U3: 105.8 | V3: 100.3 | W3: 105.4 | X3: 104.8 | Y3: 104.1 | Z3: 103.2 | AA3: 102.9 | AB3: 103.5 | AC3: 104.3 | AD3: 103.7 | AE3: 104 | AF3: =IF(AND(J3>150,K3>150),"Yes","No") -> No | AK3: John | AL3: 35000 | AM3: =IF(AL3<50000,CONCATENATE(AK3," ","Low"),CONCATENATE(AK3," ","High")) -> John Low
A4: Rural+Urban | B4: 2013 | C4: January | D4: =B4&" "&C4 -> 2013 January | E4: 108.4 | F4: 107.3 | G4: 110 | H4: 104.4 | I4: 105.1 | J4: 103.2 | K4: 102.2 | L4: 106 | M4: 106.2 | N4: 102.7 | O4: 104.9 | P4: 107.3 | Q4: 105.6 | R4: 105.1 | S4: 106.3 | T4: 105.5 | U4: 106.2 | V4: 100.3 | W4: 105.5 | X4: 104.8 | Y4: 104 | Z4: 103.2 | AA4: 103.1 | AB4: 103.6 | AC4: 104.5 | AD4: 103.9 | AE4: 104.6 | AF4: =IF(AND(J4>150,K4>150),"Yes","No") -> No | AK4: Sally | AL4: 55000 | AM4: =IF(AL4<50000,CONCATENATE(AK4," ","Low"),CONCATENATE(AK4," ","High")) -> Sally High
A5: Rural | B5: 2013 | C5: February | D5: =B5&" "&C5 -> 2013 February | E5: 109.2 | F5: 108.7 | G5: 110.2 | H5: 105.4 | I5: 106.7 | J5: 104 | K5: 102.4 | L5: 105.9 | M5: 105.7 | N5: 103.1 | O5: 105.1 | P5: 107.7 | Q5: 106.3 | R5: 105.6 | S5: 107.1 | T5: 106.3 | U5: 107 | V5: NA | W5: 106.2 | X5: 105.2 | Y5: 104.4 | Z5: 103.9 | AA5: 104 | AB5: 104.1 | AC5: 104.6 | AD5: 104.4 | AE5: 105.8 | AF5: =IF(AND(J5>150,K5>150),"Yes","No") -> No | AK5: Kevin | AL5: 60000 | AM5: =IF(AL5<50000,CONCATENATE(AK5," ","Low"),CONCATENATE(AK5," ","High")) -> Kevin High
A6: Urban | B6: 2013 | C6: February | D6: =B6&" "&C6 -> 2013 February | E6: 112.9 | F6: 112.9 | G6: 116.9 | H6: 104 | I6: 103.5 | J6: 103.1 | K6: 104.9 | L6: 104.1 | M6: 103.8 | N6: 102.3 | O6: 106 | P6: 109 | Q6: 107.2 | R6: 106 | S6: 106.6 | T6: 105.5 | U6: 106.4 | V6: 100.4 | W6: 105.7 | X6: 105.2 | Y6: 104.7 | Z6: 104.4 | AA6: 103.3 | AB6: 103.7 | AC6: 104.3 | AD6: 104.3 | AE6: 104.7 | AF6: =IF(AND(J6>150,K6>150),"Yes","No") -> No | AK6: Anna | AL6: 40000 | AM6: =IF(AL6<50000,CONCATENATE(AK6," ","Low"),CONCATENATE(AK6," ","High")) -> Anna Low
A7: Rural+Urban | B7: 2013 | C7: February | D7: =B7&" "&C7 -> 2013 February | E7: 110.4 | F7: 110.2 | G7: 112.8 | H7: 104.9 | I7: 105.5 | J7: 103.6 | K7: 103.2 | L7: 105.3 | M7: 105.1 | N7: 102.8 | O7: 105.5 | P7: 108.3 | Q7: 106.6 | R7: 105.7 | S7: 106.9 | T7: 106 | U7: 106.8 | V7: 100.4 | W7: 106 | X7: 105.2 | Y7: 104.5 | Z7: 104.2 | AA7: 103.6 | AB7: 103.9 | AC7: 104.5 | AD7: 104.4 | AE7: 105.3 | AF7: =IF(AND(J7>150,K7>150),"Yes","No") -> No
A8: Rural | B8: 2013 | C8: March | D8: =B8&" "&C8 -> 2013 March | E8: 110.2 | F8: 108.8 | G8: 109.9 | H8: 105.6 | I8: 106.2 | J8: 105.7 | K8: 101.4 | L8: 105.7 | M8: 105 | N8: 103.3 | O8: 105.6 | P8: 108.2 | Q8: 106.6 | R8: 106.5 | S8: 107.6 | T8: 106.8 | U8: 107.5 | V8: NA | W8: 106.1 | X8: 105.6 | Y8: 104.7 | Z8: 104.6 | AA8: 104 | AB8: 104.3 | AC8: 104.3 | AD8: 104.6 | AE8: 106 | AF8: =IF(AND(J8>150,K8>150),"Yes","No") -> No | AK8: Kevin | AL8: =INDEX(AM2:AM6,MATCH(AK8,AK2:AK6,0)) -> Kevin High
A9: Urban | B9: 2013 | C9: March | D9: =B9&" "&C9 -> 2013 March | E9: 113.9 | F9: 111.4 | G9: 113.2 | H9: 104.3 | I9: 102.7 | J9: 104.9 | K9: 103.8 | L9: 103.5 | M9: 102.6 | N9: 102.4 | O9: 107 | P9: 109.8 | Q9: 107.3 | R9: 106.8 | S9: 107.2 | T9: 106 | U9: 107 | V9: 100.4 | W9: 106 | X9: 105.7 | Y9: 105.2 | Z9: 105.5 | AA9: 103.5 | AB9: 103.8 | AC9: 104.2 | AD9: 104.9 | AE9: 105 | AF9: =IF(AND(J9>150,K9>150),"Yes","No") -> No
A10: Rural+Urban | B10: 2013 | C10: March | D10: =B10&" "&C10 -> 2013 March | E10: 111.4 | F10: 109.7 | G10: 111.2 | H10: 105.1 | I10: 104.9 | J10: 105.3 | K10: 102.2 | L10: 105 | M10: 104.2 | N10: 103 | O10: 106.2 | P10: 108.9 | Q10: 106.9 | R10: 106.6 | S10: 107.4 | T10: 106.5 | U10: 107.3 | V10: 100.4 | W10: 106.1 | X10: 105.6 | Y10: 104.9 | Z10: 105.1 | AA10: 103.7 | AB10: 104 | AC10: 104.3 | AD10: 104.7 | AE10: 105.5 | AF10: =IF(AND(J10>150,K10>150),"Yes","No") -> No
A11: Rural | B11: 2013 | C11: April | D11: =B11&" "&C11 -> 2013 April | E11: 110.2 | F11: 109.5 | G11: 106.9 | H11: 106.3 | I11: 105.7 | J11: 108.3 | K11: 103.4 | L11: 105.7 | M11: 104.2 | N11: 103.2 | O11: 106.5 | P11: 108.8 | Q11: 107.1 | R11: 107.1 | S11: 108.1 | T11: 107.4 | U11: 108 | V11: NA | W11: 106.5 | X11: 106.1 | Y11: 105.1 | Z11: 104.4 | AA11: 104.5 | AB11: 104.8 | AC11: 102.7 | AD11: 104.6 | AE11: 106.4 | AF11: =IF(AND(J11>150,K11>150),"Yes","No") -> No
A12: Urban | B12: 2013 | C12: April | D12: =B12&" "&C12 -> 2013 April | E12: 114.6 | F12: 113.4 | G12: 106 | H12: 104.7 | I12: 102.1 | J12: 109.5 | K12: 109.7 | L12: 104.6 | M12: 102 | N12: 103.5 | O12: 108.2 | P12: 110.6 | Q12: 108.8 | R12: 108.5 | S12: 107.9 | T12: 106.4 | U12: 107.7 | V12: 100.5 | W12: 106.4 | X12: 106.5 | Y12: 105.7 | Z12: 105 | AA12: 104 | AB12: 105.2 | AC12: 103.2 | AD12: 105.1 | AE12: 105.7 | AF12: =IF(AND(J12>150,K12>150),"Yes","No") -> No
A13: Rural+Urban | B13: 2013 | C13: April | D13: =B13&" "&C13 -> 2013 April | E13: 111.6 | F13: 110.9 | G13: 106.6 | H13: 105.7 | I13: 104.4 | J13: 108.9 | K13: 105.5 | L13: 105.3 | M13: 103.5 | N13: 103.3 | O13: 107.2 | P13: 109.6 | Q13: 107.7 | R13: 107.5 | S13: 108 | T13: 107 | U13: 107.9 | V13: 100.5 | W13: 106.5 | X13: 106.3 | Y13: 105.3 | Z13: 104.7 | AA13: 104.2 | AB13: 105 | AC13: 102.9 | AD13: 104.8 | AE13: 106.1 | AF13: =IF(AND(J13>150,K13>150),"Yes","No") -> No
A14: Rural | B14: 2013 | C14: May | D14: =B14&" "&C14 -> 2013 May | E14: 110.9 | F14: 109.8 | G14: 105.9 | H14: 107.5 | I14: 105.3 | J14: 108.1 | K14: 107.3 | L14: 106.1 | M14: 103.7 | N14: 104 | O14: 107.4 | P14: 109.9 | Q14: 108.1 | R14: 108.1 | S14: 108.8 | T14: 107.9 | U14: 108.6 | V14: NA | W14: 107.5 | X14: 106.8 | Y14: 105.7 | Z14: 104.1 | AA14: 105 | AB14: 105.5 | AC14: 102.1 | AD14: 104.8 | AE14: 107.2 | AF14: =IF(AND(J14>150,K14>150),"Yes","No") -> No
A15: Urban | B15: 2013 | C15: May | D15: =B15&" "&C15 -> 2013 May | E15: 115.4 | F15: 114.2 | G15: 102.7 | H15: 105.5 | I15: 101.5 | J15: 110.6 | K15: 123.7 | L15: 105.2 | M15: 101.9 | N15: 105 | O15: 109.1 | P15: 111.3 | Q15: 111.1 | R15: 109.8 | S15: 108.5 | T15: 106.7 | U15: 108.3 | V15: 100.5 | W15: 107.2 | X15: 107.1 | Y15: 106.2 | Z15: 103.9 | AA15: 104.6 | AB15: 105.7 | AC15: 102.6 | AD15: 104.9 | AE15: 106.6 | AF15: =IF(AND(J15>150,K15>150),"Yes","No") -> No
A16: Rural+Urban | B16: 2013 | C16: May | D16: =B16&" "&C16 -> 2013 May | E16: 112.3 | F16: 111.3 | G16: 104.7 | H16: 106.8 | I16: 103.9 | J16: 109.3 | K16: 112.9 | L16: 105.8 | M16: 103.1 | N16: 104.3 | O16: 108.1 | P16: 110.5 | Q16: 109.2 | R16: 108.6 | S16: 108.7 | T16: 107.4 | U16: 108.5 | V16: 100.5 | W16: 107.4 | X16: 106.9 | Y16: 105.9 | Z16: 104 | AA16: 104.8 | AB16: 105.6 | AC16: 102.3 | AD16: 104.8 | AE16: 106.9 | AF16: =IF(AND(J16>150,K16>150),"Yes","No") -> No
A17: Rural | B17: 2013 | C17: June | D17: =B17&" "&C17 -> 2013 June | E17: 112.3 | F17: 112.1 | G17: 108.1 | H17: 108.3 | I17: 105.9 | J17: 109.2 | K17: 118 | L17: 106.8 | M17: 104.1 | N17: 105.4 | O17: 108.2 | P17: 111 | Q17: 110.6 | R17: 109 | S17: 109.7 | T17: 108.8 | U17: 109.5 | V17: NA | W17: 108.5 | X17: 107.5 | Y17: 106.3 | Z17: 105 | AA17: 105.6 | AB17: 106.5 | AC17: 102.5 | AD17: 105.5 | AE17: 108.9 | AF17: =IF(AND(J17>150,K17>150),"Yes","No") -> No
A18: Urban | B18: 2013 | C18: June | D18: =B18&" "&C18 -> 2013 June | E18: 117 | F18: 120.1 | G18: 112.5 | H18: 107.3 | I18: 101.3 | J18: 112.4 | K18: 143.6 | L18: 105.4 | M18: 101.4 | N18: 106.4 | O18: 110 | P18: 112.2 | Q18: 115 | R18: 110.9 | S18: 109.2 | T18: 107.2 | U18: 108.9 | V18: 106.6 | W18: 108 | X18: 107.7 | Y18: 106.5 | Z18: 105.2 | AA18: 105.2 | AB18: 108.1 | AC18: 103.3 | AD18: 106.1 | AE18: 109.7 | AF18: =IF(AND(J18>150,K18>150),"Yes","No") -> No
A19: Rural+Urban | B19: 2013 | C19: June | D19: =B19&" "&C19 -> 2013 June | E19: 113.8 | F19: 114.9 | G19: 109.8 | H19: 107.9 | I19: 104.2 | J19: 110.7 | K19: 126.7 | L19: 106.3 | M19: 103.2 | N19: 105.7 | O19: 109 | P19: 111.6 | Q19: 112.2 | R19: 109.5 | S19: 109.5 | T19: 108.1 | U19: 109.3 | V19: 106.6 | W19: 108.3 | X19: 107.6 | Y19: 106.4 | Z19: 105.1 | AA19: 105.4 | AB19: 107.4 | AC19: 102.8 | AD19: 105.8 | AE19: 109.3 | AF19: =IF(AND(J19>150,K19>150),"Yes","No") -> No
A20: Rural | B20: 2013 | C20: July | D20: =B20&" "&C20 -> 2013 July | E20: 113.4 | F20: 114.9 | G20: 110.5 | H20: 109.3 | I20: 106.2 | J20: 110.3 | K20: 129.2 | L20: 107.1 | M20: 104.3 | N20: 106.4 | O20: 109.1 | P20: 112.1 | Q20: 113.1 | R20: 109.8 | S20: 110.5 | T20: 109.5 | U20: 110.3 | V20: NA | W20: 109.5 | X20: 108.3 | Y20: 106.9 | Z20: 106.8 | AA20: 106.4 | AB20: 107.8 | AC20: 102.5 | AD20: 106.5 | AE20: 110.7 | AF20: =IF(AND(J20>150,K20>150),"Yes","No") -> No
A21: Urban | B21: 2013 | C21: July | D21: =B21&" "&C21 -> 2013 July | E21: 117.8 | F21: 119.2 | G21: 114 | H21: 108.3 | I21: 101.1 | J21: 113.2 | K21: 160.9 | L21: 105.1 | M21: 101.3 | N21: 107.5 | O21: 110.4 | P21: 113.1 | Q21: 117.5 | R21: 111.7 | S21: 109.8 | T21: 107.8 | U21: 109.5 | V21: 107.7 | W21: 108.6 | X21: 108.1 | Y21: 107.1 | Z21: 107.3 | AA21: 105.9 | AB21: 110.1 | AC21: 103.2 | AD21: 107.3 | AE21: 111.4 | AF21: =IF(AND(J21>150,K21>150),"Yes","No") -> No
A22: Rural+Urban | B22: 2013 | C22: July | D22: =B22&" "&C22 -> 2013 July | E22: 114.8 | F22: 116.4 | G22: 111.9 | H22: 108.9 | I22: 104.3 | J22: 111.7 | K22: 140 | L22: 106.4 | M22: 103.3 | N22: 106.8 | O22: 109.6 | P22: 112.6 | Q22: 114.7 | R22: 110.3 | S22: 110.2 | T22: 108.8 | U22: 110 | V22: 107.7 | W22: 109.2 | X22: 108.2 | Y22: 107 | Z22: 107.1 | AA22: 106.1 | AB22: 109.1 | AC22: 102.8 | AD22: 106.9 | AE22: 111 | AF22: =IF(AND(J22>150,K22>150),"Yes","No") -> No
A23: Rural | B23: 2013 | C23: August | D23: =B23&" "&C23 -> 2013 August | E23: 114.3 | F23: 115.4 | G23: 111.1 | H23: 110 | I23: 106.4 | J23: 110.8 | K23: 138.9 | L23: 107.4 | M23: 104.1 | N23: 106.9 | O23: 109.7 | P23: 112.6 | Q23: 114.9 | R23: 110.7 | S23: 111.3 | T23: 110.2 | U23: 111.1 | V23: NA | W23: 109.9 | X23: 108.7 | Y23: 107.5 | Z23: 107.8 | AA23: 106.8 | AB23: 108.7 | AC23: 105 | AD23: 107.5 | AE23: 112.1 | AF23: =IF(AND(J23>150,K23>150),"Yes","No") -> No
A24: Urban | B24: 2013 | C24: August | D24: =B24&" "&C24 -> 2013 August | E24: 118.3 | F24: 120.4 | G24: 112.7 | H24: 108.9 | I24: 101.1 | J24: 108.7 | K24: 177 | L24: 104.7 | M24: 101 | N24: 108.5 | O24: 110.9 | P24: 114.3 | Q24: 119.6 | R24: 112.4 | S24: 110.6 | T24: 108.3 | U24: 110.2 | V24: 108.9 | W24: 109.3 | X24: 108.7 | Y24: 107.6 | Z24: 108.1 | AA24: 106.5 | AB24: 110.8 | AC24: 106 | AD24: 108.3 | AE24: 112.7 | AF24: =IF(AND(J24>150,K24>150),"Yes","No") -> No
A25: Rural+Urban | B25: 2013 | C25: August | D25: =B25&" "&C25 -> 2013 August | E25: 115.6 | F25: 117.2 | G25: 111.7 | H25: 109.6 | I25: 104.5 | J25: 109.8 | K25: 151.8 | L25: 106.5 | M25: 103.1 | N25: 107.4 | O25: 110.2 | P25: 113.4 | Q25: 116.6 | R25: 111.2 | S25: 111 | T25: 109.4 | U25: 110.7 | V25: 108.9 | W25: 109.7 | X25: 108.7 | Y25: 107.5 | Z25: 108 | AA25: 106.6 | AB25: 109.9 | AC25: 105.4 | AD25: 107.9 | AE25: 112.4 | AF25: =IF(AND(J25>150,K25>150),"Yes","No") -> No
A26: Rural | B26: 2013 | C26: September | D26: =B26&" "&C26 -> 2013 September | E26: 115.4 | F26: 115.7 | G26: 111.7 | H26: 111 | I26: 107.4 | J26: 110.9 | K26: 154 | L26: 108.1 | M26: 104.2 | N26: 107.9 | O26: 110.4 | P26: 114 | Q26: 117.8 | R26: 111.7 | S26: 112.7 | T26: 111.4 | U26: 112.5 | V26: NA | W26: 111.1 | X26: 109.6 | Y26: 108.3 | Z26: 109.3 | AA26: 107.7 | AB26: 109.8 | AC26: 106.7 | AD26: 108.7 | AE26: 114.2 | AF26: =IF(AND(J26>150,K26>150),"Yes","No") -> No
A27: Urban | B27: 2013 | C27: September | D27: =B27&" "&C27 -> 2013 September | E27: 118.6 | F27: 119.1 | G27: 113.2 | H27: 109.6 | I27: 101.7 | J27: 103.2 | K27: 174.3 | L27: 105.1 | M27: 100.8 | N27: 109.1 | O27: 111.1 | P27: 115.4 | Q27: 119.2 | R27: 112.9 | S27: 111.4 | T27: 109 | U27: 111.1 | V27: 109.7 | W27: 109.5 | X27: 109.6 | Y27: 107.9 | Z27: 110.4 | AA27: 107.4 | AB27: 111.2 | AC27: 106.9 | AD27: 109.4 | AE27: 113.2 | AF27: =IF(AND(J27>150,K27>150),"Yes","No") -> No
A28: Rural+Urban | B28: 2013 | C28: September | D28: =B28&" "&C28 -> 2013 September | E28: 116.4 | F28: 116.9 | G28: 112.3 | H28: 110.5 | I28: 105.3 | J28: 107.3 | K28: 160.9 | L28: 107.1 | M28: 103.1 | N28: 108.3 | O28: 110.7 | P28: 114.6 | Q28: 118.3 | R28: 112 | S28: 112.2 | T28: 110.4 | U28: 111.9 | V28: 109.7 | W28: 110.5 | X28: 109.6 | Y28: 108.1 | Z28: 109.9 | AA28: 107.5 | AB28: 110.6 | AC28: 106.8 | AD28: 109 | AE28: 113.7 | AF28: =IF(AND(J28>150,K28>150),"Yes","No") -> No
A29: Rural | B29: 2013 | C29: October | D29: =B29&" "&C29 -> 2013 October | E29: 116.3 | F29: 115.4 | G29: 112.6 | H29: 111.7 | I29: 107.7 | J29: 113.2 | K29: 164.9 | L29: 108.3 | M29: 103.9 | N29: 108.2 | O29: 111.1 | P29: 114.9 | Q29: 119.8 | R29: 112.2 | S29: 113.6 | T29: 112.3 | U29: 113.4 | V29: NA | W29: 111.6 | X29: 110.4 | Y29: 108.9 | Z29: 109.3 | AA29: 108.3 | AB29: 110.2 | AC29: 107.5 | AD29: 109.1 | AE29: 115.5 | AF29: =IF(AND(J29>150,K29>150),"Yes","No") -> No
A30: Urban | B30: 2013 | C30: October | D30: =B30&" "&C30 -> 2013 October | E30: 118.9 | F30: 118.1 | G30: 114.5 | H30: 110.4 | I30: 102.3 | J30: 106.2 | K30: 183.5 | L30: 105.3 | M30: 100.2 | N30: 109.6 | O30: 111.4 | P30: 116 | Q30: 120.8 | R30: 113.5 | S30: 112.5 | T30: 109.7 | U30: 112 | V30: 110.5 | W30: 109.7 | X30: 110.2 | Y30: 108.2 | Z30: 109.7 | AA30: 108 | AB30: 111.3 | AC30: 107.3 | AD30: 109.4 | AE30: 114 | AF30: =IF(AND(J30>150,K30>150),"Yes","No") -> No
A31: Rural+Urban | B31: 2013 | C31: October | D31: =B31&" "&C31 -> 2013 October | E31: 117.1 | F31: 116.3 | G31: 113.3 | H31: 111.2 | I31: 105.7 | J31: 109.9 | K31: 171.2 | L31: 107.3 | M31: 102.7 | N31: 108.7 | O31: 111.2 | P31: 115.4 | Q31: 120.2 | R31: 112.5 | S31: 113.2 | T31: 111.2 | U31: 112.8 | V31: 110.5 | W31: 110.9 | X31: 110.3 | Y31: 108.6 | Z31: 109.5 | AA31: 108.1 | AB31: 110.8 | AC31: 107.4 | AD31: 109.2 | AE31: 114.8 | AF31: =IF(AND(J31>150,K31>150),"Yes","No") -> No
A32: Rural | B32: 2013 | C32: November | D32: =B32&" "&C32 -> 2013 November | E32: 117.3 | F32: 114.9 | G32: 116.2 | H32: 112.8 | I32: 108.9 | J32: 116.6 | K32: 178.1 | L32: 109.1 | M32: 103.6 | N32: 109 | O32: 111.8 | P32: 116 | Q32: 122.5 | R32: 112.8 | S32: 114.6 | T32: 113.1 | U32: 114.4 | V32: NA | W32: 112.6 | X32: 111.3 | Y32: 109.7 | Z32: 109.6 | AA32: 108.7 | AB32: 111 | AC32: 108.2 | AD32: 109.8 | AE32: 117.4 | AF32: =IF(AND(J32>150,K32>150),"Yes","No") -> No
A33: Urban | B33: 2013 | C33: November | D33: =B33&" "&C33 -> 2013 November | E33: 119.8 | F33: 116.3 | G33: 122.6 | H33: 112 | I33: 103.2 | J33: 110 | K33: 192.8 | L33: 106.3 | M33: 99.5 | N33: 110.3 | O33: 111.8 | P33: 117.1 | Q33: 122.9 | R33: 114.1 | S33: 113.5 | T33: 110.3 | U33: 113 | V33: 111.1 | W33: 110 | X33: 110.9 | Y33: 108.6 | Z33: 109.5 | AA33: 108.5 | AB33: 111.3 | AC33: 107.9 | AD33: 109.6 | AE33: 115 | AF33: =IF(AND(J33>150,K33>150),"Yes","No") -> No
A34: Rural+Urban | B34: 2013 | C34: November | D34: =B34&" "&C34 -> 2013 November | E34: 118.1 | F34: 115.4 | G34: 118.7 | H34: 112.5 | I34: 106.8 | J34: 113.5 | K34: 183.1 | L34: 108.2 | M34: 102.2 | N34: 109.4 | O34: 111.8 | P34: 116.5 | Q34: 122.6 | R34: 113.1 | S34: 114.2 | T34: 111.9 | U34: 113.8 | V34: 111.1 | W34: 111.6 | X34: 111.1 | Y34: 109.3 | Z34: 109.5 | AA34: 108.6 | AB34: 111.2 | AC34: 108.1 | AD34: 109.7 | AE34: 116.3 | AF34: =IF(AND(J34>150,K34>150),"Yes","No") -> No
A35: Rural | B35: 2013 | C35: December | D35: =B35&" "&C35 -> 2013 December | E35: 118.4 | F35: 115.9 | G35: 120.4 | H35: 113.8 | I35: 109.5 | J35: 115.5 | K35: 145.7 | L35: 109.5 | M35: 102.9 | N35: 109.8 | O35: 112.1 | P35: 116.8 | Q35: 118.7 | R35: 113.6 | S35: 115.8 | T35: 114 | U35: 115.5 | V35: NA | W35: 112.8 | X35: 112.1 | Y35: 110.1 | Z35: 109.9 | AA35: 109.2 | AB35: 111.6 | AC35: 108.1 | AD35: 110.1 | AE35: 115.5 | AF35: =IF(AND(J35>150,K35>150),"Yes","No") -> No
A36: Urban | B36: 2013 | C36: December | D36: =B36&" "&C36 -> 2013 December | E36: 120.5 | F36: 118.1 | G36: 128.5 | H36: 112.8 | I36: 103.4 | J36: 110.7 | K36: 144.8 | L36: 107.1 | M36: 98.6 | N36: 111.9 | O36: 112.1 | P36: 118.1 | Q36: 117.8 | R36: 115 | S36: 114.2 | T36: 110.9 | U36: 113.7 | V36: 110.7 | W36: 110.4 | X36: 111.3 | Y36: 109 | Z36: 109.7 | AA36: 108.9 | AB36: 111.4 | AC36: 107.7 | AD36: 109.8 | AE36: 113.3 | AF36: =IF(AND(J36>150,K36>150),"Yes","No") -> No
A37: Rural+Urban | B37: 2013 | C37: December | D37: =B37&" "&C37 -> 2013 December | E37: 119.1 | F37: 116.7 | G37: 123.5 | H37: 113.4 | I37: 107.3 | J37: 113.3 | K37: 145.4 | L37: 108.7 | M37: 101.5 | N37: 110.5 | O37: 112.1 | P37: 117.4 | Q37: 118.4 | R37: 114 | S37: 115.2 | T37: 112.7 | U37: 114.8 | V37: 110.7 | W37: 111.9 | X37: 111.7 | Y37: 109.7 | Z37: 109.8 | AA37: 109 | AB37: 111.5 | AC37: 107.9 | AD37: 110 | AE37: 114.5 | AF37: =IF(AND(J37>150,K37>150),"Yes","No") -> No
A38: Rural | B38: 2014 | C38: January | D38: =B38&" "&C38 -> 2014 January | E38: 118.9 | F38: 117.1 | G38: 120.5 | H38: 114.4 | I38: 109 | J38: 115.5 | K38: 123.9 | L38: 109.6 | M38: 101.8 | N38: 110.2 | O38: 112.4 | P38: 117.3 | Q38: 116 | R38: 114 | S38: 116.5 | T38: 114.5 | U38: 116.2 | V38: NA | W38: 113 | X38: 112.6 | Y38: 110.6 | Z38: 110.5 | AA38: 109.6 | AB38: 111.8 | AC38: 108.3 | AD38: 110.6 | AE38: 114.2 | AF38: =IF(AND(J38>150,K38>150),"Yes","No") -> No
A39: Urban | B39: 2014 | C39: January | D39: =B39&" "&C39 -> 2014 January | E39: 121.2 | F39: 122 | G39: 129.9 | H39: 113.6 | I39: 102.9 | J39: 112.1 | K39: 118.9 | L39: 107.5 | M39: 96.9 | N39: 112.7 | O39: 112.1 | P39: 119 | Q39: 115.5 | R39: 115.7 | S39: 114.8 | T39: 111.3 | U39: 114.3 | V39: 111.6 | W39: 111 | X39: 111.9 | Y39: 109.7 | Z39: 110.8 | AA39: 109.8 | AB39: 111.5 | AC39: 108 | AD39: 110.5 | AE39: 112.9 | AF39: =IF(AND(J39>150,K39>150),"Yes","No") -> No
A40: Rural+Urban | B40: 2014 | C40: January | D40: =B40&" "&C40 -> 2014 January | E40: 119.6 | F40: 118.8 | G40: 124.1 | H40: 114.1 | I40: 106.8 | J40: 113.9 | K40: 122.2 | L40: 108.9 | M40: 100.2 | N40: 111 | O40: 112.3 | P40: 118.1 | Q40: 115.8 | R40: 114.5 | S40: 115.8 | T40: 113.2 | U40: 115.4 | V40: 111.6 | W40: 112.2 | X40: 112.3 | Y40: 110.3 | Z40: 110.7 | AA40: 109.7 | AB40: 111.6 | AC40: 108.2 | AD40: 110.6 | AE40: 113.6 | AF40: =IF(AND(J40>150,K40>150),"Yes","No") -> No
A41: Rural | B41: 2014 | C41: February | D41: =B41&" "&C41 -> 2014 February | E41: 119.4 | F41: 117.7 | G41: 121.2 | H41: 115 | I41: 109 | J41: 116.6 | K41: 116 | L41: 109.8 | M41: 101.1 | N41: 110.4 | O41: 112.9 | P41: 117.8 | Q41: 115.3 | R41: 114.2 | S41: 117.1 | T41: 114.5 | U41: 116.7 | V41: NA | W41: 113.2 | X41: 112.9 | Y41: 110.9 | Z41: 110.8 | AA41: 109.9 | AB41: 112 | AC41: 108.7 | AD41: 110.9 | AE41: 114 | AF41: =IF(AND(J41>150,K41>150),"Yes","No") -> No
A42: Urban | B42: 2014 | C42: February | D42: =B42&" "&C42 -> 2014 February | E42: 121.9 | F42: 122 | G42: 124.5 | H42: 115.2 | I42: 102.5 | J42: 114.1 | K42: 111.5 | L42: 108.2 | M42: 95.4 | N42: 113.5 | O42: 112.1 | P42: 119.9 | Q42: 115.2 | R42: 116.2 | S42: 115.3 | T42: 111.7 | U42: 114.7 | V42: 112.5 | W42: 111.1 | X42: 112.6 | Y42: 110.4 | Z42: 111.3 | AA42: 110.3 | AB42: 111.6 | AC42: 108.7 | AD42: 111 | AE42: 113.1 | AF42: =IF(AND(J42>150,K42>150),"Yes","No") -> No
A43: Rural+Urban | B43: 2014 | C43: February | D43: =B43&" "&C43 -> 2014 February | E43: 120.2 | F43: 119.2 | G43: 122.5 | H43: 115.1 | I43: 106.6 | J43: 115.4 | K43: 114.5 | L43: 109.3 | M43: 99.2 | N43: 111.4 | O43: 112.6 | P43: 118.8 | Q43: 115.3 | R43: 114.7 | S43: 116.4 | T43: 113.3 | U43: 115.9 | V43: 112.5 | W43: 112.4 | X43: 112.8 | Y43: 110.7 | Z43: 111.1 | AA43: 110.1 | AB43: 111.8 | AC43: 108.7 | AD43: 110.9 | AE43: 113.6 | AF43: =IF(AND(J43>150,K43>150),"Yes","No") -> No
A44: Rural | B44: 2014 | C44: March | D44: =B44&" "&C44 -> 2014 March | E44: 120.1 | F44: 118.1 | G44: 120.7 | H44: 116.1 | I44: 109.3 | J44: 119.6 | K44: 117.9 | L44: 110.2 | M44: 101.2 | N44: 110.7 | O44: 113 | P44: 118.3 | Q44: 116.2 | R44: 114.6 | S44: 117.5 | T44: 114.9 | U44: 117.2 | V44: NA | W44: 113.4 | X44: 113.4 | Y44: 111.4 | Z44: 111.2 | AA44: 110.2 | AB44: 112.4 | AC44: 108.9 | AD44: 111.3 | AE44: 114.6 | AF44: =IF(AND(J44>150,K44>150),"Yes","No") -> No
A45: Urban | B45: 2014 | C45: March | D45: =B45&" "&C45 -> 2014 March | E45: 122.1 | F45: 121.4 | G45: 121.5 | H45: 116.2 | I45: 102.8 | J45: 117.7 | K45: 113.3 | L45: 108.9 | M45: 96.3 | N45: 114.1 | O45: 112.2 | P45: 120.5 | Q45: 116 | R45: 116.7 | S45: 115.8 | T45: 112.1 | U45: 115.2 | V45: 113.2 | W45: 110.9 | X45: 113 | Y45: 110.8 | Z45: 111.6 | AA45: 110.9 | AB45: 111.8 | AC45: 109.2 | AD45: 111.4 | AE45: 113.7 | AF45: =IF(AND(J45>150,K45>150),"Yes","No") -> No
A46: Rural+Urban | B46: 2014 | C46: Marcrh | D46: =B46&" "&C46 -> 2014 Marcrh | E46: 120.7 | F46: 119.3 | G46: 121 | H46: 116.1 | I46: 106.9 | J46: 118.7 | K46: 116.3 | L46: 109.8 | M46: 99.6 | N46: 111.8 | O46: 112.7 | P46: 119.3 | Q46: 116.1 | R46: 115.2 | S46: 116.8 | T46: 113.7 | U46: 116.4 | V46: 113.2 | W46: 112.5 | X46: 113.2 | Y46: 111.2 | Z46: 111.4 | AA46: 110.6 | AB46: 112 | AC46: 109 | AD46: 111.3 | AE46: 114.2 | AF46: =IF(AND(J46>150,K46>150),"Yes","No") -> No
A47: Rural | B47: 2014 | C47: April | D47: =B47&" "&C47 -> 2014 April | E47: 120.2 | F47: 118.9 | G47: 118.1 | H47: 117 | I47: 109.7 | J47: 125.5 | K47: 120.5 | L47: 111 | M47: 102.6 | N47: 111.2 | O47: 113.5 | P47: 118.7 | Q47: 117.2 | R47: 115.4 | S47: 118.1 | T47: 116.1 | U47: 117.8 | V47: NA | W47: 113.4 | X47: 113.7 | Y47: 111.8 | Z47: 111.2 | AA47: 110.5 | AB47: 113 | AC47: 108.9 | AD47: 111.5 | AE47: 115.4 | AF47: =IF(AND(J47>150,K47>150),"Yes","No") -> No
A48: Urban | B48: 2014 | C48: April | D48: =B48&" "&C48 -> 2014 April | E48: 122.5 | F48: 121.7 | G48: 113.3 | H48: 117 | I48: 103.1 | J48: 126.7 | K48: 121.2 | L48: 111 | M48: 100.3 | N48: 115.3 | O48: 112.7 | P48: 121 | Q48: 118.2 | R48: 117.6 | S48: 116.3 | T48: 112.5 | U48: 115.7 | V48: 113.9 | W48: 110.9 | X48: 113.4 | Y48: 111 | Z48: 111.2 | AA48: 111.2 | AB48: 112.5 | AC48: 109.1 | AD48: 111.4 | AE48: 114.7 | AF48: =IF(AND(J48>150,K48>150),"Yes","No") -> No
A49: Rural+Urban | B49: 2014 | C49: April | D49: =B49&" "&C49 -> 2014 April | E49: 120.9 | F49: 119.9 | G49: 116.2 | H49: 117 | I49: 107.3 | J49: 126.1 | K49: 120.7 | L49: 111 | M49: 101.8 | N49: 112.6 | O49: 113.2 | P49: 119.8 | Q49: 117.6 | R49: 116 | S49: 117.4 | T49: 114.6 | U49: 117 | V49: 113.9 | W49: 112.5 | X49: 113.6 | Y49: 111.5 | Z49: 111.2 | AA49: 110.9 | AB49: 112.7 | AC49: 109 | AD49: 111.5 | AE49: 115.1 | AF49: =IF(AND(J49>150,K49>150),"Yes","No") -> No
A50: Rural | B50: 2014 | C50: May | D50: =B50&" "&C50 -> 2014 May | E50: 120.3 | F50: 120.2 | G50: 116.9 | H50: 118 | I50: 110.1 | J50: 126.3 | K50: 123.9 | L50: 111.5 | M50: 103.5 | N50: 111.6 | O50: 114.2 | P50: 119.2 | Q50: 118.2 | R50: 116.3 | S50: 118.7 | T50: 116.8 | U50: 118.5 | V50: NA | W50: 113.4 | X50: 114.1 | Y50: 112.1 | Z50: 111.4 | AA50: 110.9 | AB50: 113.1 | AC50: 108.9 | AD50: 111.8 | AE50: 116 | AF50: =IF(AND(J50>150,K50>150),"Yes","No") -> No
A51: Urban | B51: 2014 | C51: May | D51: =B51&" "&C51 -> 2014 May | E51: 122.7 | F51: 124.1 | G51: 114.2 | H51: 119.1 | I51: 103.5 | J51: 129.2 | K51: 127 | L51: 112.6 | M51: 101.3 | N51: 117 | O51: 112.9 | P51: 121.7 | Q51: 120 | R51: 118.3 | S51: 116.8 | T51: 112.9 | U51: 116.2 | V51: 114.3 | W51: 111.1 | X51: 114.1 | Y51: 111.2 | Z51: 111.3 | AA51: 111.5 | AB51: 112.9 | AC51: 109.3 | AD51: 111.7 | AE51: 115.6 | AF51: =IF(AND(J51>150,K51>150),"Yes","No") -> No
A52: Rural+Urban | B52: 2014 | C52: May | D52: =B52&" "&C52 -> 2014 May | E52: 121.1 | F52: 121.6 | G52: 115.9 | H52: 118.4 | I52: 107.7 | J52: 127.7 | K52: 125 | L52: 111.9 | M52: 102.8 | N52: 113.4 | O52: 113.7 | P52: 120.4 | Q52: 118.9 | R52: 116.8 | S52: 118 | T52: 115.2 | U52: 117.6 | V52: 114.3 | W52: 112.5 | X52: 114.1 | Y52: 111.8 | Z52: 111.3 | AA52: 111.2 | AB52: 113 | AC52: 109.1 | AD52: 111.8 | AE52: 115.8 | AF52: =IF(AND(J52>150,K52>150),"Yes","No") -> No
A53: Rural | B53: 2014 | C53: June | D53: =B53&" "&C53 -> 2014 June | E53: 120.7 | F53: 121.6 | G53: 116.1 | H53: 119.3 | I53: 110.3 | J53: 125.8 | K53: 129.3 | L53: 112.2 | M53: 103.6 | N53: 112.3 | O53: 114.9 | P53: 120.1 | Q53: 119.5 | R53: 117.3 | S53: 119.7 | T53: 117.3 | U53: 119.3 | V53: NA | W53: 114.4 | X53: 114.9 | Y53: 112.8 | Z53: 112.2 | AA53: 111.4 | AB53: 114.3 | AC53: 108 | AD53: 112.3 | AE53: 117 | AF53: =IF(AND(J53>150,K53>150),"Yes","No") -> No
A54: Urban | B54: 2014 | C54: June | D54: =B54&" "&C54 -> 2014 June | E54: 123.1 | F54: 125.9 | G54: 115.4 | H54: 120.4 | I54: 103.4 | J54: 131.2 | K54: 137.5 | L54: 112.8 | M54: 101.4 | N54: 118.3 | O54: 113.2 | P54: 122.4 | Q54: 122 | R54: 119 | S54: 117.4 | T54: 113.2 | U54: 116.7 | V54: 113.9 | W54: 111.2 | X54: 114.3 | Y54: 111.4 | Z54: 111.5 | AA54: 111.8 | AB54: 115.1 | AC54: 108.7 | AD54: 112.2 | AE54: 116.4 | AF54: =IF(AND(J54>150,K54>150),"Yes","No") -> No
A55: Rural+Urban | B55: 2014 | C55: June | D55: =B55&" "&C55 -> 2014 June | E55: 121.5 | F55: 123.1 | G55: 115.8 | H55: 119.7 | I55: 107.8 | J55: 128.3 | K55: 132.1 | L55: 112.4 | M55: 102.9 | N55: 114.3 | O55: 114.2 | P55: 121.2 | Q55: 120.4 | R55: 117.8 | S55: 118.8 | T55: 115.6 | U55: 118.3 | V55: 113.9 | W55: 113.2 | X55: 114.6 | Y55: 112.3 | Z55: 111.8 | AA55: 111.6 | AB55: 114.8 | AC55: 108.3 | AD55: 112.3 | AE55: 116.7 | AF55: =IF(AND(J55>150,K55>150),"Yes","No") -> No
A56: Rural | B56: 2014 | C56: July | D56: =B56&" "&C56 -> 2014 July | E56: 121.7 | F56: 122.5 | G56: 117.7 | H56: 120.6 | I56: 110.4 | J56: 129.1 | K56: 150.1 | L56: 113.2 | M56: 104.8 | N56: 113.3 | O56: 115.6 | P56: 120.9 | Q56: 123.3 | R56: 118 | S56: 120.7 | T56: 118.3 | U56: 120.3 | V56: NA | W56: 115.3 | X56: 115.4 | Y56: 113.4 | Z56: 113.2 | AA56: 111.8 | AB56: 115.5 | AC56: 108.8 | AD56: 113.1 | AE56: 119.5 | AF56: =IF(AND(J56>150,K56>150),"Yes","No") -> No
A57: Urban | B57: 2014 | C57: July | D57: =B57&" "&C57 -> 2014 July | E57: 123.8 | F57: 126.4 | G57: 118 | H57: 121.6 | I57: 103.5 | J57: 133.7 | K57: 172.4 | L57: 113.1 | M57: 102.7 | N57: 120 | O57: 113.8 | P57: 123.4 | Q57: 127.1 | R57: 121 | S57: 118 | T57: 113.6 | U57: 117.4 | V57: 114.8 | W57: 111.6 | X57: 114.9 | Y57: 111.5 | Z57: 113 | AA57: 112.4 | AB57: 117.8 | AC57: 109.7 | AD57: 113.5 | AE57: 118.9 | AF57: =IF(AND(J57>150,K57>150),"Yes","No") -> No
A58: Rural+Urban | B58: 2014 | C58: July | D58: =B58&" "&C58 -> 2014 July | E58: 122.4 | F58: 123.9 | G58: 117.8 | H58: 121 | I58: 107.9 | J58: 131.2 | K58: 157.7 | L58: 113.2 | M58: 104.1 | N58: 115.5 | O58: 114.8 | P58: 122.1 | Q58: 124.7 | R58: 118.8 | S58: 119.6 | T58: 116.3 | U58: 119.1 | V58: 114.8 | W58: 113.9 | X58: 115.2 | Y58: 112.7 | Z58: 113.1 | AA58: 112.1 | AB58: 116.8 | AC58: 109.2 | AD58: 113.3 | AE58: 119.2 | AF58: =IF(AND(J58>150,K58>150),"Yes","No") -> No
A59: Rural | B59: 2014 | C59: August | D59: =B59&" "&C59 -> 2014 August | E59: 121.8 | F59: 122.8 | G59: 117.8 | H59: 121.9 | I59: 110.6 | J59: 129.7 | K59: 161.1 | L59: 114.1 | M59: 105.1 | N59: 114.6 | O59: 115.8 | P59: 121.7 | Q59: 125.3 | R59: 118.8 | S59: 120.9 | T59: 118.8 | U59: 120.7 | V59: NA | W59: 115.4 | X59: 115.9 | Y59: 114 | Z59: 113.2 | AA59: 112.2 | AB59: 116.2 | AC59: 109.4 | AD59: 113.5 | AE59: 120.7 | AF59: =IF(AND(J59>150,K59>150),"Yes","No") -> No
A60: Urban | B60: 2014 | C60: August | D60: =B60&" "&C60 -> 2014 August | E60: 124.8 | F60: 127.3 | G60: 116.5 | H60: 122.2 | I60: 103.6 | J60: 132.7 | K60: 181.9 | L60: 115.2 | M60: 102.7 | N60: 122.1 | O60: 114.4 | P60: 124.7 | Q60: 128.9 | R60: 123 | S60: 118.6 | T60: 114.1 | U60: 117.9 | V60: 115.5 | W60: 111.8 | X60: 115.3 | Y60: 112.2 | Z60: 112.5 | AA60: 112.9 | AB60: 119.2 | AC60: 110.5 | AD60: 113.9 | AE60: 119.9 | AF60: =IF(AND(J60>150,K60>150),"Yes","No") -> No
A61: Rural+Urban | B61: 2014 | C61: August | D61: =B61&" "&C61 -> 2014 August | E61: 122.7 | F61: 124.4 | G61: 117.3 | H61: 122 | I61: 108 | J61: 131.1 | K61: 168.2 | L61: 114.5 | M61: 104.3 | N61: 117.1 | O61: 115.2 | P61: 123.1 | Q61: 126.6 | R61: 119.9 | S61: 120 | T61: 116.8 | U61: 119.6 | V61: 115.5 | W61: 114 | X61: 115.6 | Y61: 113.3 | Z61: 112.8 | AA61: 112.6 | AB61: 118 | AC61: 109.9 | AD61: 113.7 | AE61: 120.3 | AF61: =IF(AND(J61>150,K61>150),"Yes","No") -> No
A62: Rural | B62: 2014 | C62: September | D62: =B62&" "&C62 -> 2014 September | E62: 122.3 | F62: 122.4 | G62: 117.8 | H62: 122.7 | I62: 110.4 | J62: 129.8 | K62: 158.8 | L62: 115 | M62: 104.7 | N62: 114.9 | O62: 116.5 | P62: 122.6 | Q62: 125.3 | R62: 119.5 | S62: 121.7 | T62: 119.2 | U62: 121.3 | V62: NA | W62: 115.8 | X62: 116.7 | Y62: 114.5 | Z62: 112.8 | AA62: 112.6 | AB62: 116.6 | AC62: 109.1 | AD62: 113.7 | AE62: 120.9 | AF62: =IF(AND(J62>150,K62>150),"Yes","No") -> No
A63: Urban | B63: 2014 | C63: September | D63: =B63&" "&C63 -> 2014 September | E63: 124.2 | F63: 125.4 | G63: 116.4 | H63: 122.7 | I63: 103.5 | J63: 124.5 | K63: 168.6 | L63: 116.9 | M63: 101.9 | N63: 122.9 | O63: 114.8 | P63: 125.2 | Q63: 126.7 | R63: 124.3 | S63: 119.2 | T63: 114.5 | U63: 118.4 | V63: 116.1 | W63: 111.8 | X63: 115.5 | Y63: 112.3 | Z63: 111.2 | AA63: 113.4 | AB63: 120 | AC63: 110 | AD63: 113.6 | AE63: 119.2 | AF63: =IF(AND(J63>150,K63>150),"Yes","No") -> No
A64: Rural+Urban | B64: 2014 | C64: September | D64: =B64&" "&C64 -> 2014 September | E64: 122.9 | F64: 123.5 | G64: 117.3 | H64: 122.7 | I64: 107.9 | J64: 127.3 | K64: 162.1 | L64: 115.6 | M64: 103.8 | N64: 117.6 | O64: 115.8 | P64: 123.8 | Q64: 125.8 | R64: 120.8 | S64: 120.7 | T64: 117.2 | U64: 120.1 | V64: 116.1 | W64: 114.3 | X64: 116.1 | Y64: 113.7 | Z64: 112 | AA64: 113.1 | AB64: 118.6 | AC64: 109.5 | AD64: 113.7 | AE64: 120.1 | AF64: =IF(AND(J64>150,K64>150),"Yes","No") -> No
A65: Rural | B65: 2014 | C65: October | D65: =B65&" "&C65 -> 2014 October | E65: 122.6 | F65: 122.5 | G65: 118.3 | H65: 123.2 | I65: 110.5 | J65: 128.9 | K65: 155.3 | L65: 115.5 | M65: 104 | N65: 115.3 | O65: 116.8 | P65: 123.2 | Q65: 125.1 | R65: 120 | S65: 122.7 | T65: 120.3 | U65: 122.3 | V65: NA | W65: 116.4 | X65: 117.5 | Y65: 115.3 | Z65: 112.6 | AA65: 113 | AB65: 116.9 | AC65: 109.3 | AD65: 114 | AE65: 121 | AF65: =IF(AND(J65>150,K65>150),"Yes","No") -> No
A66: Urban | B66: 2014 | C66: October | D66: =B66&" "&C66 -> 2014 October | E66: 124.6 | F66: 126.1 | G66: 117.8 | H66: 123.1 | I66: 103.5 | J66: 123.5 | K66: 159.6 | L66: 117.4 | M66: 101.2 | N66: 123.8 | O66: 115.2 | P66: 125.9 | Q66: 125.8 | R66: 124.3 | S66: 119.6 | T66: 114.9 | U66: 118.9 | V66: 116.7 | W66: 112 | X66: 115.8 | Y66: 112.6 | Z66: 111 | AA66: 113.6 | AB66: 120.2 | AC66: 110.1 | AD66: 113.7 | AE66: 119.1 | AF66: =IF(AND(J66>150,K66>150),"Yes","No") -> No
A67: Rural+Urban | B67: 2014 | C67: October | D67: =B67&" "&C67 -> 2014 October | E67: 123.2 | F67: 123.8 | G67: 118.1 | H67: 123.2 | I67: 107.9 | J67: 126.4 | K67: 156.8 | L67: 116.1 | M67: 103.1 | N67: 118.1 | O67: 116.1 | P67: 124.5 | Q67: 125.4 | R67: 121.1 | S67: 121.5 | T67: 118.1 | U67: 121 | V67: 116.7 | W67: 114.7 | X67: 116.7 | Y67: 114.3 | Z67: 111.8 | AA67: 113.3 | AB67: 118.8 | AC67: 109.6 | AD67: 113.9 | AE67: 120.1 | AF67: =IF(AND(J67>150,K67>150),"Yes","No") -> No
A68: Rural | B68: 2014 | C68: November | D68: =B68&" "&C68 -> 2014 November | E68: 122.7 | F68: 122.6 | G68: 119.9 | H68: 124 | I68: 110.5 | J68: 128.8 | K68: 152 | L68: 116.2 | M68: 103.3 | N68: 115.8 | O68: 116.8 | P68: 124.5 | Q68: 124.9 | R68: 120.8 | S68: 123.3 | T68: 120.5 | U68: 122.9 | V68: NA | W68: 117.3 | X68: 118.1 | Y68: 115.9 | Z68: 112 | AA68: 113.3 | AB68: 117.2 | AC68: 108.8 | AD68: 114.1 | AE68: 121.1 | AF68: =IF(AND(J68>150,K68>150),"Yes","No") -> No
A69: Urban | B69: 2014 | C69: November | D69: =B69&" "&C69 -> 2014 November | E69: 124.5 | F69: 125.6 | G69: 122.7 | H69: 124.6 | I69: 103.2 | J69: 122.2 | K69: 153.2 | L69: 119.3 | M69: 99.8 | N69: 124.6 | O69: 115.8 | P69: 126.9 | Q69: 125.4 | R69: 125.8 | S69: 120.3 | T69: 115.4 | U69: 119.5 | V69: 117.1 | W69: 112.6 | X69: 116.4 | Y69: 113 | Z69: 109.7 | AA69: 114 | AB69: 120.3 | AC69: 109.6 | AD69: 113.4 | AE69: 119 | AF69: =IF(AND(J69>150,K69>150),"Yes","No") -> No
A70: Rural+Urban | B70: 2014 | C70: November | D70: =B70&" "&C70 -> 2014 November | E70: 123.3 | F70: 123.7 | G70: 121 | H70: 124.2 | I70: 107.8 | J70: 125.7 | K70: 152.4 | L70: 117.2 | M70: 102.1 | N70: 118.7 | O70: 116.4 | P70: 125.6 | Q70: 125.1 | R70: 122.1 | S70: 122.1 | T70: 118.4 | U70: 121.6 | V70: 117.1 | W70: 115.5 | X70: 117.3 | Y70: 114.8 | Z70: 110.8 | AA70: 113.7 | AB70: 119 | AC70: 109.1 | AD70: 113.8 | AE70: 120.1 | AF70: =IF(AND(J70>150,K70>150),"Yes","No") -> No
A71: Rural | B71: 2014 | C71: December | D71: =B71&" "&C71 -> 2014 December | E71: 122.4 | F71: 122.4 | G71: 121.8 | H71: 124.2 | I71: 110.2 | J71: 128.6 | K71: 140.3 | L71: 116.3 | M71: 102 | N71: 116 | O71: 117.3 | P71: 124.8 | Q71: 123.3 | R71: 121.7 | S71: 123.8 | T71: 120.6 | U71: 123.3 | V71: NA | W71: 117.4 | X71: 118.2 | Y71: 116.2 | Z71: 111.5 | AA71: 113.3 | AB71: 117.7 | AC71: 109.4 | AD71: 114.2 | AE71: 120.3 | AF71: =IF(AND(J71>150,K71>150),"Yes","No") -> No
A72: Urban | B72: 2014 | C72: December | D72: =B72&" "&C72 -> 2014 December | E72: 124 | F72: 124.7 | G72: 126.3 | H72: 124.9 | I72: 103 | J72: 122.3 | K72: 141 | L72: 120.1 | M72: 97.8 | N72: 125.4 | O72: 116.1 | P72: 127.6 | Q72: 124 | R72: 126.4 | S72: 120.7 | T72: 115.8 | U72: 120 | V72: 116.5 | W72: 113 | X72: 116.8 | Y72: 113.2 | Z72: 108.8 | AA72: 114.3 | AB72: 120.7 | AC72: 110.4 | AD72: 113.4 | AE72: 118.4 | AF72: =IF(AND(J72>150,K72>150),"Yes","No") -> No
A73: Rural+Urban | B73: 2014 | C73: December | D73: =B73&" "&C73 -> 2014 December | E73: 122.9 | F73: 123.2 | G73: 123.5 | H73: 124.5 | I73: 107.6 | J73: 125.7 | K73: 140.5 | L73: 117.6 | M73: 100.6 | N73: 119.1 | O73: 116.8 | P73: 126.1 | Q73: 123.6 | R73: 123 | S73: 122.6 | T73: 118.6 | U73: 122 | V73: 116.5 | W73: 115.7 | X73: 117.5 | Y73: 115.1 | Z73: 110.1 | AA73: 113.9 | AB73: 119.5 | AC73: 109.8 | AD73: 113.8 | AE73: 119.4 | AF73: =IF(AND(J73>150,K73>150),"Yes","No") -> No
A74: Rural | B74: 2015 | C74: January | D74: =B74&" "&C74 -> 2015 January | E74: 123.1 | F74: 123.1 | G74: 122.1 | H74: 124.9 | I74: 111 | J74: 130.4 | K74: 132.3 | L74: 117.2 | M74: 100.5 | N74: 117.2 | O74: 117.9 | P74: 125.6 | Q74: 122.8 | R74: 122.7 | S74: 124.4 | T74: 121.6 | U74: 124 | V74: NA | W74: 118.4 | X74: 118.9 | Y74: 116.6 | Z74: 111 | AA74: 114 | AB74: 118.2 | AC74: 110.2 | AD74: 114.5 | AE74: 120.3 | AF74: =IF(AND(J74>150,K74>150),"Yes","No") -> No
A75: Urban | B75: 2015 | C75: January | D75: =B75&" "&C75 -> 2015 January | E75: 124 | F75: 125.5 | G75: 126.6 | H75: 125.2 | I75: 104.3 | J75: 121.3 | K75: 134.4 | L75: 122.9 | M75: 96.1 | N75: 126.6 | O75: 116.5 | P75: 128 | Q75: 123.5 | R75: 127.4 | S75: 121 | T75: 116.1 | U75: 120.2 | V75: 117.3 | W75: 113.4 | X75: 117.2 | Y75: 113.7 | Z75: 107.9 | AA75: 114.6 | AB75: 120.8 | AC75: 111.4 | AD75: 113.4 | AE75: 118.5 | AF75: =IF(AND(J75>150,K75>150),"Yes","No") -> No
A76: Rural+Urban | B76: 2015 | C76: January | D76: =B76&" "&C76 -> 2015 January | E76: 123.4 | F76: 123.9 | G76: 123.8 | H76: 125 | I76: 108.5 | J76: 126.2 | K76: 133 | L76: 119.1 | M76: 99 | N76: 120.3 | O76: 117.3 | P76: 126.7 | Q76: 123.1 | R76: 124 | S76: 123.1 | T76: 119.3 | U76: 122.5 | V76: 117.3 | W76: 116.5 | X76: 118.1 | Y76: 115.5 | Z76: 109.4 | AA76: 114.3 | AB76: 119.7 | AC76: 110.7 | AD76: 114 | AE76: 119.5 | AF76: =IF(AND(J76>150,K76>150),"Yes","No") -> No
A77: Rural | B77: 2015 | C77: February | D77: =B77&" "&C77 -> 2015 February | E77: 123.4 | F77: 124.4 | G77: 122.1 | H77: 125.8 | I77: 111.5 | J77: 129.4 | K77: 128.2 | L77: 118.8 | M77: 100 | N77: 118.6 | O77: 118.8 | P77: 126.8 | Q77: 122.8 | R77: 124.2 | S77: 125.4 | T77: 122.7 | U77: 125 | V77: NA | W77: 120 | X77: 119.6 | Y77: 117.7 | Z77: 110.9 | AA77: 114.8 | AB77: 118.7 | AC77: 110.8 | AD77: 115 | AE77: 120.6 | AF77: =IF(AND(J77>150,K77>150),"Yes","No") -> No
A78: Urban | B78: 2015 | C78: February | D78: =B78&" "&C78 -> 2015 February | E78: 124.3 | F78: 126.5 | G78: 119.5 | H78: 125.6 | I78: 104.9 | J78: 121.6 | K78: 131.8 | L78: 125.1 | M78: 95 | N78: 127.7 | O78: 116.8 | P78: 128.6 | Q78: 123.7 | R78: 128.1 | S78: 121.3 | T78: 116.5 | U78: 120.6 | V78: 118.1 | W78: 114 | X78: 117.7 | Y78: 114.1 | Z78: 106.8 | AA78: 114.9 | AB78: 120.4 | AC78: 111.7 | AD78: 113.2 | AE78: 118.7 | AF78: =IF(AND(J78>150,K78>150),"Yes","No") -> No
A79: Rural+Urban | B79: 2015 | C79: February | D79: =B79&" "&C79 -> 2015 February | E79: 123.7 | F79: 125.1 | G79: 121.1 | H79: 125.7 | I79: 109.1 | J79: 125.8 | K79: 129.4 | L79: 120.9 | M79: 98.3 | N79: 121.6 | O79: 118 | P79: 127.6 | Q79: 123.1 | R79: 125.2 | S79: 123.8 | T79: 120.1 | U79: 123.3 | V79: 118.1 | W79: 117.7 | X79: 118.7 | Y79: 116.3 | Z79: 108.7 | AA79: 114.9 | AB79: 119.7 | AC79: 111.2 | AD79: 114.1 | AE79: 119.7 | AF79: =IF(AND(J79>150,K79>150),"Yes","No") -> No
A80: Rural | B80: 2015 | C80: March | D80: =B80&" "&C80 -> 2015 March | E80: 123.3 | F80: 124.7 | G80: 118.9 | H80: 126 | I80: 111.8 | J80: 130.9 | K80: 128 | L80: 119.9 | M80: 98.9 | N80: 119.4 | O80: 118.9 | P80: 127.7 | Q80: 123.1 | R80: 124.7 | S80: 126 | T80: 122.9 | U80: 125.5 | V80: NA | W80: 120.6 | X80: 120.2 | Y80: 118.2 | Z80: 111.6 | AA80: 115.5 | AB80: 119.4 | AC80: 110.8 | AD80: 115.5 | AE80: 121.1 | AF80: =IF(AND(J80>150,K80>150),"Yes","No") -> No
A81: Urban | B81: 2015 | C81: March | D81: =B81&" "&C81 -> 2015 March | E81: 124 | F81: 126.7 | G81: 113.5 | H81: 125.9 | I81: 104.8 | J81: 123.8 | K81: 131.4 | L81: 127.2 | M81: 93.2 | N81: 127.4 | O81: 117 | P81: 129.2 | Q81: 123.9 | R81: 128.8 | S81: 121.7 | T81: 116.9 | U81: 120.9 | V81: 118.6 | W81: 114.4 | X81: 118 | Y81: 114.3 | Z81: 108.4 | AA81: 115.4 | AB81: 120.6 | AC81: 111.3 | AD81: 113.8 | AE81: 119.1 | AF81: =IF(AND(J81>150,K81>150),"Yes","No") -> No
A82: Rural+Urban | B82: 2015 | C82: March | D82: =B82&" "&C82 -> 2015 March | E82: 123.5 | F82: 125.4 | G82: 116.8 | H82: 126 | I82: 109.2 | J82: 127.6 | K82: 129.2 | L82: 122.4 | M82: 97 | N82: 122.1 | O82: 118.1 | P82: 128.4 | Q82: 123.4 | R82: 125.8 | S82: 124.3 | T82: 120.4 | U82: 123.7 | V82: 118.6 | W82: 118.3 | X82: 119.2 | Y82: 116.7 | Z82: 109.9 | AA82: 115.4 | AB82: 120.1 | AC82: 111 | AD82: 114.7 | AE82: 120.2 | AF82: =IF(AND(J82>150,K82>150),"Yes","No") -> No
A83: Rural | B83: 2015 | C83: April | D83: =B83&" "&C83 -> 2015 April | E83: 123.3 | F83: 125.5 | G83: 117.2 | H83: 126.8 | I83: 111.9 | J83: 134.2 | K83: 127.5 | L83: 121.5 | M83: 97.8 | N83: 119.8 | O83: 119.4 | P83: 128.7 | Q83: 123.6 | R83: 125.7 | S83: 126.4 | T83: 123.3 | U83: 126 | V83: NA | W83: 121.2 | X83: 120.9 | Y83: 118.6 | Z83: 111.9 | AA83: 116.2 | AB83: 119.9 | AC83: 111.6 | AD83: 116 | AE83: 121.5 | AF83: =IF(AND(J83>150,K83>150),"Yes","No") -> No
A84: Urban | B84: 2015 | C84: April | D84: =B84&" "&C84 -> 2015 April | E84: 123.8 | F84: 128.2 | G84: 110 | H84: 126.3 | I84: 104.5 | J84: 130.6 | K84: 130.8 | L84: 131.3 | M84: 91.6 | N84: 127.7 | O84: 117.2 | P84: 129.5 | Q84: 124.6 | R84: 130.1 | S84: 122.1 | T84: 117.2 | U84: 121.3 | V84: 119.2 | W84: 114.7 | X84: 118.4 | Y84: 114.6 | Z84: 108.4 | AA84: 115.6 | AB84: 121.7 | AC84: 111.8 | AD84: 114.2 | AE84: 119.7 | AF84: =IF(AND(J84>150,K84>150),"Yes","No") -> No
A85: Rural+Urban | B85: 2015 | C85: April | D85: =B85&" "&C85 -> 2015 April | E85: 123.5 | F85: 126.4 | G85: 114.4 | H85: 126.6 | I85: 109.2 | J85: 132.5 | K85: 128.6 | L85: 124.8 | M85: 95.7 | N85: 122.4 | O85: 118.5 | P85: 129.1 | Q85: 124 | R85: 126.9 | S85: 124.7 | T85: 120.8 | U85: 124.1 | V85: 119.2 | W85: 118.7 | X85: 119.7 | Y85: 117.1 | Z85: 110.1 | AA85: 115.9 | AB85: 121 | AC85: 111.7 | AD85: 115.1 | AE85: 120.7 | AF85: =IF(AND(J85>150,K85>150),"Yes","No") -> No
A86: Rural | B86: 2015 | C86: May | D86: =B86&" "&C86 -> 2015 May | E86: 123.5 | F86: 127.1 | G86: 117.3 | H86: 127.7 | I86: 112.5 | J86: 134.1 | K86: 128.5 | L86: 124.3 | M86: 97.6 | N86: 120.7 | O86: 120.2 | P86: 129.8 | Q86: 124.4 | R86: 126.7 | S86: 127.3 | T86: 124.1 | U86: 126.8 | V86: NA | W86: 121.9 | X86: 121.5 | Y86: 119.4 | Z86: 113.3 | AA86: 116.7 | AB86: 120.5 | AC86: 112.3 | AD86: 116.9 | AE86: 122.4 | AF86: =IF(AND(J86>150,K86>150),"Yes","No") -> No
A87: Urban | B87: 2015 | C87: May | D87: =B87&" "&C87 -> 2015 May | E87: 123.8 | F87: 129.7 | G87: 111.3 | H87: 126.6 | I87: 105.2 | J87: 130.8 | K87: 135.6 | L87: 142.6 | M87: 90.8 | N87: 128.8 | O87: 117.7 | P87: 129.9 | Q87: 126.1 | R87: 131.3 | S87: 122.4 | T87: 117.4 | U87: 121.6 | V87: 119.6 | W87: 114.9 | X87: 118.7 | Y87: 114.9 | Z87: 110.8 | AA87: 116 | AB87: 122 | AC87: 112.4 | AD87: 115.2 | AE87: 120.7 | AF87: =IF(AND(J87>150,K87>150),"Yes","No") -> No
A88: Rural+Urban | B88: 2015 | C88: May | D88: =B88&" "&C88 -> 2015 May | E88: 123.6 | F88: 128 | G88: 115 | H88: 127.3 | I88: 109.8 | J88: 132.6 | K88: 130.9 | L88: 130.5 | M88: 95.3 | N88: 123.4 | O88: 119.2 | P88: 129.8 | Q88: 125 | R88: 127.9 | S88: 125.4 | T88: 121.3 | U88: 124.7 | V88: 119.6 | W88: 119.2 | X88: 120.2 | Y88: 117.7 | Z88: 112 | AA88: 116.3 | AB88: 121.4 | AC88: 112.3 | AD88: 116.1 | AE88: 121.6 | AF88: =IF(AND(J88>150,K88>150),"Yes","No") -> No
A89: Rural | B89: 2015 | C89: June | D89: =B89&" "&C89 -> 2015 June | E89: 124.1 | F89: 130.4 | G89: 122.1 | H89: 128.7 | I89: 114.1 | J89: 133.2 | K89: 135.2 | L89: 131.9 | M89: 96.3 | N89: 123 | O89: 121.1 | P89: 131.2 | Q89: 126.6 | R89: 128.2 | S89: 128.4 | T89: 125.1 | U89: 128 | V89: NA | W89: 122.6 | X89: 122.8 | Y89: 120.4 | Z89: 114.2 | AA89: 117.9 | AB89: 122 | AC89: 113 | AD89: 117.9 | AE89: 124.1 | AF89: =IF(AND(J89>150,K89>150),"Yes","No") -> No
A90: Urban | B90: 2015 | C90: June | D90: =B90&" "&C90 -> 2015 June | E90: 123.6 | F90: 134.4 | G90: 120.9 | H90: 127.3 | I90: 106 | J90: 132.3 | K90: 146.7 | L90: 148.1 | M90: 89.8 | N90: 130.5 | O90: 118 | P90: 130.5 | Q90: 128.5 | R90: 132.1 | S90: 123.2 | T90: 117.6 | U90: 122.3 | V90: 119 | W90: 115.1 | X90: 119.2 | Y90: 115.4 | Z90: 111.7 | AA90: 116.2 | AB90: 123.8 | AC90: 112.5 | AD90: 116 | AE90: 121.7 | AF90: =IF(AND(J90>150,K90>150),"Yes","No") -> No
A91: Rural+Urban | B91: 2015 | C91: June | D91: =B91&" "&C91 -> 2015 June | E91: 123.9 | F91: 131.8 | G91: 121.6 | H91: 128.2 | I91: 111.1 | J91: 132.8 | K91: 139.1 | L91: 137.4 | M91: 94.1 | N91: 125.5 | O91: 119.8 | P91: 130.9 | Q91: 127.3 | R91: 129.2 | S91: 126.4 | T91: 122 | U91: 125.7 | V91: 119 | W91: 119.8 | X91: 121.1 | Y91: 118.5 | Z91: 112.9 | AA91: 116.9 | AB91: 123.1 | AC91: 112.8 | AD91: 117 | AE91: 123 | AF91: =IF(AND(J91>150,K91>150),"Yes","No") -> No
A92: Rural | B92: 2015 | C92: July | D92: =B92&" "&C92 -> 2015 July | E92: 124 | F92: 131.5 | G92: 122 | H92: 128.7 | I92: 113.5 | J92: 133.3 | K92: 140.8 | L92: 133.8 | M92: 94.1 | N92: 123.4 | O92: 121 | P92: 131.7 | Q92: 127.5 | R92: 129.4 | S92: 128.8 | T92: 125.5 | U92: 128.3 | V92: NA | W92: 123 | X92: 123 | Y92: 120.8 | Z92: 114.1 | AA92: 118 | AB92: 122.9 | AC92: 112.7 | AD92: 118.1 | AE92: 124.7 | AF92: =IF(AND(J92>150,K92>150),"Yes","No") -> No
A93: Urban | B93: 2015 | C93: July | D93: =B93&" "&C93 -> 2015 July | E93: 123.2 | F93: 134.3 | G93: 119.5 | H93: 127.7 | I93: 106.3 | J93: 132.8 | K93: 153.5 | L93: 149.5 | M93: 85.7 | N93: 131.5 | O93: 118.3 | P93: 131.1 | Q93: 129.5 | R93: 133.1 | S93: 123.5 | T93: 117.9 | U93: 122.7 | V93: 119.9 | W93: 115.3 | X93: 119.5 | Y93: 116 | Z93: 111.5 | AA93: 116.6 | AB93: 125.4 | AC93: 111.7 | AD93: 116.3 | AE93: 122.4 | AF93: =IF(AND(J93>150,K93>150),"Yes","No") -> No
A94: Rural+Urban | B94: 2015 | C94: July | D94: =B94&" "&C94 -> 2015 July | E94: 123.7 | F94: 132.5 | G94: 121 | H94: 128.3 | I94: 110.9 | J94: 133.1 | K94: 145.1 | L94: 139.1 | M94: 91.3 | N94: 126.1 | O94: 119.9 | P94: 131.4 | Q94: 128.2 | R94: 130.4 | S94: 126.7 | T94: 122.3 | U94: 126.1 | V94: 119.9 | W94: 120.1 | X94: 121.3 | Y94: 119 | Z94: 112.7 | AA94: 117.2 | AB94: 124.4 | AC94: 112.3 | AD94: 117.2 | AE94: 123.6 | AF94: =IF(AND(J94>150,K94>150),"Yes","No") -> No
A95: Rural | B95: 2015 | C95: August | D95: =B95&" "&C95 -> 2015 August | E95: 124.7 | F95: 131.3 | G95: 121.3 | H95: 128.8 | I95: 114 | J95: 134.2 | K95: 153.6 | L95: 137.9 | M95: 93.1 | N95: 123.9 | O95: 121.5 | P95: 132.5 | Q95: 129.8 | R95: 130.1 | S95: 129.5 | T95: 126.3 | U95: 129 | V95: NA | W95: 123.8 | X95: 123.7 | Y95: 121.1 | Z95: 113.6 | AA95: 118.5 | AB95: 123.6 | AC95: 112.5 | AD95: 118.2 | AE95: 126.1 | AF95: =IF(AND(J95>150,K95>150),"Yes","No") -> No
A96: Urban | B96: 2015 | C96: August | D96: =B96&" "&C96 -> 2015 August | E96: 123.1 | F96: 131.7 | G96: 118.1 | H96: 128 | I96: 106.8 | J96: 130.1 | K96: 165.5 | L96: 156 | M96: 85.3 | N96: 132.7 | O96: 118.8 | P96: 131.7 | Q96: 131.1 | R96: 134.2 | S96: 123.7 | T96: 118.2 | U96: 122.9 | V96: 120.9 | W96: 115.3 | X96: 120 | Y96: 116.6 | Z96: 109.9 | AA96: 117.2 | AB96: 126.2 | AC96: 112 | AD96: 116.2 | AE96: 123.2 | AF96: =IF(AND(J96>150,K96>150),"Yes","No") -> No
A97: Rural+Urban | B97: 2015 | C97: August | D97: =B97&" "&C97 -> 2015 August | E97: 124.2 | F97: 131.4 | G97: 120.1 | H97: 128.5 | I97: 111.4 | J97: 132.3 | K97: 157.6 | L97: 144 | M97: 90.5 | N97: 126.8 | O97: 120.4 | P97: 132.1 | Q97: 130.3 | R97: 131.2 | S97: 127.2 | T97: 122.9 | U97: 126.6 | V97: 120.9 | W97: 120.6 | X97: 122 | Y97: 119.4 | Z97: 111.7 | AA97: 117.8 | AB97: 125.1 | AC97: 112.3 | AD97: 117.2 | AE97: 124.8 | AF97: =IF(AND(J97>150,K97>150),"Yes","No") -> No
A98: Rural | B98: 2015 | C98: September | D98: =B98&" "&C98 -> 2015 September | E98: 125.1 | F98: 131.1 | G98: 120.7 | H98: 129.2 | I98: 114.7 | J98: 132.3 | K98: 158.9 | L98: 142.1 | M98: 92.5 | N98: 125.4 | O98: 121.9 | P98: 132.7 | Q98: 131 | R98: 131 | S98: 130.4 | T98: 126.8 | U98: 129.9 | V98: NA | W98: 123.7 | X98: 124.5 | Y98: 121.4 | Z98: 113.8 | AA98: 119.6 | AB98: 124.5 | AC98: 113.7 | AD98: 118.8 | AE98: 127 | AF98: =IF(AND(J98>150,K98>150),"Yes","No") -> No
A99: Urban | B99: 2015 | C99: September | D99: =B99&" "&C99 -> 2015 September | E99: 123.4 | F99: 129 | G99: 115.6 | H99: 128.3 | I99: 107 | J99: 124 | K99: 168.5 | L99: 165.4 | M99: 86.3 | N99: 134.4 | O99: 119.1 | P99: 132.3 | Q99: 131.5 | R99: 134.7 | S99: 124 | T99: 118.6 | U99: 123.2 | V99: 121.6 | W99: 115.1 | X99: 120.4 | Y99: 117.1 | Z99: 109.1 | AA99: 117.3 | AB99: 126.5 | AC99: 112.9 | AD99: 116.2 | AE99: 123.5 | AF99: =IF(AND(J99>150,K99>150),"Yes","No") -> No
A100: Rural+Urban | B100: 2015 | C100: September | D100: =B100&" "&C100 -> 2015 September | E100: 124.6 | F100: 130.4 | G100: 118.7 | H100: 128.9 | I100: 111.9 | J100: 128.4 | K100: 162.2 | L100: 150 | M100: 90.4 | N100: 128.4 | O100: 120.7 | P100: 132.5 | Q100: 131.2 | R100: 132 | S100: 127.9 | T100: 123.4 | U100: 127.2 | V100: 121.6 | W100: 120.4 | X100: 122.6 | Y100: 119.8 | Z100: 111.3 | AA100: 118.3 | AB100: 125.7 | AC100: 113.4 | AD100: 117.5 | AE100: 125.4 | AF100: =IF(AND(J100>150,K100>150),"Yes","No") -> No
...

Sheet Objective
B2: Objective
B4: The objective of this case study is to analyze India’s inflation patterns using Consumer Price Index (CPI) data
B5: The CPI tracks changes in the price of a fixed basket of goods and services over time and reflects inflation trends faced by Indian consumers.
B6: This project aims to: Identify the contribution of major CPI categories toward overall inflation
B7: Examine year-over-year inflation trends
B8: Evaluate food price inflation
B9: Assess the impact of COVID-19, and Analyze how global crude oil fluctuations influence India’s inflation.

Sheet Notes
B2: Data Summary
B3: Rows | C3: 372
B4: Columns | C4: 30
B5: Sectors | C5: Rural, Urban, Rural+Urban
B6: Blank/Null Values | C6: 243
B7: Time Line | C7: 2013 - 2023
B9: Calculation for Problem Statement | C9: Formula Used
B10: BROADER CATEGORY CONTRIBUTION ANALYSIS | C10: Contribution = ( (CPI index of Category)/TOTAL CPI Value )*100
B11: YOY Increase In Overall CPI For Rural + Urban | C11: YOY Inflation = ((Current Year - Previous Year)/Previous Year) *100
B12: MONTH OVER MONTH INLFATION OVER FOOD CATEGORIES | C12: MOM Inflation = ((Current Month - Previous Month)/Previous Month) *100
B13: CATEGORY WISE INFLATION OVER COVID PERIODS | C13: Periodic Inflation = (End Of Year - Start Of Year)/Start Of Year)*100
B14: IMPACT OF CRUDE OIL WITH ALL CATEGORIES AND CORRELATION | C14: Correl Function Between Crude Oil Array and The Category Array
B16: List Of Formulas Used For Project
B17: Index Match (Nested Index Match for Multiple Criteria)
B18: Averageifs
B19: Sum
B20: Hlookup
B21: Correl
B23: Data Cleaning Steps
B24: Identification of Columns having null values using countif and sum function
B25: Replacing the null values using moving average
B27: Extras
B28: Crude Oil Data Exported from PPAC Website
B29: Data Validation for Selection of Sectors

Sheet Updated DATA SET
A1: Sector | B1: Year | C1: Month | D1: Time frame | E1: Cereals and products | F1: Meat and fish | G1: Egg | H1: Milk and products | I1: Oils and fats | J1: Fruits | K1: Vegetables | L1: Pulses and products | M1: Sugar and Confectionery | N1: Spices | O1: Non-alcoholic beverages | P1: Prepared meals, snacks, sweets etc. | Q1: Food and beverages | R1: Pan, tobacco and intoxicants | S1: Clothing | T1: Footwear | U1: Clothing and footwear | V1: Housing | W1: NEW HOUSING | X1: Fuel and light | Y1: Household goods and services | Z1: Health | AA1: Transport and communication | AB1: Recreation and amusement | AC1: Education | AD1: Personal care and effects | AE1: Miscellaneous | AF1: General index | AG1: FOOD | AH1: CLOTHING | AI1: ESSENTIAL | AJ1: HEALTH | AK1: ENERGY | AL1: LUXURY
A2: Rural | B2: 2013 | C2: January | D2: =B2&" "&C2 -> 2013 January | E2: 107.5 | F2: 106.3 | G2: 108.1 | H2: 104.9 | I2: 106.1 | J2: 103.9 | K2: 101.9 | L2: 106.1 | M2: 106.8 | N2: 103.1 | O2: 104.8 | P2: 106.7 | Q2: 105.5 | R2: 105.1 | S2: 106.5 | T2: 105.8 | U2: 106.4 | V2: NA | W2: =IF(OR(V2="NA",V2="-"),V3,V2) -> 100.3 | X2: 105.5 | Y2: 104.8 | Z2: 104 | AA2: 103.3 | AB2: 103.4 | AC2: 103.8 | AD2: 104.7 | AE2: 104 | AF2: 105.1 | AG2: =SUM($E2:$Q2) -> 1371.7 | AH2: =SUM($S2:$U2) -> 318.7 | AI2: =SUM(W2,Y2,AC2) -> 308.9 | AJ2: =SUM(Z2,AD2) -> 208.7 | AK2: =SUM(X2,AA2) -> 208.8 | AL2: =SUM(AE2,R2,AB2) -> 312.5
A3: Urban | B3: 2013 | C3: January | D3: =B3&" "&C3 -> 2013 January | E3: 110.5 | F3: 109.1 | G3: 113 | H3: 103.6 | I3: 103.4 | J3: 102.3 | K3: 102.9 | L3: 105.8 | M3: 105.1 | N3: 101.8 | O3: 105.1 | P3: 107.9 | Q3: 105.9 | R3: 105.2 | S3: 105.9 | T3: 105 | U3: 105.8 | V3: 100.3 | W3: =IF(OR(V3="NA",V3="-"),V4,V3) -> 100.3 | X3: 105.4 | Y3: 104.8 | Z3: 104.1 | AA3: 103.2 | AB3: 102.9 | AC3: 103.5 | AD3: 104.3 | AE3: 103.7 | AF3: 104 | AG3: =SUM($E3:$Q3) -> 1376.4 | AH3: =SUM($S3:$U3) -> 316.7 | AI3: =SUM(W3,Y3,AC3) -> 308.6 | AJ3: =SUM(Z3,AD3) -> 208.4 | AK3: =SUM(X3,AA3) -> 208.6 | AL3: =SUM(AE3,R3,AB3) -> 311.8
A4: Rural+Urban | B4: 2013 | C4: January | D4: =B4&" "&C4 -> 2013 January | E4: 108.4 | F4: 107.3 | G4: 110 | H4: 104.4 | I4: 105.1 | J4: 103.2 | K4: 102.2 | L4: 106 | M4: 106.2 | N4: 102.7 | O4: 104.9 | P4: 107.3 | Q4: 105.6 | R4: 105.1 | S4: 106.3 | T4: 105.5 | U4: 106.2 | V4: 100.3 | W4: =IF(OR(V4="NA",V4="-"),V5,V4) -> 100.3 | X4: 105.5 | Y4: 104.8 | Z4: 104 | AA4: 103.2 | AB4: 103.1 | AC4: 103.6 | AD4: 104.5 | AE4: 103.9 | AF4: 104.6 | AG4: =SUM($E4:$Q4) -> 1373.3 | AH4: =SUM($S4:$U4) -> 318 | AI4: =SUM(W4,Y4,AC4) -> 308.7 | AJ4: =SUM(Z4,AD4) -> 208.5 | AK4: =SUM(X4,AA4) -> 208.7 | AL4: =SUM(AE4,R4,AB4) -> 312.1
A5: Rural | B5: 2013 | C5: February | D5: =B5&" "&C5 -> 2013 February | E5: 109.2 | F5: 108.7 | G5: 110.2 | H5: 105.4 | I5: 106.7 | J5: 104 | K5: 102.4 | L5: 105.9 | M5: 105.7 | N5: 103.1 | O5: 105.1 | P5: 107.7 | Q5: 106.3 | R5: 105.6 | S5: 107.1 | T5: 106.3 | U5: 107 | V5: NA | W5: =IF(OR(V5="NA",V5="-"),V6,V5) -> 100.4 | X5: 106.2 | Y5: 105.2 | Z5: 104.4 | AA5: 103.9 | AB5: 104 | AC5: 104.1 | AD5: 104.6 | AE5: 104.4 | AF5: 105.8 | AG5: =SUM($E5:$Q5) -> 1380.4 | AH5: =SUM($S5:$U5) -> 320.4 | AI5: =SUM(W5,Y5,AC5) -> 309.7 | AJ5: =SUM(Z5,AD5) -> 209 | AK5: =SUM(X5,AA5) -> 210.1 | AL5: =SUM(AE5,R5,AB5) -> 314
A6: Urban | B6: 2013 | C6: February | D6: =B6&" "&C6 -> 2013 February | E6: 112.9 | F6: 112.9 | G6: 116.9 | H6: 104 | I6: 103.5 | J6: 103.1 | K6: 104.9 | L6: 104.1 | M6: 103.8 | N6: 102.3 | O6: 106 | P6: 109 | Q6: 107.2 | R6: 106 | S6: 106.6 | T6: 105.5 | U6: 106.4 | V6: 100.4 | W6: =IF(OR(V6="NA",V6="-"),V7,V6) -> 100.4 | X6: 105.7 | Y6: 105.2 | Z6: 104.7 | AA6: 104.4 | AB6: 103.3 | AC6: 103.7 | AD6: 104.3 | AE6: 104.3 | AF6: 104.7 | AG6: =SUM($E6:$Q6) -> 1390.6 | AH6: =SUM($S6:$U6) -> 318.5 | AI6: =SUM(W6,Y6,AC6) -> 309.3 | AJ6: =SUM(Z6,AD6) -> 209 | AK6: =SUM(X6,AA6) -> 210.1 | AL6: =SUM(AE6,R6,AB6) -> 313.6
A7: Rural+Urban | B7: 2013 | C7: February | D7: =B7&" "&C7 -> 2013 February | E7: 110.4 | F7: 110.2 | G7: 112.8 | H7: 104.9 | I7: 105.5 | J7: 103.6 | K7: 103.2 | L7: 105.3 | M7: 105.1 | N7: 102.8 | O7: 105.5 | P7: 108.3 | Q7: 106.6 | R7: 105.7 | S7: 106.9 | T7: 106 | U7: 106.8 | V7: 100.4 | W7: =IF(OR(V7="NA",V7="-"),V8,V7) -> 100.4 | X7: 106 | Y7: 105.2 | Z7: 104.5 | AA7: 104.2 | AB7: 103.6 | AC7: 103.9 | AD7: 104.5 | AE7: 104.4 | AF7: 105.3 | AG7: =SUM($E7:$Q7) -> 1384.2 | AH7: =SUM($S7:$U7) -> 319.7 | AI7: =SUM(W7,Y7,AC7) -> 309.5 | AJ7: =SUM(Z7,AD7) -> 209 | AK7: =SUM(X7,AA7) -> 210.2 | AL7: =SUM(AE7,R7,AB7) -> 313.7
A8: Rural | B8: 2013 | C8: March | D8: =B8&" "&C8 -> 2013 March | E8: 110.2 | F8: 108.8 | G8: 109.9 | H8: 105.6 | I8: 106.2 | J8: 105.7 | K8: 101.4 | L8: 105.7 | M8: 105 | N8: 103.3 | O8: 105.6 | P8: 108.2 | Q8: 106.6 | R8: 106.5 | S8: 107.6 | T8: 106.8 | U8: 107.5 | V8: NA | W8: =IF(OR(V8="NA",V8="-"),V9,V8) -> 100.4 | X8: 106.1 | Y8: 105.6 | Z8: 104.7 | AA8: 104.6 | AB8: 104 | AC8: 104.3 | AD8: 104.3 | AE8: 104.6 | AF8: 106 | AG8: =SUM($E8:$Q8) -> 1382.2 | AH8: =SUM($S8:$U8) -> 321.9 | AI8: =SUM(W8,Y8,AC8) -> 310.3 | AJ8: =SUM(Z8,AD8) -> 209 | AK8: =SUM(X8,AA8) -> 210.7 | AL8: =SUM(AE8,R8,AB8) -> 315.1
A9: Urban | B9: 2013 | C9: March | D9: =B9&" "&C9 -> 2013 March | E9: 113.9 | F9: 111.4 | G9: 113.2 | H9: 104.3 | I9: 102.7 | J9: 104.9 | K9: 103.8 | L9: 103.5 | M9: 102.6 | N9: 102.4 | O9: 107 | P9: 109.8 | Q9: 107.3 | R9: 106.8 | S9: 107.2 | T9: 106 | U9: 107 | V9: 100.4 | W9: =IF(OR(V9="NA",V9="-"),V10,V9) -> 100.4 | X9: 106 | Y9: 105.7 | Z9: 105.2 | AA9: 105.5 | AB9: 103.5 | AC9: 103.8 | AD9: 104.2 | AE9: 104.9 | AF9: 105 | AG9: =SUM($E9:$Q9) -> 1386.8 | AH9: =SUM($S9:$U9) -> 320.2 | AI9: =SUM(W9,Y9,AC9) -> 309.9 | AJ9: =SUM(Z9,AD9) -> 209.4 | AK9: =SUM(X9,AA9) -> 211.5 | AL9: =SUM(AE9,R9,AB9) -> 315.2
A10: Rural+Urban | B10: 2013 | C10: March | D10: =B10&" "&C10 -> 2013 March | E10: 111.4 | F10: 109.7 | G10: 111.2 | H10: 105.1 | I10: 104.9 | J10: 105.3 | K10: 102.2 | L10: 105 | M10: 104.2 | N10: 103 | O10: 106.2 | P10: 108.9 | Q10: 106.9 | R10: 106.6 | S10: 107.4 | T10: 106.5 | U10: 107.3 | V10: 100.4 | W10: =IF(OR(V10="NA",V10="-"),V11,V10) -> 100.4 | X10: 106.1 | Y10: 105.6 | Z10: 104.9 | AA10: 105.1 | AB10: 103.7 | AC10: 104 | AD10: 104.3 | AE10: 104.7 | AF10: 105.5 | AG10: =SUM($E10:$Q10) -> 1384 | AH10: =SUM($S10:$U10) -> 321.2 | AI10: =SUM(W10,Y10,AC10) -> 310 | AJ10: =SUM(Z10,AD10) -> 209.2 | AK10: =SUM(X10,AA10) -> 211.2 | AL10: =SUM(AE10,R10,AB10) -> 315
A11: Rural | B11: 2013 | C11: April | D11: =B11&" "&C11 -> 2013 April | E11: 110.2 | F11: 109.5 | G11: 106.9 | H11: 106.3 | I11: 105.7 | J11: 108.3 | K11: 103.4 | L11: 105.7 | M11: 104.2 | N11: 103.2 | O11: 106.5 | P11: 108.8 | Q11: 107.1 | R11: 107.1 | S11: 108.1 | T11: 107.4 | U11: 108 | V11: NA | W11: =IF(OR(V11="NA",V11="-"),V12,V11) -> 100.5 | X11: 106.5 | Y11: 106.1 | Z11: 105.1 | AA11: 104.4 | AB11: 104.5 | AC11: 104.8 | AD11: 102.7 | AE11: 104.6 | AF11: 106.4 | AG11: =SUM($E11:$Q11) -> 1385.8 | AH11: =SUM($S11:$U11) -> 323.5 | AI11: =SUM(W11,Y11,AC11) -> 311.4 | AJ11: =SUM(Z11,AD11) -> 207.8 | AK11: =SUM(X11,AA11) -> 210.9 | AL11: =SUM(AE11,R11,AB11) -> 316.2
A12: Urban | B12: 2013 | C12: April | D12: =B12&" "&C12 -> 2013 April | E12: 114.6 | F12: 113.4 | G12: 106 | H12: 104.7 | I12: 102.1 | J12: 109.5 | K12: 109.7 | L12: 104.6 | M12: 102 | N12: 103.5 | O12: 108.2 | P12: 110.6 | Q12: 108.8 | R12: 108.5 | S12: 107.9 | T12: 106.4 | U12: 107.7 | V12: 100.5 | W12: =IF(OR(V12="NA",V12="-"),V13,V12) -> 100.5 | X12: 106.4 | Y12: 106.5 | Z12: 105.7 | AA12: 105 | AB12: 104 | AC12: 105.2 | AD12: 103.2 | AE12: 105.1 | AF12: 105.7 | AG12: =SUM($E12:$Q12) -> 1397.7 | AH12: =SUM($S12:$U12) -> 322 | AI12: =SUM(W12,Y12,AC12) -> 312.2 | AJ12: =SUM(Z12,AD12) -> 208.9 | AK12: =SUM(X12,AA12) -> 211.4 | AL12: =SUM(AE12,R12,AB12) -> 317.6
A13: Rural+Urban | B13: 2013 | C13: April | D13: =B13&" "&C13 -> 2013 April | E13: 111.6 | F13: 110.9 | G13: 106.6 | H13: 105.7 | I13: 104.4 | J13: 108.9 | K13: 105.5 | L13: 105.3 | M13: 103.5 | N13: 103.3 | O13: 107.2 | P13: 109.6 | Q13: 107.7 | R13: 107.5 | S13: 108 | T13: 107 | U13: 107.9 | V13: 100.5 | W13: =IF(OR(V13="NA",V13="-"),V14,V13) -> 100.5 | X13: 106.5 | Y13: 106.3 | Z13: 105.3 | AA13: 104.7 | AB13: 104.2 | AC13: 105 | AD13: 102.9 | AE13: 104.8 | AF13: 106.1 | AG13: =SUM($E13:$Q13) -> 1390.2 | AH13: =SUM($S13:$U13) -> 322.9 | AI13: =SUM(W13,Y13,AC13) -> 311.8 | AJ13: =SUM(Z13,AD13) -> 208.2 | AK13: =SUM(X13,AA13) -> 211.2 | AL13: =SUM(AE13,R13,AB13) -> 316.5
A14: Rural | B14: 2013 | C14: May | D14: =B14&" "&C14 -> 2013 May | E14: 110.9 | F14: 109.8 | G14: 105.9 | H14: 107.5 | I14: 105.3 | J14: 108.1 | K14: 107.3 | L14: 106.1 | M14: 103.7 | N14: 104 | O14: 107.4 | P14: 109.9 | Q14: 108.1 | R14: 108.1 | S14: 108.8 | T14: 107.9 | U14: 108.6 | V14: NA | W14: =IF(OR(V14="NA",V14="-"),V15,V14) -> 100.5 | X14: 107.5 | Y14: 106.8 | Z14: 105.7 | AA14: 104.1 | AB14: 105 | AC14: 105.5 | AD14: 102.1 | AE14: 104.8 | AF14: 107.2 | AG14: =SUM($E14:$Q14) -> 1394 | AH14: =SUM($S14:$U14) -> 325.3 | AI14: =SUM(W14,Y14,AC14) -> 312.8 | AJ14: =SUM(Z14,AD14) -> 207.8 | AK14: =SUM(X14,AA14) -> 211.6 | AL14: =SUM(AE14,R14,AB14) -> 317.9
A15: Urban | B15: 2013 | C15: May | D15: =B15&" "&C15 -> 2013 May | E15: 115.4 | F15: 114.2 | G15: 102.7 | H15: 105.5 | I15: 101.5 | J15: 110.6 | K15: 123.7 | L15: 105.2 | M15: 101.9 | N15: 105 | O15: 109.1 | P15: 111.3 | Q15: 111.1 | R15: 109.8 | S15: 108.5 | T15: 106.7 | U15: 108.3 | V15: 100.5 | W15: =IF(OR(V15="NA",V15="-"),V16,V15) -> 100.5 | X15: 107.2 | Y15: 107.1 | Z15: 106.2 | AA15: 103.9 | AB15: 104.6 | AC15: 105.7 | AD15: 102.6 | AE15: 104.9 | AF15: 106.6 | AG15: =SUM($E15:$Q15) -> 1417.2 | AH15: =SUM($S15:$U15) -> 323.5 | AI15: =SUM(W15,Y15,AC15) -> 313.3 | AJ15: =SUM(Z15,AD15) -> 208.8 | AK15: =SUM(X15,AA15) -> 211.1 | AL15: =SUM(AE15,R15,AB15) -> 319.3
A16: Rural+Urban | B16: 2013 | C16: May | D16: =B16&" "&C16 -> 2013 May | E16: 112.3 | F16: 111.3 | G16: 104.7 | H16: 106.8 | I16: 103.9 | J16: 109.3 | K16: 112.9 | L16: 105.8 | M16: 103.1 | N16: 104.3 | O16: 108.1 | P16: 110.5 | Q16: 109.2 | R16: 108.6 | S16: 108.7 | T16: 107.4 | U16: 108.5 | V16: 100.5 | W16: =IF(OR(V16="NA",V16="-"),V17,V16) -> 100.5 | X16: 107.4 | Y16: 106.9 | Z16: 105.9 | AA16: 104 | AB16: 104.8 | AC16: 105.6 | AD16: 102.3 | AE16: 104.8 | AF16: 106.9 | AG16: =SUM($E16:$Q16) -> 1402.2 | AH16: =SUM($S16:$U16) -> 324.6 | AI16: =SUM(W16,Y16,AC16) -> 313 | AJ16: =SUM(Z16,AD16) -> 208.2 | AK16: =SUM(X16,AA16) -> 211.4 | AL16: =SUM(AE16,R16,AB16) -> 318.2
A17: Rural | B17: 2013 | C17: June | D17: =B17&" "&C17 -> 2013 June | E17: 112.3 | F17: 112.1 | G17: 108.1 | H17: 108.3 | I17: 105.9 | J17: 109.2 | K17: 118 | L17: 106.8 | M17: 104.1 | N17: 105.4 | O17: 108.2 | P17: 111 | Q17: 110.6 | R17: 109 | S17: 109.7 | T17: 108.8 | U17: 109.5 | V17: NA | W17: =IF(OR(V17="NA",V17="-"),V18,V17) -> 106.6 | X17: 108.5 | Y17: 107.5 | Z17: 106.3 | AA17: 105 | AB17: 105.6 | AC17: 106.5 | AD17: 102.5 | AE17: 105.5 | AF17: 108.9 | AG17: =SUM($E17:$Q17) -> 1420 | AH17: =SUM($S17:$U17) -> 328 | AI17: =SUM(W17,Y17,AC17) -> 320.6 | AJ17: =SUM(Z17,AD17) -> 208.8 | AK17: =SUM(X17,AA17) -> 213.5 | AL17: =SUM(AE17,R17,AB17) -> 320.1
A18: Urban | B18: 2013 | C18: June | D18: =B18&" "&C18 -> 2013 June | E18: 117 | F18: 120.1 | G18: 112.5 | H18: 107.3 | I18: 101.3 | J18: 112.4 | K18: 143.6 | L18: 105.4 | M18: 101.4 | N18: 106.4 | O18: 110 | P18: 112.2 | Q18: 115 | R18: 110.9 | S18: 109.2 | T18: 107.2 | U18: 108.9 | V18: 106.6 | W18: =IF(OR(V18="NA",V18="-"),V19,V18) -> 106.6 | X18: 108 | Y18: 107.7 | Z18: 106.5 | AA18: 105.2 | AB18: 105.2 | AC18: 108.1 | AD18: 103.3 | AE18: 106.1 | AF18: 109.7 | AG18: =SUM($E18:$Q18) -> 1464.6 | AH18: =SUM($S18:$U18) -> 325.3 | AI18: =SUM(W18,Y18,AC18) -> 322.4 | AJ18: =SUM(Z18,AD18) -> 209.8 | AK18: =SUM(X18,AA18) -> 213.2 | AL18: =SUM(AE18,R18,AB18) -> 322.2
A19: Rural+Urban | B19: 2013 | C19: June | D19: =B19&" "&C19 -> 2013 June | E19: 113.8 | F19: 114.9 | G19: 109.8 | H19: 107.9 | I19: 104.2 | J19: 110.7 | K19: 126.7 | L19: 106.3 | M19: 103.2 | N19: 105.7 | O19: 109 | P19: 111.6 | Q19: 112.2 | R19: 109.5 | S19: 109.5 | T19: 108.1 | U19: 109.3 | V19: 106.6 | W19: =IF(OR(V19="NA",V19="-"),V20,V19) -> 106.6 | X19: 108.3 | Y19: 107.6 | Z19: 106.4 | AA19: 105.1 | AB19: 105.4 | AC19: 107.4 | AD19: 102.8 | AE19: 105.8 | AF19: 109.3 | AG19: =SUM($E19:$Q19) -> 1436 | AH19: =SUM($S19:$U19) -> 326.9 | AI19: =SUM(W19,Y19,AC19) -> 321.6 | AJ19: =SUM(Z19,AD19) -> 209.2 | AK19: =SUM(X19,AA19) -> 213.4 | AL19: =SUM(AE19,R19,AB19) -> 320.7
A20: Rural | B20: 2013 | C20: July | D20: =B20&" "&C20 -> 2013 July | E20: 113.4 | F20: 114.9 | G20: 110.5 | H20: 109.3 | I20: 106.2 | J20: 110.3 | K20: 129.2 | L20: 107.1 | M20: 104.3 | N20: 106.4 | O20: 109.1 | P20: 112.1 | Q20: 113.1 | R20: 109.8 | S20: 110.5 | T20: 109.5 | U20: 110.3 | V20: NA | W20: =IF(OR(V20="NA",V20="-"),V21,V20) -> 107.7 | X20: 109.5 | Y20: 108.3 | Z20: 106.9 | AA20: 106.8 | AB20: 106.4 | AC20: 107.8 | AD20: 102.5 | AE20: 106.5 | AF20: 110.7 | AG20: =SUM($E20:$Q20) -> 1445.9 | AH20: =SUM($S20:$U20) -> 330.3 | AI20: =SUM(W20,Y20,AC20) -> 323.8 | AJ20: =SUM(Z20,AD20) -> 209.4 | AK20: =SUM(X20,AA20) -> 216.3 | AL20: =SUM(AE20,R20,AB20) -> 322.7
A21: Urban | B21: 2013 | C21: July | D21: =B21&" "&C21 -> 2013 July | E21: 117.8 | F21: 119.2 | G21: 114 | H21: 108.3 | I21: 101.1 | J21: 113.2 | K21: 160.9 | L21: 105.1 | M21: 101.3 | N21: 107.5 | O21: 110.4 | P21: 113.1 | Q21: 117.5 | R21: 111.7 | S21: 109.8 | T21: 107.8 | U21: 109.5 | V21: 107.7 | W21: =IF(OR(V21="NA",V21="-"),V22,V21) -> 107.7 | X21: 108.6 | Y21: 108.1 | Z21: 107.1 | AA21: 107.3 | AB21: 105.9 | AC21: 110.1 | AD21: 103.2 | AE21: 107.3 | AF21: 111.4 | AG21: =SUM($E21:$Q21) -> 1489.4 | AH21: =SUM($S21:$U21) -> 327.1 | AI21: =SUM(W21,Y21,AC21) -> 325.9 | AJ21: =SUM(Z21,AD21) -> 210.3 | AK21: =SUM(X21,AA21) -> 215.9 | AL21: =SUM(AE21,R21,AB21) -> 324.9
A22: Rural+Urban | B22: 2013 | C22: July | D22: =B22&" "&C22 -> 2013 July | E22: 114.8 | F22: 116.4 | G22: 111.9 | H22: 108.9 | I22: 104.3 | J22: 111.7 | K22: 140 | L22: 106.4 | M22: 103.3 | N22: 106.8 | O22: 109.6 | P22: 112.6 | Q22: 114.7 | R22: 110.3 | S22: 110.2 | T22: 108.8 | U22: 110 | V22: 107.7 | W22: =IF(OR(V22="NA",V22="-"),V23,V22) -> 107.7 | X22: 109.2 | Y22: 108.2 | Z22: 107 | AA22: 107.1 | AB22: 106.1 | AC22: 109.1 | AD22: 102.8 | AE22: 106.9 | AF22: 111 | AG22: =SUM($E22:$Q22) -> 1461.4 | AH22: =SUM($S22:$U22) -> 329 | AI22: =SUM(W22,Y22,AC22) -> 325 | AJ22: =SUM(Z22,AD22) -> 209.8 | AK22: =SUM(X22,AA22) -> 216.3 | AL22: =SUM(AE22,R22,AB22) -> 323.3
A23: Rural | B23: 2013 | C23: August | D23: =B23&" "&C23 -> 2013 August | E23: 114.3 | F23: 115.4 | G23: 111.1 | H23: 110 | I23: 106.4 | J23: 110.8 | K23: 138.9 | L23: 107.4 | M23: 104.1 | N23: 106.9 | O23: 109.7 | P23: 112.6 | Q23: 114.9 | R23: 110.7 | S23: 111.3 | T23: 110.2 | U23: 111.1 | V23: NA | W23: =IF(OR(V23="NA",V23="-"),V24,V23) -> 108.9 | X23: 109.9 | Y23: 108.7 | Z23: 107.5 | AA23: 107.8 | AB23: 106.8 | AC23: 108.7 | AD23: 105 | AE23: 107.5 | AF23: 112.1 | AG23: =SUM($E23:$Q23) -> 1462.5 | AH23: =SUM($S23:$U23) -> 332.6 | AI23: =SUM(W23,Y23,AC23) -> 326.3 | AJ23: =SUM(Z23,AD23) -> 212.5 | AK23: =SUM(X23,AA23) -> 217.7 | AL23: =SUM(AE23,R23,AB23) -> 325
A24: Urban | B24: 2013 | C24: August | D24: =B24&" "&C24 -> 2013 August | E24: 118.3 | F24: 120.4 | G24: 112.7 | H24: 108.9 | I24: 101.1 | J24: 108.7 | K24: 177 | L24: 104.7 | M24: 101 | N24: 108.5 | O24: 110.9 | P24: 114.3 | Q24: 119.6 | R24: 112.4 | S24: 110.6 | T24: 108.3 | U24: 110.2 | V24: 108.9 | W24: =IF(OR(V24="NA",V24="-"),V25,V24) -> 108.9 | X24: 109.3 | Y24: 108.7 | Z24: 107.6 | AA24: 108.1 | AB24: 106.5 | AC24: 110.8 | AD24: 106 | AE24: 108.3 | AF24: 112.7 | AG24: =SUM($E24:$Q24) -> 1506.1 | AH24: =SUM($S24:$U24) -> 329.1 | AI24: =SUM(W24,Y24,AC24) -> 328.4 | AJ24: =SUM(Z24,AD24) -> 213.6 | AK24: =SUM(X24,AA24) -> 217.4 | AL24: =SUM(AE24,R24,AB24) -> 327.2
A25: Rural+Urban | B25: 2013 | C25: August | D25: =B25&" "&C25 -> 2013 August | E25: 115.6 | F25: 117.2 | G25: 111.7 | H25: 109.6 | I25: 104.5 | J25: 109.8 | K25: 151.8 | L25: 106.5 | M25: 103.1 | N25: 107.4 | O25: 110.2 | P25: 113.4 | Q25: 116.6 | R25: 111.2 | S25: 111 | T25: 109.4 | U25: 110.7 | V25: 108.9 | W25: =IF(OR(V25="NA",V25="-"),V26,V25) -> 108.9 | X25: 109.7 | Y25: 108.7 | Z25: 107.5 | AA25: 108 | AB25: 106.6 | AC25: 109.9 | AD25: 105.4 | AE25: 107.9 | AF25: 112.4 | AG25: =SUM($E25:$Q25) -> 1477.4 | AH25: =SUM($S25:$U25) -> 331.1 | AI25: =SUM(W25,Y25,AC25) -> 327.5 | AJ25: =SUM(Z25,AD25) -> 212.9 | AK25: =SUM(X25,AA25) -> 217.7 | AL25: =SUM(AE25,R25,AB25) -> 325.7
A26: Rural | B26: 2013 | C26: September | D26: =B26&" "&C26 -> 2013 September | E26: 115.4 | F26: 115.7 | G26: 111.7 | H26: 111 | I26: 107.4 | J26: 110.9 | K26: 154 | L26: 108.1 | M26: 104.2 | N26: 107.9 | O26: 110.4 | P26: 114 | Q26: 117.8 | R26: 111.7 | S26: 112.7 | T26: 111.4 | U26: 112.5 | V26: NA | W26: =IF(OR(V26="NA",V26="-"),V27,V26) -> 109.7 | X26: 111.1 | Y26: 109.6 | Z26: 108.3 | AA26: 109.3 | AB26: 107.7 | AC26: 109.8 | AD26: 106.7 | AE26: 108.7 | AF26: 114.2 | AG26: =SUM($E26:$Q26) -> 1488.5 | AH26: =SUM($S26:$U26) -> 336.6 | AI26: =SUM(W26,Y26,AC26) -> 329.1 | AJ26: =SUM(Z26,AD26) -> 215 | AK26: =SUM(X26,AA26) -> 220.4 | AL26: =SUM(AE26,R26,AB26) -> 328.1
A27: Urban | B27: 2013 | C27: September | D27: =B27&" "&C27 -> 2013 September | E27: 118.6 | F27: 119.1 | G27: 113.2 | H27: 109.6 | I27: 101.7 | J27: 103.2 | K27: 174.3 | L27: 105.1 | M27: 100.8 | N27: 109.1 | O27: 111.1 | P27: 115.4 | Q27: 119.2 | R27: 112.9 | S27: 111.4 | T27: 109 | U27: 111.1 | V27: 109.7 | W27: =IF(OR(V27="NA",V27="-"),V28,V27) -> 109.7 | X27: 109.5 | Y27: 109.6 | Z27: 107.9 | AA27: 110.4 | AB27: 107.4 | AC27: 111.2 | AD27: 106.9 | AE27: 109.4 | AF27: 113.2 | AG27: =SUM($E27:$Q27) -> 1500.4 | AH27: =SUM($S27:$U27) -> 331.5 | AI27: =SUM(W27,Y27,AC27) -> 330.5 | AJ27: =SUM(Z27,AD27) -> 214.8 | AK27: =SUM(X27,AA27) -> 219.9 | AL27: =SUM(AE27,R27,AB27) -> 329.7
A28: Rural+Urban | B28: 2013 | C28: September | D28: =B28&" "&C28 -> 2013 September | E28: 116.4 | F28: 116.9 | G28: 112.3 | H28: 110.5 | I28: 105.3 | J28: 107.3 | K28: 160.9 | L28: 107.1 | M28: 103.1 | N28: 108.3 | O28: 110.7 | P28: 114.6 | Q28: 118.3 | R28: 112 | S28: 112.2 | T28: 110.4 | U28: 111.9 | V28: 109.7 | W28: =IF(OR(V28="NA",V28="-"),V29,V28) -> 109.7 | X28: 110.5 | Y28: 109.6 | Z28: 108.1 | AA28: 109.9 | AB28: 107.5 | AC28: 110.6 | AD28: 106.8 | AE28: 109 | AF28: 113.7 | AG28: =SUM($E28:$Q28) -> 1491.7 | AH28: =SUM($S28:$U28) -> 334.5 | AI28: =SUM(W28,Y28,AC28) -> 329.9 | AJ28: =SUM(Z28,AD28) -> 214.9 | AK28: =SUM(X28,AA28) -> 220.4 | AL28: =SUM(AE28,R28,AB28) -> 328.5
A29: Rural | B29: 2013 | C29: October | D29: =B29&" "&C29 -> 2013 October | E29: 116.3 | F29: 115.4 | G29: 112.6 | H29: 111.7 | I29: 107.7 | J29: 113.2 | K29: 164.9 | L29: 108.3 | M29: 103.9 | N29: 108.2 | O29: 111.1 | P29: 114.9 | Q29: 119.8 | R29: 112.2 | S29: 113.6 | T29: 112.3 | U29: 113.4 | V29: NA | W29: =IF(OR(V29="NA",V29="-"),V30,V29) -> 110.5 | X29: 111.6 | Y29: 110.4 | Z29: 108.9 | AA29: 109.3 | AB29: 108.3 | AC29: 110.2 | AD29: 107.5 | AE29: 109.1 | AF29: 115.5 | AG29: =SUM($E29:$Q29) -> 1508 | AH29: =SUM($S29:$U29) -> 339.3 | AI29: =SUM(W29,Y29,AC29) -> 331.1 | AJ29: =SUM(Z29,AD29) -> 216.4 | AK29: =SUM(X29,AA29) -> 220.9 | AL29: =SUM(AE29,R29,AB29) -> 329.6
A30: Urban | B30: 2013 | C30: October | D30: =B30&" "&C30 -> 2013 October | E30: 118.9 | F30: 118.1 | G30: 114.5 | H30: 110.4 | I30: 102.3 | J30: 106.2 | K30: 183.5 | L30: 105.3 | M30: 100.2 | N30: 109.6 | O30: 111.4 | P30: 116 | Q30: 120.8 | R30: 113.5 | S30: 112.5 | T30: 109.7 | U30: 112 | V30: 110.5 | W30: =IF(OR(V30="NA",V30="-"),V31,V30) -> 110.5 | X30: 109.7 | Y30: 110.2 | Z30: 108.2 | AA30: 109.7 | AB30: 108 | AC30: 111.3 | AD30: 107.3 | AE30: 109.4 | AF30: 114 | AG30: =SUM($E30:$Q30) -> 1517.2 | AH30: =SUM($S30:$U30) -> 334.2 | AI30: =SUM(W30,Y30,AC30) -> 332 | AJ30: =SUM(Z30,AD30) -> 215.5 | AK30: =SUM(X30,AA30) -> 219.4 | AL30: =SUM(AE30,R30,AB30) -> 330.9
A31: Rural+Urban | B31: 2013 | C31: October | D31: =B31&" "&C31 -> 2013 October | E31: 117.1 | F31: 116.3 | G31: 113.3 | H31: 111.2 | I31: 105.7 | J31: 109.9 | K31: 171.2 | L31: 107.3 | M31: 102.7 | N31: 108.7 | O31: 111.2 | P31: 115.4 | Q31: 120.2 | R31: 112.5 | S31: 113.2 | T31: 111.2 | U31: 112.8 | V31: 110.5 | W31: =IF(OR(V31="NA",V31="-"),V32,V31) -> 110.5 | X31: 110.9 | Y31: 110.3 | Z31: 108.6 | AA31: 109.5 | AB31: 108.1 | AC31: 110.8 | AD31: 107.4 | AE31: 109.2 | AF31: 114.8 | AG31: =SUM($E31:$Q31) -> 1510.2 | AH31: =SUM($S31:$U31) -> 337.2 | AI31: =SUM(W31,Y31,AC31) -> 331.6 | AJ31: =SUM(Z31,AD31) -> 216 | AK31: =SUM(X31,AA31) -> 220.4 | AL31: =SUM(AE31,R31,AB31) -> 329.8
A32: Rural | B32: 2013 | C32: November | D32: =B32&" "&C32 -> 2013 November | E32: 117.3 | F32: 114.9 | G32: 116.2 | H32: 112.8 | I32: 108.9 | J32: 116.6 | K32: 178.1 | L32: 109.1 | M32: 103.6 | N32: 109 | O32: 111.8 | P32: 116 | Q32: 122.5 | R32: 112.8 | S32: 114.6 | T32: 113.1 | U32: 114.4 | V32: NA | W32: =IF(OR(V32="NA",V32="-"),V33,V32) -> 111.1 | X32: 112.6 | Y32: 111.3 | Z32: 109.7 | AA32: 109.6 | AB32: 108.7 | AC32: 111 | AD32: 108.2 | AE32: 109.8 | AF32: 117.4 | AG32: =SUM($E32:$Q32) -> 1536.8 | AH32: =SUM($S32:$U32) -> 342.1 | AI32: =SUM(W32,Y32,AC32) -> 333.4 | AJ32: =SUM(Z32,AD32) -> 217.9 | AK32: =SUM(X32,AA32) -> 222.2 | AL32: =SUM(AE32,R32,AB32) -> 331.3
A33: Urban | B33: 2013 | C33: November | D33: =B33&" "&C33 -> 2013 November | E33: 119.8 | F33: 116.3 | G33: 122.6 | H33: 112 | I33: 103.2 | J33: 110 | K33: 192.8 | L33: 106.3 | M33: 99.5 | N33: 110.3 | O33: 111.8 | P33: 117.1 | Q33: 122.9 | R33: 114.1 | S33: 113.5 | T33: 110.3 | U33: 113 | V33: 111.1 | W33: =IF(OR(V33="NA",V33="-"),V34,V33) -> 111.1 | X33: 110 | Y33: 110.9 | Z33: 108.6 | AA33: 109.5 | AB33: 108.5 | AC33: 111.3 | AD33: 107.9 | AE33: 109.6 | AF33: 115 | AG33: =SUM($E33:$Q33) -> 1544.6 | AH33: =SUM($S33:$U33) -> 336.8 | AI33: =SUM(W33,Y33,AC33) -> 333.3 | AJ33: =SUM(Z33,AD33) -> 216.5 | AK33: =SUM(X33,AA33) -> 219.5 | AL33: =SUM(AE33,R33,AB33) -> 332.2
A34: Rural+Urban | B34: 2013 | C34: November | D34: =B34&" "&C34 -> 2013 November | E34: 118.1 | F34: 115.4 | G34: 118.7 | H34: 112.5 | I34: 106.8 | J34: 113.5 | K34: 183.1 | L34: 108.2 | M34: 102.2 | N34: 109.4 | O34: 111.8 | P34: 116.5 | Q34: 122.6 | R34: 113.1 | S34: 114.2 | T34: 111.9 | U34: 113.8 | V34: 111.1 | W34: =IF(OR(V34="NA",V34="-"),V35,V34) -> 111.1 | X34: 111.6 | Y34: 111.1 | Z34: 109.3 | AA34: 109.5 | AB34: 108.6 | AC34: 111.2 | AD34: 108.1 | AE34: 109.7 | AF34: 116.3 | AG34: =SUM($E34:$Q34) -> 1538.8 | AH34: =SUM($S34:$U34) -> 339.9 | AI34: =SUM(W34,Y34,AC34) -> 333.4 | AJ34: =SUM(Z34,AD34) -> 217.4 | AK34: =SUM(X34,AA34) -> 221.1 | AL34: =SUM(AE34,R34,AB34) -> 331.4
A35: Rural | B35: 2013 | C35: December | D35: =B35&" "&C35 -> 2013 December | E35: 118.4 | F35: 115.9 | G35: 120.4 | H35: 113.8 | I35: 109.5 | J35: 115.5 | K35: 145.7 | L35: 109.5 | M35: 102.9 | N35: 109.8 | O35: 112.1 | P35: 116.8 | Q35: 118.7 | R35: 113.6 | S35: 115.8 | T35: 114 | U35: 115.5 | V35: NA | W35: =IF(OR(V35="NA",V35="-"),V36,V35) -> 110.7 | X35: 112.8 | Y35: 112.1 | Z35: 110.1 | AA35: 109.9 | AB35: 109.2 | AC35: 111.6 | AD35: 108.1 | AE35: 110.1 | AF35: 115.5 | AG35: =SUM($E35:$Q35) -> 1509 | AH35: =SUM($S35:$U35) -> 345.3 | AI35: =SUM(W35,Y35,AC35) -> 334.4 | AJ35: =SUM(Z35,AD35) -> 218.2 | AK35: =SUM(X35,AA35) -> 222.7 | AL35: =SUM(AE35,R35,AB35) -> 332.9
A36: Urban | B36: 2013 | C36: December | D36: =B36&" "&C36 -> 2013 December | E36: 120.5 | F36: 118.1 | G36: 128.5 | H36: 112.8 | I36: 103.4 | J36: 110.7 | K36: 144.8 | L36: 107.1 | M36: 98.6 | N36: 111.9 | O36: 112.1 | P36: 118.1 | Q36: 117.8 | R36: 115 | S36: 114.2 | T36: 110.9 | U36: 113.7 | V36: 110.7 | W36: =IF(OR(V36="NA",V36="-"),V37,V36) -> 110.7 | X36: 110.4 | Y36: 111.3 | Z36: 109 | AA36: 109.7 | AB36: 108.9 | AC36: 111.4 | AD36: 107.7 | AE36: 109.8 | AF36: 113.3 | AG36: =SUM($E36:$Q36) -> 1504.4 | AH36: =SUM($S36:$U36) -> 338.8 | AI36: =SUM(W36,Y36,AC36) -> 333.4 | AJ36: =SUM(Z36,AD36) -> 216.7 | AK36: =SUM(X36,AA36) -> 220.1 | AL36: =SUM(AE36,R36,AB36) -> 333.7
A37: Rural+Urban | B37: 2013 | C37: December | D37: =B37&" "&C37 -> 2013 December | E37: 119.1 | F37: 116.7 | G37: 123.5 | H37: 113.4 | I37: 107.3 | J37: 113.3 | K37: 145.4 | L37: 108.7 | M37: 101.5 | N37: 110.5 | O37: 112.1 | P37: 117.4 | Q37: 118.4 | R37: 114 | S37: 115.2 | T37: 112.7 | U37: 114.8 | V37: 110.7 | W37: =IF(OR(V37="NA",V37="-"),V38,V37) -> 110.7 | X37: 111.9 | Y37: 111.7 | Z37: 109.7 | AA37: 109.8 | AB37: 109 | AC37: 111.5 | AD37: 107.9 | AE37: 110 | AF37: 114.5 | AG37: =SUM($E37:$Q37) -> 1507.3 | AH37: =SUM($S37:$U37) -> 342.7 | AI37: =SUM(W37,Y37,AC37) -> 333.9 | AJ37: =SUM(Z37,AD37) -> 217.6 | AK37: =SUM(X37,AA37) -> 221.7 | AL37: =SUM(AE37,R37,AB37) -> 333
A38: Rural | B38: 2014 | C38: January | D38: =B38&" "&C38 -> 2014 January | E38: 118.9 | F38: 117.1 | G38: 120.5 | H38: 114.4 | I38: 109 | J38: 115.5 | K38: 123.9 | L38: 109.6 | M38: 101.8 | N38: 110.2 | O38: 112.4 | P38: 117.3 | Q38: 116 | R38: 114 | S38: 116.5 | T38: 114.5 | U38: 116.2 | V38: NA | W38: =IF(OR(V38="NA",V38="-"),V39,V38) -> 111.6 | X38: 113 | Y38: 112.6 | Z38: 110.6 | AA38: 110.5 | AB38: 109.6 | AC38: 111.8 | AD38: 108.3 | AE38: 110.6 | AF38: 114.2 | AG38: =SUM($E38:$Q38) -> 1486.6 | AH38: =SUM($S38:$U38) -> 347.2 | AI38: =SUM(W38,Y38,AC38) -> 336 | AJ38: =SUM(Z38,AD38) -> 218.9 | AK38: =SUM(X38,AA38) -> 223.5 | AL38: =SUM(AE38,R38,AB38) -> 334.2
A39: Urban | B39: 2014 | C39: January | D39: =B39&" "&C39 -> 2014 January | E39: 121.2 | F39: 122 | G39: 129.9 | H39: 113.6 | I39: 102.9 | J39: 112.1 | K39: 118.9 | L39: 107.5 | M39: 96.9 | N39: 112.7 | O39: 112.1 | P39: 119 | Q39: 115.5 | R39: 115.7 | S39: 114.8 | T39: 111.3 | U39: 114.3 | V39: 111.6 | W39: =IF(OR(V39="NA",V39="-"),V40,V39) -> 111.6 | X39: 111 | Y39: 111.9 | Z39: 109.7 | AA39: 110.8 | AB39: 109.8 | AC39: 111.5 | AD39: 108 | AE39: 110.5 | AF39: 112.9 | AG39: =SUM($E39:$Q39) -> 1484.3 | AH39: =SUM($S39:$U39) -> 340.4 | AI39: =SUM(W39,Y39,AC39) -> 335 | AJ39: =SUM(Z39,AD39) -> 217.7 | AK39: =SUM(X39,AA39) -> 221.8 | AL39: =SUM(AE39,R39,AB39) -> 336
A40: Rural+Urban | B40: 2014 | C40: January | D40: =B40&" "&C40 -> 2014 January | E40: 119.6 | F40: 118.8 | G40: 124.1 | H40: 114.1 | I40: 106.8 | J40: 113.9 | K40: 122.2 | L40: 108.9 | M40: 100.2 | N40: 111 | O40: 112.3 | P40: 118.1 | Q40: 115.8 | R40: 114.5 | S40: 115.8 | T40: 113.2 | U40: 115.4 | V40: 111.6 | W40: =IF(OR(V40="NA",V40="-"),V41,V40) -> 111.6 | X40: 112.2 | Y40: 112.3 | Z40: 110.3 | AA40: 110.7 | AB40: 109.7 | AC40: 111.6 | AD40: 108.2 | AE40: 110.6 | AF40: 113.6 | AG40: =SUM($E40:$Q40) -> 1485.8 | AH40: =SUM($S40:$U40) -> 344.4 | AI40: =SUM(W40,Y40,AC40) -> 335.5 | AJ40: =SUM(Z40,AD40) -> 218.5 | AK40: =SUM(X40,AA40) -> 222.9 | AL40: =SUM(AE40,R40,AB40) -> 334.8
A41: Rural | B41: 2014 | C41: February | D41: =B41&" "&C41 -> 2014 February | E41: 119.4 | F41: 117.7 | G41: 121.2 | H41: 115 | I41: 109 | J41: 116.6 | K41: 116 | L41: 109.8 | M41: 101.1 | N41: 110.4 | O41: 112.9 | P41: 117.8 | Q41: 115.3 | R41: 114.2 | S41: 117.1 | T41: 114.5 | U41: 116.7 | V41: NA | W41: =IF(OR(V41="NA",V41="-"),V42,V41) -> 112.5 | X41: 113.2 | Y41: 112.9 | Z41: 110.9 | AA41: 110.8 | AB41: 109.9 | AC41: 112 | AD41: 108.7 | AE41: 110.9 | AF41: 114 | AG41: =SUM($E41:$Q41) -> 1482.2 | AH41: =SUM($S41:$U41) -> 348.3 | AI41: =SUM(W41,Y41,AC41) -> 337.4 | AJ41: =SUM(Z41,AD41) -> 219.6 | AK41: =SUM(X41,AA41) -> 224 | AL41: =SUM(AE41,R41,AB41) -> 335
A42: Urban | B42: 2014 | C42: February | D42: =B42&" "&C42 -> 2014 February | E42: 121.9 | F42: 122 | G42: 124.5 | H42: 115.2 | I42: 102.5 | J42: 114.1 | K42: 111.5 | L42: 108.2 | M42: 95.4 | N42: 113.5 | O42: 112.1 | P42: 119.9 | Q42: 115.2 | R42: 116.2 | S42: 115.3 | T42: 111.7 | U42: 114.7 | V42: 112.5 | W42: =IF(OR(V42="NA",V42="-"),V43,V42) -> 112.5 | X42: 111.1 | Y42: 112.6 | Z42: 110.4 | AA42: 111.3 | AB42: 110.3 | AC42: 111.6 | AD42: 108.7 | AE42: 111 | AF42: 113.1 | AG42: =SUM($E42:$Q42) -> 1476 | AH42: =SUM($S42:$U42) -> 341.7 | AI42: =SUM(W42,Y42,AC42) -> 336.7 | AJ42: =SUM(Z42,AD42) -> 219.1 | AK42: =SUM(X42,AA42) -> 222.4 | AL42: =SUM(AE42,R42,AB42) -> 337.5
A43: Rural+Urban | B43: 2014 | C43: February | D43: =B43&" "&C43 -> 2014 February | E43: 120.2 | F43: 119.2 | G43: 122.5 | H43: 115.1 | I43: 106.6 | J43: 115.4 | K43: 114.5 | L43: 109.3 | M43: 99.2 | N43: 111.4 | O43: 112.6 | P43: 118.8 | Q43: 115.3 | R43: 114.7 | S43: 116.4 | T43: 113.3 | U43: 115.9 | V43: 112.5 | W43: =IF(OR(V43="NA",V43="-"),V44,V43) -> 112.5 | X43: 112.4 | Y43: 112.8 | Z43: 110.7 | AA43: 111.1 | AB43: 110.1 | AC43: 111.8 | AD43: 108.7 | AE43: 110.9 | AF43: 113.6 | AG43: =SUM($E43:$Q43) -> 1480.1 | AH43: =SUM($S43:$U43) -> 345.6 | AI43: =SUM(W43,Y43,AC43) -> 337.1 | AJ43: =SUM(Z43,AD43) -> 219.4 | AK43: =SUM(X43,AA43) -> 223.5 | AL43: =SUM(AE43,R43,AB43) -> 335.7
A44: Rural | B44: 2014 | C44: March | D44: =B44&" "&C44 -> 2014 March | E44: 120.1 | F44: 118.1 | G44: 120.7 | H44: 116.1 | I44: 109.3 | J44: 119.6 | K44: 117.9 | L44: 110.2 | M44: 101.2 | N44: 110.7 | O44: 113 | P44: 118.3 | Q44: 116.2 | R44: 114.6 | S44: 117.5 | T44: 114.9 | U44: 117.2 | V44: NA | W44: =IF(OR(V44="NA",V44="-"),V45,V44) -> 113.2 | X44: 113.4 | Y44: 113.4 | Z44: 111.4 | AA44: 111.2 | AB44: 110.2 | AC44: 112.4 | AD44: 108.9 | AE44: 111.3 | AF44: 114.6 | AG44: =SUM($E44:$Q44) -> 1491.4 | AH44: =SUM($S44:$U44) -> 349.6 | AI44: =SUM(W44,Y44,AC44) -> 339 | AJ44: =SUM(Z44,AD44) -> 220.3 | AK44: =SUM(X44,AA44) -> 224.6 | AL44: =SUM(AE44,R44,AB44) -> 336.1
A45: Urban | B45: 2014 | C45: March | D45: =B45&" "&C45 -> 2014 March | E45: 122.1 | F45: 121.4 | G45: 121.5 | H45: 116.2 | I45: 102.8 | J45: 117.7 | K45: 113.3 | L45: 108.9 | M45: 96.3 | N45: 114.1 | O45: 112.2 | P45: 120.5 | Q45: 116 | R45: 116.7 | S45: 115.8 | T45: 112.1 | U45: 115.2 | V45: 113.2 | W45: =IF(OR(V45="NA",V45="-"),V46,V45) -> 113.2 | X45: 110.9 | Y45: 113 | Z45: 110.8 | AA45: 111.6 | AB45: 110.9 | AC45: 111.8 | AD45: 109.2 | AE45: 111.4 | AF45: 113.7 | AG45: =SUM($E45:$Q45) -> 1483 | AH45: =SUM($S45:$U45) -> 343.1 | AI45: =SUM(W45,Y45,AC45) -> 338 | AJ45: =SUM(Z45,AD45) -> 220 | AK45: =SUM(X45,AA45) -> 222.5 | AL45: =SUM(AE45,R45,AB45) -> 339
A46: Rural+Urban | B46: 2014 | C46: March | D46: =B46&" "&C46 -> 2014 March | E46: 120.7 | F46: 119.3 | G46: 121 | H46: 116.1 | I46: 106.9 | J46: 118.7 | K46: 116.3 | L46: 109.8 | M46: 99.6 | N46: 111.8 | O46: 112.7 | P46: 119.3 | Q46: 116.1 | R46: 115.2 | S46: 116.8 | T46: 113.7 | U46: 116.4 | V46: 113.2 | W46: =IF(OR(V46="NA",V46="-"),V47,V46) -> 113.2 | X46: 112.5 | Y46: 113.2 | Z46: 111.2 | AA46: 111.4 | AB46: 110.6 | AC46: 112 | AD46: 109 | AE46: 111.3 | AF46: 114.2 | AG46: =SUM($E46:$Q46) -> 1488.3 | AH46: =SUM($S46:$U46) -> 346.9 | AI46: =SUM(W46,Y46,AC46) -> 338.4 | AJ46: =SUM(Z46,AD46) -> 220.2 | AK46: =SUM(X46,AA46) -> 223.9 | AL46: =SUM(AE46,R46,AB46) -> 337.1
A47: Rural | B47: 2014 | C47: April | D47: =B47&" "&C47 -> 2014 April | E47: 120.2 | F47: 118.9 | G47: 118.1 | H47: 117 | I47: 109.7 | J47: 125.5 | K47: 120.5 | L47: 111 | M47: 102.6 | N47: 111.2 | O47: 113.5 | P47: 118.7 | Q47: 117.2 | R47: 115.4 | S47: 118.1 | T47: 116.1 | U47: 117.8 | V47: NA | W47: =IF(OR(V47="NA",V47="-"),V48,V47) -> 113.9 | X47: 113.4 | Y47: 113.7 | Z47: 111.8 | AA47: 111.2 | AB47: 110.5 | AC47: 113 | AD47: 108.9 | AE47: 111.5 | AF47: 115.4 | AG47: =SUM($E47:$Q47) -> 1504.1 | AH47: =SUM($S47:$U47) -> 352 | AI47: =SUM(W47,Y47,AC47) -> 340.6 | AJ47: =SUM(Z47,AD47) -> 220.7 | AK47: =SUM(X47,AA47) -> 224.6 | AL47: =SUM(AE47,R47,AB47) -> 337.4
A48: Urban | B48: 2014 | C48: April | D48: =B48&" "&C48 -> 2014 April | E48: 122.5 | F48: 121.7 | G48: 113.3 | H48: 117 | I48: 103.1 | J48: 126.7 | K48: 121.2 | L48: 111 | M48: 100.3 | N48: 115.3 | O48: 112.7 | P48: 121 | Q48: 118.2 | R48: 117.6 | S48: 116.3 | T48: 112.5 | U48: 115.7 | V48: 113.9 | W48: =IF(OR(V48="NA",V48="-"),V49,V48) -> 113.9 | X48: 110.9 | Y48: 113.4 | Z48: 111 | AA48: 111.2 | AB48: 111.2 | AC48: 112.5 | AD48: 109.1 | AE48: 111.4 | AF48: 114.7 | AG48: =SUM($E48:$Q48) -> 1504 | AH48: =SUM($S48:$U48) -> 344.5 | AI48: =SUM(W48,Y48,AC48) -> 339.8 | AJ48: =SUM(Z48,AD48) -> 220.1 | AK48: =SUM(X48,AA48) -> 222.1 | AL48: =SUM(AE48,R48,AB48) -> 340.2
A49: Rural+Urban | B49: 2014 | C49: April | D49: =B49&" "&C49 -> 2014 April | E49: 120.9 | F49: 119.9 | G49: 116.2 | H49: 117 | I49: 107.3 | J49: 126.1 | K49: 120.7 | L49: 111 | M49: 101.8 | N49: 112.6 | O49: 113.2 | P49: 119.8 | Q49: 117.6 | R49: 116 | S49: 117.4 | T49: 114.6 | U49: 117 | V49: 113.9 | W49: =IF(OR(V49="NA",V49="-"),V50,V49) -> 113.9 | X49: 112.5 | Y49: 113.6 | Z49: 111.5 | AA49: 111.2 | AB49: 110.9 | AC49: 112.7 | AD49: 109 | AE49: 111.5 | AF49: 115.1 | AG49: =SUM($E49:$Q49) -> 1504.1 | AH49: =SUM($S49:$U49) -> 349 | AI49: =SUM(W49,Y49,AC49) -> 340.2 | AJ49: =SUM(Z49,AD49) -> 220.5 | AK49: =SUM(X49,AA49) -> 223.7 | AL49: =SUM(AE49,R49,AB49) -> 338.4
A50: Rural | B50: 2014 | C50: May | D50: =B50&" "&C50 -> 2014 May | E50: 120.3 | F50: 120.2 | G50: 116.9 | H50: 118 | I50: 110.1 | J50: 126.3 | K50: 123.9 | L50: 111.5 | M50: 103.5 | N50: 111.6 | O50: 114.2 | P50: 119.2 | Q50: 118.2 | R50: 116.3 | S50: 118.7 | T50: 116.8 | U50: 118.5 | V50: NA | W50: =IF(OR(V50="NA",V50="-"),V51,V50) -> 114.3 | X50: 113.4 | Y50: 114.1 | Z50: 112.1 | AA50: 111.4 | AB50: 110.9 | AC50: 113.1 | AD50: 108.9 | AE50: 111.8 | AF50: 116 | AG50: =SUM($E50:$Q50) -> 1513.9 | AH50: =SUM($S50:$U50) -> 354 | AI50: =SUM(W50,Y50,AC50) -> 341.5 | AJ50: =SUM(Z50,AD50) -> 221 | AK50: =SUM(X50,AA50) -> 224.8 | AL50: =SUM(AE50,R50,AB50) -> 339
A51: Urban | B51: 2014 | C51: May | D51: =B51&" "&C51 -> 2014 May | E51: 122.7 | F51: 124.1 | G51: 114.2 | H51: 119.1 | I51: 103.5 | J51: 129.2 | K51: 127 | L51: 112.6 | M51: 101.3 | N51: 117 | O51: 112.9 | P51: 121.7 | Q51: 120 | R51: 118.3 | S51: 116.8 | T51: 112.9 | U51: 116.2 | V51: 114.3 | W51: =IF(OR(V51="NA",V51="-"),V52,V51) -> 114.3 | X51: 111.1 | Y51: 114.1 | Z51: 111.2 | AA51: 111.3 | AB51: 111.5 | AC51: 112.9 | AD51: 109.3 | AE51: 111.7 | AF51: 115.6 | AG51: =SUM($E51:$Q51) -> 1525.3 | AH51: =SUM($S51:$U51) -> 345.9 | AI51: =SUM(W51,Y51,AC51) -> 341.3 | AJ51: =SUM(Z51,AD51) -> 220.5 | AK51: =SUM(X51,AA51) -> 222.4 | AL51: =SUM(AE51,R51,AB51) -> 341.5
A52: Rural+Urban | B52: 2014 | C52: May | D52: =B52&" "&C52 -> 2014 May | E52: 121.1 | F52: 121.6 | G52: 115.9 | H52: 118.4 | I52: 107.7 | J52: 127.7 | K52: 125 | L52: 111.9 | M52: 102.8 | N52: 113.4 | O52: 113.7 | P52: 120.4 | Q52: 118.9 | R52: 116.8 | S52: 118 | T52: 115.2 | U52: 117.6 | V52: 114.3 | W52: =IF(OR(V52="NA",V52="-"),V53,V52) -> 114.3 | X52: 112.5 | Y52: 114.1 | Z52: 111.8 | AA52: 111.3 | AB52: 111.2 | AC52: 113 | AD52: 109.1 | AE52: 111.8 | AF52: 115.8 | AG52: =SUM($E52:$Q52) -> 1518.5 | AH52: =SUM($S52:$U52) -> 350.8 | AI52: =SUM(W52,Y52,AC52) -> 341.4 | AJ52: =SUM(Z52,AD52) -> 220.9 | AK52: =SUM(X52,AA52) -> 223.8 | AL52: =SUM(AE52,R52,AB52) -> 339.8
A53: Rural | B53: 2014 | C53: June | D53: =B53&" "&C53 -> 2014 June | E53: 120.7 | F53: 121.6 | G53: 116.1 | H53: 119.3 | I53: 110.3 | J53: 125.8 | K53: 129.3 | L53: 112.2 | M53: 103.6 | N53: 112.3 | O53: 114.9 | P53: 120.1 | Q53: 119.5 | R53: 117.3 | S53: 119.7 | T53: 117.3 | U53: 119.3 | V53: NA | W53: =IF(OR(V53="NA",V53="-"),V54,V53) -> 113.9 | X53: 114.4 | Y53: 114.9 | Z53: 112.8 | AA53: 112.2 | AB53: 111.4 | AC53: 114.3 | AD53: 108 | AE53: 112.3 | AF53: 117 | AG53: =SUM($E53:$Q53) -> 1525.7 | AH53: =SUM($S53:$U53) -> 356.3 | AI53: =SUM(W53,Y53,AC53) -> 343.1 | AJ53: =SUM(Z53,AD53) -> 220.8 | AK53: =SUM(X53,AA53) -> 226.6 | AL53: =SUM(AE53,R53,AB53) -> 341
A54: Urban | B54: 2014 | C54: June | D54: =B54&" "&C54 -> 2014 June | E54: 123.1 | F54: 125.9 | G54: 115.4 | H54: 120.4 | I54: 103.4 | J54: 131.2 | K54: 137.5 | L54: 112.8 | M54: 101.4 | N54: 118.3 | O54: 113.2 | P54: 122.4 | Q54: 122 | R54: 119 | S54: 117.4 | T54: 113.2 | U54: 116.7 | V54: 113.9 | W54: =IF(OR(V54="NA",V54="-"),V55,V54) -> 113.9 | X54: 111.2 | Y54: 114.3 | Z54: 111.4 | AA54: 111.5 | AB54: 111.8 | AC54: 115.1 | AD54: 108.7 | AE54: 112.2 | AF54: 116.4 | AG54: =SUM($E54:$Q54) -> 1547 | AH54: =SUM($S54:$U54) -> 347.3 | AI54: =SUM(W54,Y54,AC54) -> 343.3 | AJ54: =SUM(Z54,AD54) -> 220.1 | AK54: =SUM(X54,AA54) -> 222.7 | AL54: =SUM(AE54,R54,AB54) -> 343
A55: Rural+Urban | B55: 2014 | C55: June | D55: =B55&" "&C55 -> 2014 June | E55: 121.5 | F55: 123.1 | G55: 115.8 | H55: 119.7 | I55: 107.8 | J55: 128.3 | K55: 132.1 | L55: 112.4 | M55: 102.9 | N55: 114.3 | O55: 114.2 | P55: 121.2 | Q55: 120.4 | R55: 117.8 | S55: 118.8 | T55: 115.6 | U55: 118.3 | V55: 113.9 | W55: =IF(OR(V55="NA",V55="-"),V56,V55) -> 113.9 | X55: 113.2 | Y55: 114.6 | Z55: 112.3 | AA55: 111.8 | AB55: 111.6 | AC55: 114.8 | AD55: 108.3 | AE55: 112.3 | AF55: 116.7 | AG55: =SUM($E55:$Q55) -> 1533.7 | AH55: =SUM($S55:$U55) -> 352.7 | AI55: =SUM(W55,Y55,AC55) -> 343.3 | AJ55: =SUM(Z55,AD55) -> 220.6 | AK55: =SUM(X55,AA55) -> 225 | AL55: =SUM(AE55,R55,AB55) -> 341.7
A56: Rural | B56: 2014 | C56: July | D56: =B56&" "&C56 -> 2014 July | E56: 121.7 | F56: 122.5 | G56: 117.7 | H56: 120.6 | I56: 110.4 | J56: 129.1 | K56: 150.1 | L56: 113.2 | M56: 104.8 | N56: 113.3 | O56: 115.6 | P56: 120.9 | Q56: 123.3 | R56: 118 | S56: 120.7 | T56: 118.3 | U56: 120.3 | V56: NA | W56: =IF(OR(V56="NA",V56="-"),V57,V56) -> 114.8 | X56: 115.3 | Y56: 115.4 | Z56: 113.4 | AA56: 113.2 | AB56: 111.8 | AC56: 115.5 | AD56: 108.8 | AE56: 113.1 | AF56: 119.5 | AG56: =SUM($E56:$Q56) -> 1563.2 | AH56: =SUM($S56:$U56) -> 359.3 | AI56: =SUM(W56,Y56,AC56) -> 345.7 | AJ56: =SUM(Z56,AD56) -> 222.2 | AK56: =SUM(X56,AA56) -> 228.5 | AL56: =SUM(AE56,R56,AB56) -> 342.9
A57: Urban | B57: 2014 | C57: July | D57: =B57&" "&C57 -> 2014 July | E57: 123.8 | F57: 126.4 | G57: 118 | H57: 121.6 | I57: 103.5 | J57: 133.7 | K57: 172.4 | L57: 113.1 | M57: 102.7 | N57: 120 | O57: 113.8 | P57: 123.4 | Q57: 127.1 | R57: 121 | S57: 118 | T57: 113.6 | U57: 117.4 | V57: 114.8 | W57: =IF(OR(V57="NA",V57="-"),V58,V57) -> 114.8 | X57: 111.6 | Y57: 114.9 | Z57: 111.5 | AA57: 113 | AB57: 112.4 | AC57: 117.8 | AD57: 109.7 | AE57: 113.5 | AF57: 118.9 | AG57: =SUM($E57:$Q57) -> 1599.5 | AH57: =SUM($S57:$U57) -> 349 | AI57: =SUM(W57,Y57,AC57) -> 347.5 | AJ57: =SUM(Z57,AD57) -> 221.2 | AK57: =SUM(X57,AA57) -> 224.6 | AL57: =SUM(AE57,R57,AB57) -> 346.9
A58: Rural+Urban | B58: 2014 | C58: July | D58: =B58&" "&C58 -> 2014 July | E58: 122.4 | F58: 123.9 | G58: 117.8 | H58: 121 | I58: 107.9 | J58: 131.2 | K58: 157.7 | L58: 113.2 | M58: 104.1 | N58: 115.5 | O58: 114.8 | P58: 122.1 | Q58: 124.7 | R58: 118.8 | S58: 119.6 | T58: 116.3 | U58: 119.1 | V58: 114.8 | W58: =IF(OR(V58="NA",V58="-"),V59,V58) -> 114.8 | X58: 113.9 | Y58: 115.2 | Z58: 112.7 | AA58: 113.1 | AB58: 112.1 | AC58: 116.8 | AD58: 109.2 | AE58: 113.3 | AF58: 119.2 | AG58: =SUM($E58:$Q58) -> 1576.3 | AH58: =SUM($S58:$U58) -> 355 | AI58: =SUM(W58,Y58,AC58) -> 346.8 | AJ58: =SUM(Z58,AD58) -> 221.9 | AK58: =SUM(X58,AA58) -> 227 | AL58: =SUM(AE58,R58,AB58) -> 344.2
A59: Rural | B59: 2014 | C59: August | D59: =B59&" "&C59 -> 2014 August | E59: 121.8 | F59: 122.8 | G59: 117.8 | H59: 121.9 | I59: 110.6 | J59: 129.7 | K59: 161.1 | L59: 114.1 | M59: 105.1 | N59: 114.6 | O59: 115.8 | P59: 121.7 | Q59: 125.3 | R59: 118.8 | S59: 120.9 | T59: 118.8 | U59: 120.7 | V59: NA | W59: =IF(OR(V59="NA",V59="-"),V60,V59) -> 115.5 | X59: 115.4 | Y59: 115.9 | Z59: 114 | AA59: 113.2 | AB59: 112.2 | AC59: 116.2 | AD59: 109.4 | AE59: 113.5 | AF59: 120.7 | AG59: =SUM($E59:$Q59) -> 1582.3 | AH59: =SUM($S59:$U59) -> 360.4 | AI59: =SUM(W59,Y59,AC59) -> 347.6 | AJ59: =SUM(Z59,AD59) -> 223.4 | AK59: =SUM(X59,AA59) -> 228.6 | AL59: =SUM(AE59,R59,AB59) -> 344.5
A60: Urban | B60: 2014 | C60: August | D60: =B60&" "&C60 -> 2014 August | E60: 124.8 | F60: 127.3 | G60: 116.5 | H60: 122.2 | I60: 103.6 | J60: 132.7 | K60: 181.9 | L60: 115.2 | M60: 102.7 | N60: 122.1 | O60: 114.4 | P60: 124.7 | Q60: 128.9 | R60: 123 | S60: 118.6 | T60: 114.1 | U60: 117.9 | V60: 115.5 | W60: =IF(OR(V60="NA",V60="-"),V61,V60) -> 115.5 | X60: 111.8 | Y60: 115.3 | Z60: 112.2 | AA60: 112.5 | AB60: 112.9 | AC60: 119.2 | AD60: 110.5 | AE60: 113.9 | AF60: 119.9 | AG60: =SUM($E60:$Q60) -> 1617 | AH60: =SUM($S60:$U60) -> 350.6 | AI60: =SUM(W60,Y60,AC60) -> 350 | AJ60: =SUM(Z60,AD60) -> 222.7 | AK60: =SUM(X60,AA60) -> 224.3 | AL60: =SUM(AE60,R60,AB60) -> 349.8
A61: Rural+Urban | B61: 2014 | C61: August | D61: =B61&" "&C61 -> 2014 August | E61: 122.7 | F61: 124.4 | G61: 117.3 | H61: 122 | I61: 108 | J61: 131.1 | K61: 168.2 | L61: 114.5 | M61: 104.3 | N61: 117.1 | O61: 115.2 | P61: 123.1 | Q61: 126.6 | R61: 119.9 | S61: 120 | T61: 116.8 | U61: 119.6 | V61: 115.5 | W61: =IF(OR(V61="NA",V61="-"),V62,V61) -> 115.5 | X61: 114 | Y61: 115.6 | Z61: 113.3 | AA61: 112.8 | AB61: 112.6 | AC61: 118 | AD61: 109.9 | AE61: 113.7 | AF61: 120.3 | AG61: =SUM($E61:$Q61) -> 1594.5 | AH61: =SUM($S61:$U61) -> 356.4 | AI61: =SUM(W61,Y61,AC61) -> 349.1 | AJ61: =SUM(Z61,AD61) -> 223.2 | AK61: =SUM(X61,AA61) -> 226.8 | AL61: =SUM(AE61,R61,AB61) -> 346.2
A62: Rural | B62: 2014 | C62: September | D62: =B62&" "&C62 -> 2014 September | E62: 122.3 | F62: 122.4 | G62: 117.8 | H62: 122.7 | I62: 110.4 | J62: 129.8 | K62: 158.8 | L62: 115 | M62: 104.7 | N62: 114.9 | O62: 116.5 | P62: 122.6 | Q62: 125.3 | R62: 119.5 | S62: 121.7 | T62: 119.2 | U62: 121.3 | V62: NA | W62: =IF(OR(V62="NA",V62="-"),V63,V62) -> 116.1 | X62: 115.8 | Y62: 116.7 | Z62: 114.5 | AA62: 112.8 | AB62: 112.6 | AC62: 116.6 | AD62: 109.1 | AE62: 113.7 | AF62: 120.9 | AG62: =SUM($E62:$Q62) -> 1583.2 | AH62: =SUM($S62:$U62) -> 362.2 | AI62: =SUM(W62,Y62,AC62) -> 349.4 | AJ62: =SUM(Z62,AD62) -> 223.6 | AK62: =SUM(X62,AA62) -> 228.6 | AL62: =SUM(AE62,R62,AB62) -> 345.8
A63: Urban | B63: 2014 | C63: September | D63: =B63&" "&C63 -> 2014 September | E63: 124.2 | F63: 125.4 | G63: 116.4 | H63: 122.7 | I63: 103.5 | J63: 124.5 | K63: 168.6 | L63: 116.9 | M63: 101.9 | N63: 122.9 | O63: 114.8 | P63: 125.2 | Q63: 126.7 | R63: 124.3 | S63: 119.2 | T63: 114.5 | U63: 118.4 | V63: 116.1 | W63: =IF(OR(V63="NA",V63="-"),V64,V63) -> 116.1 | X63: 111.8 | Y63: 115.5 | Z63: 112.3 | AA63: 111.2 | AB63: 113.4 | AC63: 120 | AD63: 110 | AE63: 113.6 | AF63: 119.2 | AG63: =SUM($E63:$Q63) -> 1593.7 | AH63: =SUM($S63:$U63) -> 352.1 | AI63: =SUM(W63,Y63,AC63) -> 351.6 | AJ63: =SUM(Z63,AD63) -> 222.3 | AK63: =SUM(X63,AA63) -> 223 | AL63: =SUM(AE63,R63,AB63) -> 351.3
A64: Rural+Urban | B64: 2014 | C64: September | D64: =B64&" "&C64 -> 2014 September | E64: 122.9 | F64: 123.5 | G64: 117.3 | H64: 122.7 | I64: 107.9 | J64: 127.3 | K64: 162.1 | L64: 115.6 | M64: 103.8 | N64: 117.6 | O64: 115.8 | P64: 123.8 | Q64: 125.8 | R64: 120.8 | S64: 120.7 | T64: 117.2 | U64: 120.1 | V64: 116.1 | W64: =IF(OR(V64="NA",V64="-"),V65,V64) -> 116.1 | X64: 114.3 | Y64: 116.1 | Z64: 113.7 | AA64: 112 | AB64: 113.1 | AC64: 118.6 | AD64: 109.5 | AE64: 113.7 | AF64: 120.1 | AG64: =SUM($E64:$Q64) -> 1586.1 | AH64: =SUM($S64:$U64) -> 358 | AI64: =SUM(W64,Y64,AC64) -> 350.8 | AJ64: =SUM(Z64,AD64) -> 223.2 | AK64: =SUM(X64,AA64) -> 226.3 | AL64: =SUM(AE64,R64,AB64) -> 347.6
A65: Rural | B65: 2014 | C65: October | D65: =B65&" "&C65 -> 2014 October | E65: 122.6 | F65: 122.5 | G65: 118.3 | H65: 123.2 | I65: 110.5 | J65: 128.9 | K65: 155.3 | L65: 115.5 | M65: 104 | N65: 115.3 | O65: 116.8 | P65: 123.2 | Q65: 125.1 | R65: 120 | S65: 122.7 | T65: 120.3 | U65: 122.3 | V65: NA | W65: =IF(OR(V65="NA",V65="-"),V66,V65) -> 116.7 | X65: 116.4 | Y65: 117.5 | Z65: 115.3 | AA65: 112.6 | AB65: 113 | AC65: 116.9 | AD65: 109.3 | AE65: 114 | AF65: 121 | AG65: =SUM($E65:$Q65) -> 1581.2 | AH65: =SUM($S65:$U65) -> 365.3 | AI65: =SUM(W65,Y65,AC65) -> 351.1 | AJ65: =SUM(Z65,AD65) -> 224.6 | AK65: =SUM(X65,AA65) -> 229 | AL65: =SUM(AE65,R65,AB65) -> 347
A66: Urban | B66: 2014 | C66: October | D66: =B66&" "&C66 -> 2014 October | E66: 124.6 | F66: 126.1 | G66: 117.8 | H66: 123.1 | I66: 103.5 | J66: 123.5 | K66: 159.6 | L66: 117.4 | M66: 101.2 | N66: 123.8 | O66: 115.2 | P66: 125.9 | Q66: 125.8 | R66: 124.3 | S66: 119.6 | T66: 114.9 | U66: 118.9 | V66: 116.7 | W66: =IF(OR(V66="NA",V66="-"),V67,V66) -> 116.7 | X66: 112 | Y66: 115.8 | Z66: 112.6 | AA66: 111 | AB66: 113.6 | AC66: 120.2 | AD66: 110.1 | AE66: 113.7 | AF66: 119.1 | AG66: =SUM($E66:$Q66) -> 1587.5 | AH66: =SUM($S66:$U66) -> 353.4 | AI66: =SUM(W66,Y66,AC66) -> 352.7 | AJ66: =SUM(Z66,AD66) -> 222.7 | AK66: =SUM(X66,AA66) -> 223 | AL66: =SUM(AE66,R66,AB66) -> 351.6
A67: Rural+Urban | B67: 2014 | C67: October | D67: =B67&" "&C67 -> 2014 October | E67: 123.2 | F67: 123.8 | G67: 118.1 | H67: 123.2 | I67: 107.9 | J67: 126.4 | K67: 156.8 | L67: 116.1 | M67: 103.1 | N67: 118.1 | O67: 116.1 | P67: 124.5 | Q67: 125.4 | R67: 121.1 | S67: 121.5 | T67: 118.1 | U67: 121 | V67: 116.7 | W67: =IF(OR(V67="NA",V67="-"),V68,V67) -> 116.7 | X67: 114.7 | Y67: 116.7 | Z67: 114.3 | AA67: 111.8 | AB67: 113.3 | AC67: 118.8 | AD67: 109.6 | AE67: 113.9 | AF67: 120.1 | AG67: =SUM($E67:$Q67) -> 1582.7 | AH67: =SUM($S67:$U67) -> 360.6 | AI67: =SUM(W67,Y67,AC67) -> 352.2 | AJ67: =SUM(Z67,AD67) -> 223.9 | AK67: =SUM(X67,AA67) -> 226.5 | AL67: =SUM(AE67,R67,AB67) -> 348.3
A68: Rural | B68: 2014 | C68: November | D68: =B68&" "&C68 -> 2014 November | E68: 122.7 | F68: 122.6 | G68: 119.9 | H68: 124 | I68: 110.5 | J68: 128.8 | K68: 152 | L68: 116.2 | M68: 103.3 | N68: 115.8 | O68: 116.8 | P68: 124.5 | Q68: 124.9 | R68: 120.8 | S68: 123.3 | T68: 120.5 | U68: 122.9 | V68: NA | W68: =IF(OR(V68="NA",V68="-"),V69,V68) -> 117.1 | X68: 117.3 | Y68: 118.1 | Z68: 115.9 | AA68: 112 | AB68: 113.3 | AC68: 117.2 | AD68: 108.8 | AE68: 114.1 | AF68: 121.1 | AG68: =SUM($E68:$Q68) -> 1582 | AH68: =SUM($S68:$U68) -> 366.7 | AI68: =SUM(W68,Y68,AC68) -> 352.4 | AJ68: =SUM(Z68,AD68) -> 224.7 | AK68: =SUM(X68,AA68) -> 229.3 | AL68: =SUM(AE68,R68,AB68) -> 348.2
A69: Urban | B69: 2014 | C69: November | D69: =B69&" "&C69 -> 2014 November | E69: 124.5 | F69: 125.6 | G69: 122.7 | H69: 124.6 | I69: 103.2 | J69: 122.2 | K69: 153.2 | L69: 119.3 | M69: 99.8 | N69: 124.6 | O69: 115.8 | P69: 126.9 | Q69: 125.4 | R69: 125.8 | S69: 120.3 | T69: 115.4 | U69: 119.5 | V69: 117.1 | W69: =IF(OR(V69="NA",V69="-"),V70,V69) -> 117.1 | X69: 112.6 | Y69: 116.4 | Z69: 113 | AA69: 109.7 | AB69: 114 | AC69: 120.3 | AD69: 109.6 | AE69: 113.4 | AF69: 119 | AG69: =SUM($E69:$Q69) -> 1587.8 | AH69: =SUM($S69:$U69) -> 355.2 | AI69: =SUM(W69,Y69,AC69) -> 353.8 | AJ69: =SUM(Z69,AD69) -> 222.6 | AK69: =SUM(X69,AA69) -> 222.3 | AL69: =SUM(AE69,R69,AB69) -> 353.2
A70: Rural+Urban | B70: 2014 | C70: November | D70: =B70&" "&C70 -> 2014 November | E70: 123.3 | F70: 123.7 | G70: 121 | H70: 124.2 | I70: 107.8 | J70: 125.7 | K70: 152.4 | L70: 117.2 | M70: 102.1 | N70: 118.7 | O70: 116.4 | P70: 125.6 | Q70: 125.1 | R70: 122.1 | S70: 122.1 | T70: 118.4 | U70: 121.6 | V70: 117.1 | W70: =IF(OR(V70="NA",V70="-"),V71,V70) -> 117.1 | X70: 115.5 | Y70: 117.3 | Z70: 114.8 | AA70: 110.8 | AB70: 113.7 | AC70: 119 | AD70: 109.1 | AE70: 113.8 | AF70: 120.1 | AG70: =SUM($E70:$Q70) -> 1583.2 | AH70: =SUM($S70:$U70) -> 362.1 | AI70: =SUM(W70,Y70,AC70) -> 353.4 | AJ70: =SUM(Z70,AD70) -> 223.9 | AK70: =SUM(X70,AA70) -> 226.3 | AL70: =SUM(AE70,R70,AB70) -> 349.6
A71: Rural | B71: 2014 | C71: December | D71: =B71&" "&C71 -> 2014 December | E71: 122.4 | F71: 122.4 | G71: 121.8 | H71: 124.2 | I71: 110.2 | J71: 128.6 | K71: 140.3 | L71: 116.3 | M71: 102 | N71: 116 | O71: 117.3 | P71: 124.8 | Q71: 123.3 | R71: 121.7 | S71: 123.8 | T71: 120.6 | U71: 123.3 | V71: NA | W71: =IF(OR(V71="NA",V71="-"),V72,V71) -> 116.5 | X71: 117.4 | Y71: 118.2 | Z71: 116.2 | AA71: 111.5 | AB71: 113.3 | AC71: 117.7 | AD71: 109.4 | AE71: 114.2 | AF71: 120.3 | AG71: =SUM($E71:$Q71) -> 1569.6 | AH71: =SUM($S71:$U71) -> 367.7 | AI71: =SUM(W71,Y71,AC71) -> 352.4 | AJ71: =SUM(Z71,AD71) -> 225.6 | AK71: =SUM(X71,AA71) -> 228.9 | AL71: =SUM(AE71,R71,AB71) -> 349.2
A72: Urban | B72: 2014 | C72: December | D72: =B72&" "&C72 -> 2014 December | E72: 124 | F72: 124.7 | G72: 126.3 | H72: 124.9 | I72: 103 | J72: 122.3 | K72: 141 | L72: 120.1 | M72: 97.8 | N72: 125.4 | O72: 116.1 | P72: 127.6 | Q72: 124 | R72: 126.4 | S72: 120.7 | T72: 115.8 | U72: 120 | V72: 116.5 | W72: =IF(OR(V72="NA",V72="-"),V73,V72) -> 116.5 | X72: 113 | Y72: 116.8 | Z72: 113.2 | AA72: 108.8 | AB72: 114.3 | AC72: 120.7 | AD72: 110.4 | AE72: 113.4 | AF72: 118.4 | AG72: =SUM($E72:$Q72) -> 1577.2 | AH72: =SUM($S72:$U72) -> 356.5 | AI72: =SUM(W72,Y72,AC72) -> 354 | AJ72: =SUM(Z72,AD72) -> 223.6 | AK72: =SUM(X72,AA72) -> 221.8 | AL72: =SUM(AE72,R72,AB72) -> 354.1
A73: Rural+Urban | B73: 2014 | C73: December | D73: =B73&" "&C73 -> 2014 December | E73: 122.9 | F73: 123.2 | G73: 123.5 | H73: 124.5 | I73: 107.6 | J73: 125.7 | K73: 140.5 | L73: 117.6 | M73: 100.6 | N73: 119.1 | O73: 116.8 | P73: 126.1 | Q73: 123.6 | R73: 123 | S73: 122.6 | T73: 118.6 | U73: 122 | V73: 116.5 | W73: =IF(OR(V73="NA",V73="-"),V74,V73) -> 116.5 | X73: 115.7 | Y73: 117.5 | Z73: 115.1 | AA73: 110.1 | AB73: 113.9 | AC73: 119.5 | AD73: 109.8 | AE73: 113.8 | AF73: 119.4 | AG73: =SUM($E73:$Q73) -> 1571.7 | AH73: =SUM($S73:$U73) -> 363.2 | AI73: =SUM(W73,Y73,AC73) -> 353.5 | AJ73: =SUM(Z73,AD73) -> 224.9 | AK73: =SUM(X73,AA73) -> 225.8 | AL73: =SUM(AE73,R73,AB73) -> 350.7
A74: Rural | B74: 2015 | C74: January | D74: =B74&" "&C74 -> 2015 January | E74: 123.1 | F74: 123.1 | G74: 122.1 | H74: 124.9 | I74: 111 | J74: 130.4 | K74: 132.3 | L74: 117.2 | M74: 100.5 | N74: 117.2 | O74: 117.9 | P74: 125.6 | Q74: 122.8 | R74: 122.7 | S74: 124.4 | T74: 121.6 | U74: 124 | V74: NA | W74: =IF(OR(V74="NA",V74="-"),V75,V74) -> 117.3 | X74: 118.4 | Y74: 118.9 | Z74: 116.6 | AA74: 111 | AB74: 114 | AC74: 118.2 | AD74: 110.2 | AE74: 114.5 | AF74: 120.3 | AG74: =SUM($E74:$Q74) -> 1568.1 | AH74: =SUM($S74:$U74) -> 370 | AI74: =SUM(W74,Y74,AC74) -> 354.4 | AJ74: =SUM(Z74,AD74) -> 226.8 | AK74: =SUM(X74,AA74) -> 229.4 | AL74: =SUM(AE74,R74,AB74) -> 351.2
A75: Urban | B75: 2015 | C75: January | D75: =B75&" "&C75 -> 2015 January | E75: 124 | F75: 125.5 | G75: 126.6 | H75: 125.2 | I75: 104.3 | J75: 121.3 | K75: 134.4 | L75: 122.9 | M75: 96.1 | N75: 126.6 | O75: 116.5 | P75: 128 | Q75: 123.5 | R75: 127.4 | S75: 121 | T75: 116.1 | U75: 120.2 | V75: 117.3 | W75: =IF(OR(V75="NA",V75="-"),V76,V75) -> 117.3 | X75: 113.4 | Y75: 117.2 | Z75: 113.7 | AA75: 107.9 | AB75: 114.6 | AC75: 120.8 | AD75: 111.4 | AE75: 113.4 | AF75: 118.5 | AG75: =SUM($E75:$Q75) -> 1574.9 | AH75: =SUM($S75:$U75) -> 357.3 | AI75: =SUM(W75,Y75,AC75) -> 355.3 | AJ75: =SUM(Z75,AD75) -> 225.1 | AK75: =SUM(X75,AA75) -> 221.3 | AL75: =SUM(AE75,R75,AB75) -> 355.4
A76: Rural+Urban | B76: 2015 | C76: January | D76: =B76&" "&C76 -> 2015 January | E76: 123.4 | F76: 123.9 | G76: 123.8 | H76: 125 | I76: 108.5 | J76: 126.2 | K76: 133 | L76: 119.1 | M76: 99 | N76: 120.3 | O76: 117.3 | P76: 126.7 | Q76: 123.1 | R76: 124 | S76: 123.1 | T76: 119.3 | U76: 122.5 | V76: 117.3 | W76: =IF(OR(V76="NA",V76="-"),V77,V76) -> 117.3 | X76: 116.5 | Y76: 118.1 | Z76: 115.5 | AA76: 109.4 | AB76: 114.3 | AC76: 119.7 | AD76: 110.7 | AE76: 114 | AF76: 119.5 | AG76: =SUM($E76:$Q76) -> 1569.3 | AH76: =SUM($S76:$U76) -> 364.9 | AI76: =SUM(W76,Y76,AC76) -> 355.1 | AJ76: =SUM(Z76,AD76) -> 226.2 | AK76: =SUM(X76,AA76) -> 225.9 | AL76: =SUM(AE76,R76,AB76) -> 352.3
A77: Rural | B77: 2015 | C77: February | D77: =B77&" "&C77 -> 2015 February | E77: 123.4 | F77: 124.4 | G77: 122.1 | H77: 125.8 | I77: 111.5 | J77: 129.4 | K77: 128.2 | L77: 118.8 | M77: 100 | N77: 118.6 | O77: 118.8 | P77: 126.8 | Q77: 122.8 | R77: 124.2 | S77: 125.4 | T77: 122.7 | U77: 125 | V77: NA | W77: =IF(OR(V77="NA",V77="-"),V78,V77) -> 118.1 | X77: 120 | Y77: 119.6 | Z77: 117.7 | AA77: 110.9 | AB77: 114.8 | AC77: 118.7 | AD77: 110.8 | AE77: 115 | AF77: 120.6 | AG77: =SUM($E77:$Q77) -> 1570.6 | AH77: =SUM($S77:$U77) -> 373.1 | AI77: =SUM(W77,Y77,AC77) -> 356.4 | AJ77: =SUM(Z77,AD77) -> 228.5 | AK77: =SUM(X77,AA77) -> 230.9 | AL77: =SUM(AE77,R77,AB77) -> 354
A78: Urban | B78: 2015 | C78: February | D78: =B78&" "&C78 -> 2015 February | E78: 124.3 | F78: 126.5 | G78: 119.5 | H78: 125.6 | I78: 104.9 | J78: 121.6 | K78: 131.8 | L78: 125.1 | M78: 95 | N78: 127.7 | O78: 116.8 | P78: 128.6 | Q78: 123.7 | R78: 128.1 | S78: 121.3 | T78: 116.5 | U78: 120.6 | V78: 118.1 | W78: =IF(OR(V78="NA",V78="-"),V79,V78) -> 118.1 | X78: 114 | Y78: 117.7 | Z78: 114.1 | AA78: 106.8 | AB78: 114.9 | AC78: 120.4 | AD78: 111.7 | AE78: 113.2 | AF78: 118.7 | AG78: =SUM($E78:$Q78) -> 1571.1 | AH78: =SUM($S78:$U78) -> 358.4 | AI78: =SUM(W78,Y78,AC78) -> 356.2 | AJ78: =SUM(Z78,AD78) -> 225.8 | AK78: =SUM(X78,AA78) -> 220.8 | AL78: =SUM(AE78,R78,AB78) -> 356.2
A79: Rural+Urban | B79: 2015 | C79: February | D79: =B79&" "&C79 -> 2015 February | E79: 123.7 | F79: 125.1 | G79: 121.1 | H79: 125.7 | I79: 109.1 | J79: 125.8 | K79: 129.4 | L79: 120.9 | M79: 98.3 | N79: 121.6 | O79: 118 | P79: 127.6 | Q79: 123.1 | R79: 125.2 | S79: 123.8 | T79: 120.1 | U79: 123.3 | V79: 118.1 | W79: =IF(OR(V79="NA",V79="-"),V80,V79) -> 118.1 | X79: 117.7 | Y79: 118.7 | Z79: 116.3 | AA79: 108.7 | AB79: 114.9 | AC79: 119.7 | AD79: 111.2 | AE79: 114.1 | AF79: 119.7 | AG79: =SUM($E79:$Q79) -> 1569.4 | AH79: =SUM($S79:$U79) -> 367.2 | AI79: =SUM(W79,Y79,AC79) -> 356.5 | AJ79: =SUM(Z79,AD79) -> 227.5 | AK79: =SUM(X79,AA79) -> 226.4 | AL79: =SUM(AE79,R79,AB79) -> 354.2
A80: Rural | B80: 2015 | C80: March | D80: =B80&" "&C80 -> 2015 March | E80: 123.3 | F80: 124.7 | G80: 118.9 | H80: 126 | I80: 111.8 | J80: 130.9 | K80: 128 | L80: 119.9 | M80: 98.9 | N80: 119.4 | O80: 118.9 | P80: 127.7 | Q80: 123.1 | R80: 124.7 | S80: 126 | T80: 122.9 | U80: 125.5 | V80: NA | W80: =IF(OR(V80="NA",V80="-"),V81,V80) -> 118.6 | X80: 120.6 | Y80: 120.2 | Z80: 118.2 | AA80: 111.6 | AB80: 115.5 | AC80: 119.4 | AD80: 110.8 | AE80: 115.5 | AF80: 121.1 | AG80: =SUM($E80:$Q80) -> 1571.5 | AH80: =SUM($S80:$U80) -> 374.4 | AI80: =SUM(W80,Y80,AC80) -> 358.2 | AJ80: =SUM(Z80,AD80) -> 229 | AK80: =SUM(X80,AA80) -> 232.2 | AL80: =SUM(AE80,R80,AB80) -> 355.7
A81: Urban | B81: 2015 | C81: March | D81: =B81&" "&C81 -> 2015 March | E81: 124 | F81: 126.7 | G81: 113.5 | H81: 125.9 | I81: 104.8 | J81: 123.8 | K81: 131.4 | L81: 127.2 | M81: 93.2 | N81: 127.4 | O81: 117 | P81: 129.2 | Q81: 123.9 | R81: 128.8 | S81: 121.7 | T81: 116.9 | U81: 120.9 | V81: 118.6 | W81: =IF(OR(V81="NA",V81="-"),V82,V81) -> 118.6 | X81: 114.4 | Y81: 118 | Z81: 114.3 | AA81: 108.4 | AB81: 115.4 | AC81: 120.6 | AD81: 111.3 | AE81: 113.8 | AF81: 119.1 | AG81: =SUM($E81:$Q81) -> 1568 | AH81: =SUM($S81:$U81) -> 359.5 | AI81: =SUM(W81,Y81,AC81) -> 357.2 | AJ81: =SUM(Z81,AD81) -> 225.6 | AK81: =SUM(X81,AA81) -> 222.8 | AL81: =SUM(AE81,R81,AB81) -> 358
A82: Rural+Urban | B82: 2015 | C82: March | D82: =B82&" "&C82 -> 2015 March | E82: 123.5 | F82: 125.4 | G82: 116.8 | H82: 126 | I82: 109.2 | J82: 127.6 | K82: 129.2 | L82: 122.4 | M82: 97 | N82: 122.1 | O82: 118.1 | P82: 128.4 | Q82: 123.4 | R82: 125.8 | S82: 124.3 | T82: 120.4 | U82: 123.7 | V82: 118.6 | W82: =IF(OR(V82="NA",V82="-"),V83,V82) -> 118.6 | X82: 118.3 | Y82: 119.2 | Z82: 116.7 | AA82: 109.9 | AB82: 115.4 | AC82: 120.1 | AD82: 111 | AE82: 114.7 | AF82: 120.2 | AG82: =SUM($E82:$Q82) -> 1569.1 | AH82: =SUM($S82:$U82) -> 368.4 | AI82: =SUM(W82,Y82,AC82) -> 357.9 | AJ82: =SUM(Z82,AD82) -> 227.7 | AK82: =SUM(X82,AA82) -> 228.2 | AL82: =SUM(AE82,R82,AB82) -> 355.9
A83: Rural | B83: 2015 | C83: April | D83: =B83&" "&C83 -> 2015 April | E83: 123.3 | F83: 125.5 | G83: 117.2 | H83: 126.8 | I83: 111.9 | J83: 134.2 | K83: 127.5 | L83: 121.5 | M83: 97.8 | N83: 119.8 | O83: 119.4 | P83: 128.7 | Q83: 123.6 | R83: 125.7 | S83: 126.4 | T83: 123.3 | U83: 126 | V83: NA | W83: =IF(OR(V83="NA",V83="-"),V84,V83) -> 119.2 | X83: 121.2 | Y83: 120.9 | Z83: 118.6 | AA83: 111.9 | AB83: 116.2 | AC83: 119.9 | AD83: 111.6 | AE83: 116 | AF83: 121.5 | AG83: =SUM($E83:$Q83) -> 1577.2 | AH83: =SUM($S83:$U83) -> 375.7 | AI83: =SUM(W83,Y83,AC83) -> 360 | AJ83: =SUM(Z83,AD83) -> 230.2 | AK83: =SUM(X83,AA83) -> 233.1 | AL83: =SUM(AE83,R83,AB83) -> 357.9
A84: Urban | B84: 2015 | C84: April | D84: =B84&" "&C84 -> 2015 April | E84: 123.8 | F84: 128.2 | G84: 110 | H84: 126.3 | I84: 104.5 | J84: 130.6 | K84: 130.8 | L84: 131.3 | M84: 91.6 | N84: 127.7 | O84: 117.2 | P84: 129.5 | Q84: 124.6 | R84: 130.1 | S84: 122.1 | T84: 117.2 | U84: 121.3 | V84: 119.2 | W84: =IF(OR(V84="NA",V84="-"),V85,V84) -> 119.2 | X84: 114.7 | Y84: 118.4 | Z84: 114.6 | AA84: 108.4 | AB84: 115.6 | AC84: 121.7 | AD84: 111.8 | AE84: 114.2 | AF84: 119.7 | AG84: =SUM($E84:$Q84) -> 1576.1 | AH84: =SUM($S84:$U84) -> 360.6 | AI84: =SUM(W84,Y84,AC84) -> 359.3 | AJ84: =SUM(Z84,AD84) -> 226.4 | AK84: =SUM(X84,AA84) -> 223.1 | AL84: =SUM(AE84,R84,AB84) -> 359.9
A85: Rural+Urban | B85: 2015 | C85: April | D85: =B85&" "&C85 -> 2015 April | E85: 123.5 | F85: 126.4 | G85: 114.4 | H85: 126.6 | I85: 109.2 | J85: 132.5 | K85: 128.6 | L85: 124.8 | M85: 95.7 | N85: 122.4 | O85: 118.5 | P85: 129.1 | Q85: 124 | R85: 126.9 | S85: 124.7 | T85: 120.8 | U85: 124.1 | V85: 119.2 | W85: =IF(OR(V85="NA",V85="-"),V86,V85) -> 119.2 | X85: 118.7 | Y85: 119.7 | Z85: 117.1 | AA85: 110.1 | AB85: 115.9 | AC85: 121 | AD85: 111.7 | AE85: 115.1 | AF85: 120.7 | AG85: =SUM($E85:$Q85) -> 1575.7 | AH85: =SUM($S85:$U85) -> 369.6 | AI85: =SUM(W85,Y85,AC85) -> 359.9 | AJ85: =SUM(Z85,AD85) -> 228.8 | AK85: =SUM(X85,AA85) -> 228.8 | AL85: =SUM(AE85,R85,AB85) -> 357.9
A86: Rural | B86: 2015 | C86: May | D86: =B86&" "&C86 -> 2015 May | E86: 123.5 | F86: 127.1 | G86: 117.3 | H86: 127.7 | I86: 112.5 | J86: 134.1 | K86: 128.5 | L86: 124.3 | M86: 97.6 | N86: 120.7 | O86: 120.2 | P86: 129.8 | Q86: 124.4 | R86: 126.7 | S86: 127.3 | T86: 124.1 | U86: 126.8 | V86: NA | W86: =IF(OR(V86="NA",V86="-"),V87,V86) -> 119.6 | X86: 121.9 | Y86: 121.5 | Z86: 119.4 | AA86: 113.3 | AB86: 116.7 | AC86: 120.5 | AD86: 112.3 | AE86: 116.9 | AF86: 122.4 | AG86: =SUM($E86:$Q86) -> 1587.7 | AH86: =SUM($S86:$U86) -> 378.2 | AI86: =SUM(W86,Y86,AC86) -> 361.6 | AJ86: =SUM(Z86,AD86) -> 231.7 | AK86: =SUM(X86,AA86) -> 235.2 | AL86: =SUM(AE86,R86,AB86) -> 360.3
A87: Urban | B87: 2015 | C87: May | D87: =B87&" "&C87 -> 2015 May | E87: 123.8 | F87: 129.7 | G87: 111.3 | H87: 126.6 | I87: 105.2 | J87: 130.8 | K87: 135.6 | L87: 142.6 | M87: 90.8 | N87: 128.8 | O87: 117.7 | P87: 129.9 | Q87: 126.1 | R87: 131.3 | S87: 122.4 | T87: 117.4 | U87: 121.6 | V87: 119.6 | W87: =IF(OR(V87="NA",V87="-"),V88,V87) -> 119.6 | X87: 114.9 | Y87: 118.7 | Z87: 114.9 | AA87: 110.8 | AB87: 116 | AC87: 122 | AD87: 112.4 | AE87: 115.2 | AF87: 120.7 | AG87: =SUM($E87:$Q87) -> 1598.9 | AH87: =SUM($S87:$U87) -> 361.4 | AI87: =SUM(W87,Y87,AC87) -> 360.3 | AJ87: =SUM(Z87,AD87) -> 227.3 | AK87: =SUM(X87,AA87) -> 225.7 | AL87: =SUM(AE87,R87,AB87) -> 362.5
A88: Rural+Urban | B88: 2015 | C88: May | D88: =B88&" "&C88 -> 2015 May | E88: 123.6 | F88: 128 | G88: 115 | H88: 127.3 | I88: 109.8 | J88: 132.6 | K88: 130.9 | L88: 130.5 | M88: 95.3 | N88: 123.4 | O88: 119.2 | P88: 129.8 | Q88: 125 | R88: 127.9 | S88: 125.4 | T88: 121.3 | U88: 124.7 | V88: 119.6 | W88: =IF(OR(V88="NA",V88="-"),V89,V88) -> 119.6 | X88: 119.2 | Y88: 120.2 | Z88: 117.7 | AA88: 112 | AB88: 116.3 | AC88: 121.4 | AD88: 112.3 | AE88: 116.1 | AF88: 121.6 | AG88: =SUM($E88:$Q88) -> 1590.4 | AH88: =SUM($S88:$U88) -> 371.4 | AI88: =SUM(W88,Y88,AC88) -> 361.2 | AJ88: =SUM(Z88,AD88) -> 230 | AK88: =SUM(X88,AA88) -> 231.2 | AL88: =SUM(AE88,R88,AB88) -> 360.3
A89: Rural | B89: 2015 | C89: June | D89: =B89&" "&C89 -> 2015 June | E89: 124.1 | F89: 130.4 | G89: 122.1 | H89: 128.7 | I89: 114.1 | J89: 133.2 | K89: 135.2 | L89: 131.9 | M89: 96.3 | N89: 123 | O89: 121.1 | P89: 131.2 | Q89: 126.6 | R89: 128.2 | S89: 128.4 | T89: 125.1 | U89: 128 | V89: NA | W89: =IF(OR(V89="NA",V89="-"),V90,V89) -> 119 | X89: 122.6 | Y89: 122.8 | Z89: 120.4 | AA89: 114.2 | AB89: 117.9 | AC89: 122 | AD89: 113 | AE89: 117.9 | AF89: 124.1 | AG89: =SUM($E89:$Q89) -> 1617.9 | AH89: =SUM($S89:$U89) -> 381.5 | AI89: =SUM(W89,Y89,AC89) -> 363.8 | AJ89: =SUM(Z89,AD89) -> 233.4 | AK89: =SUM(X89,AA89) -> 236.8 | AL89: =SUM(AE89,R89,AB89) -> 364
A90: Urban | B90: 2015 | C90: June | D90: =B90&" "&C90 -> 2015 June | E90: 123.6 | F90: 134.4 | G90: 120.9 | H90: 127.3 | I90: 106 | J90: 132.3 | K90: 146.7 | L90: 148.1 | M90: 89.8 | N90: 130.5 | O90: 118 | P90: 130.5 | Q90: 128.5 | R90: 132.1 | S90: 123.2 | T90: 117.6 | U90: 122.3 | V90: 119 | W90: =IF(OR(V90="NA",V90="-"),V91,V90) -> 119 | X90: 115.1 | Y90: 119.2 | Z90: 115.4 | AA90: 111.7 | AB90: 116.2 | AC90: 123.8 | AD90: 112.5 | AE90: 116 | AF90: 121.7 | AG90: =SUM($E90:$Q90) -> 1636.6 | AH90: =SUM($S90:$U90) -> 363.1 | AI90: =SUM(W90,Y90,AC90) -> 362 | AJ90: =SUM(Z90,AD90) -> 227.9 | AK90: =SUM(X90,AA90) -> 226.8 | AL90: =SUM(AE90,R90,AB90) -> 364.3
A91: Rural+Urban | B91: 2015 | C91: June | D91: =B91&" "&C91 -> 2015 June | E91: 123.9 | F91: 131.8 | G91: 121.6 | H91: 128.2 | I91: 111.1 | J91: 132.8 | K91: 139.1 | L91: 137.4 | M91: 94.1 | N91: 125.5 | O91: 119.8 | P91: 130.9 | Q91: 127.3 | R91: 129.2 | S91: 126.4 | T91: 122 | U91: 125.7 | V91: 119 | W91: =IF(OR(V91="NA",V91="-"),V92,V91) -> 119 | X91: 119.8 | Y91: 121.1 | Z91: 118.5 | AA91: 112.9 | AB91: 116.9 | AC91: 123.1 | AD91: 112.8 | AE91: 117 | AF91: 123 | AG91: =SUM($E91:$Q91) -> 1623.5 | AH91: =SUM($S91:$U91) -> 374.1 | AI91: =SUM(W91,Y91,AC91) -> 363.2 | AJ91: =SUM(Z91,AD91) -> 231.3 | AK91: =SUM(X91,AA91) -> 232.7 | AL91: =SUM(AE91,R91,AB91) -> 363.1
A92: Rural | B92: 2015 | C92: July | D92: =B92&" "&C92 -> 2015 July | E92: 124 | F92: 131.5 | G92: 122 | H92: 128.7 | I92: 113.5 | J92: 133.3 | K92: 140.8 | L92: 133.8 | M92: 94.1 | N92: 123.4 | O92: 121 | P92: 131.7 | Q92: 127.5 | R92: 129.4 | S92: 128.8 | T92: 125.5 | U92: 128.3 | V92: NA | W92: =IF(OR(V92="NA",V92="-"),V93,V92) -> 119.9 | X92: 123 | Y92: 123 | Z92: 120.8 | AA92: 114.1 | AB92: 118 | AC92: 122.9 | AD92: 112.7 | AE92: 118.1 | AF92: 124.7 | AG92: =SUM($E92:$Q92) -> 1625.3 | AH92: =SUM($S92:$U92) -> 382.6 | AI92: =SUM(W92,Y92,AC92) -> 365.8 | AJ92: =SUM(Z92,AD92) -> 233.5 | AK92: =SUM(X92,AA92) -> 237.1 | AL92: =SUM(AE92,R92,AB92) -> 365.5
A93: Urban | B93: 2015 | C93: July | D93: =B93&" "&C93 -> 2015 July | E93: 123.2 | F93: 134.3 | G93: 119.5 | H93: 127.7 | I93: 106.3 | J93: 132.8 | K93: 153.5 | L93: 149.5 | M93: 85.7 | N93: 131.5 | O93: 118.3 | P93: 131.1 | Q93: 129.5 | R93: 133.1 | S93: 123.5 | T93: 117.9 | U93: 122.7 | V93: 119.9 | W93: =IF(OR(V93="NA",V93="-"),V94,V93) -> 119.9 | X93: 115.3 | Y93: 119.5 | Z93: 116 | AA93: 111.5 | AB93: 116.6 | AC93: 125.4 | AD93: 111.7 | AE93: 116.3 | AF93: 122.4 | AG93: =SUM($E93:$Q93) -> 1642.9 | AH93: =SUM($S93:$U93) -> 364.1 | AI93: =SUM(W93,Y93,AC93) -> 364.8 | AJ93: =SUM(Z93,AD93) -> 227.7 | AK93: =SUM(X93,AA93) -> 226.8 | AL93: =SUM(AE93,R93,AB93) -> 366
A94: Rural+Urban | B94: 2015 | C94: July | D94: =B94&" "&C94 -> 2015 July | E94: 123.7 | F94: 132.5 | G94: 121 | H94: 128.3 | I94: 110.9 | J94: 133.1 | K94: 145.1 | L94: 139.1 | M94: 91.3 | N94: 126.1 | O94: 119.9 | P94: 131.4 | Q94: 128.2 | R94: 130.4 | S94: 126.7 | T94: 122.3 | U94: 126.1 | V94: 119.9 | W94: =IF(OR(V94="NA",V94="-"),V95,V94) -> 119.9 | X94: 120.1 | Y94: 121.3 | Z94: 119 | AA94: 112.7 | AB94: 117.2 | AC94: 124.4 | AD94: 112.3 | AE94: 117.2 | AF94: 123.6 | AG94: =SUM($E94:$Q94) -> 1630.6 | AH94: =SUM($S94:$U94) -> 375.1 | AI94: =SUM(W94,Y94,AC94) -> 365.6 | AJ94: =SUM(Z94,AD94) -> 231.3 | AK94: =SUM(X94,AA94) -> 232.8 | AL94: =SUM(AE94,R94,AB94) -> 364.8
A95: Rural | B95: 2015 | C95: August | D95: =B95&" "&C95 -> 2015 August | E95: 124.7 | F95: 131.3 | G95: 121.3 | H95: 128.8 | I95: 114 | J95: 134.2 | K95: 153.6 | L95: 137.9 | M95: 93.1 | N95: 123.9 | O95: 121.5 | P95: 132.5 | Q95: 129.8 | R95: 130.1 | S95: 129.5 | T95: 126.3 | U95: 129 | V95: NA | W95: =IF(OR(V95="NA",V95="-"),V96,V95) -> 120.9 | X95: 123.8 | Y95: 123.7 | Z95: 121.1 | AA95: 113.6 | AB95: 118.5 | AC95: 123.6 | AD95: 112.5 | AE95: 118.2 | AF95: 126.1 | AG95: =SUM($E95:$Q95) -> 1646.6 | AH95: =SUM($S95:$U95) -> 384.8 | AI95: =SUM(W95,Y95,AC95) -> 368.2 | AJ95: =SUM(Z95,AD95) -> 233.6 | AK95: =SUM(X95,AA95) -> 237.4 | AL95: =SUM(AE95,R95,AB95) -> 366.8
A96: Urban | B96: 2015 | C96: August | D96: =B96&" "&C96 -> 2015 August | E96: 123.1 | F96: 131.7 | G96: 118.1 | H96: 128 | I96: 106.8 | J96: 130.1 | K96: 165.5 | L96: 156 | M96: 85.3 | N96: 132.7 | O96: 118.8 | P96: 131.7 | Q96: 131.1 | R96: 134.2 | S96: 123.7 | T96: 118.2 | U96: 122.9 | V96: 120.9 | W96: =IF(OR(V96="NA",V96="-"),V97,V96) -> 120.9 | X96: 115.3 | Y96: 120 | Z96: 116.6 | AA96: 109.9 | AB96: 117.2 | AC96: 126.2 | AD96: 112 | AE96: 116.2 | AF96: 123.2 | AG96: =SUM($E96:$Q96) -> 1658.9 | AH96: =SUM($S96:$U96) -> 364.8 | AI96: =SUM(W96,Y96,AC96) -> 367.1 | AJ96: =SUM(Z96,AD96) -> 228.6 | AK96: =SUM(X96,AA96) -> 225.2 | AL96: =SUM(AE96,R96,AB96) -> 367.6
A97: Rural+Urban | B97: 2015 | C97: August | D97: =B97&" "&C97 -> 2015 August | E97: 124.2 | F97: 131.4 | G97: 120.1 | H97: 128.5 | I97: 111.4 | J97: 132.3 | K97: 157.6 | L97: 144 | M97: 90.5 | N97: 126.8 | O97: 120.4 | P97: 132.1 | Q97: 130.3 | R97: 131.2 | S97: 127.2 | T97: 122.9 | U97: 126.6 | V97: 120.9 | W97: =IF(OR(V97="NA",V97="-"),V98,V97) -> 120.9 | X97: 120.6 | Y97: 122 | Z97: 119.4 | AA97: 111.7 | AB97: 117.8 | AC97: 125.1 | AD97: 112.3 | AE97: 117.2 | AF97: 124.8 | AG97: =SUM($E97:$Q97) -> 1649.6 | AH97: =SUM($S97:$U97) -> 376.7 | AI97: =SUM(W97,Y97,AC97) -> 368 | AJ97: =SUM(Z97,AD97) -> 231.7 | AK97: =SUM(X97,AA97) -> 232.3 | AL97: =SUM(AE97,R97,AB97) -> 366.2
A98: Rural | B98: 2015 | C98: September | D98: =B98&" "&C98 -> 2015 September | E98: 125.1 | F98: 131.1 | G98: 120.7 | H98: 129.2 | I98: 114.7 | J98: 132.3 | K98: 158.9 | L98: 142.1 | M98: 92.5 | N98: 125.4 | O98: 121.9 | P98: 132.7 | Q98: 131 | R98: 131 | S98: 130.4 | T98: 126.8 | U98: 129.9 | V98: NA | W98: =IF(OR(V98="NA",V98="-"),V99,V98) -> 121.6 | X98: 123.7 | Y98: 124.5 | Z98: 121.4 | AA98: 113.8 | AB98: 119.6 | AC98: 124.5 | AD98: 113.7 | AE98: 118.8 | AF98: 127 | AG98: =SUM($E98:$Q98) -> 1657.6 | AH98: =SUM($S98:$U98) -> 387.1 | AI98: =SUM(W98,Y98,AC98) -> 370.6 | AJ98: =SUM(Z98,AD98) -> 235.1 | AK98: =SUM(X98,AA98) -> 237.5 | AL98: =SUM(AE98,R98,AB98) -> 369.4
A99: Urban | B99: 2015 | C99: September | D99: =B99&" "&C99 -> 2015 September | E99: 123.4 | F99: 129 | G99: 115.6 | H99: 128.3 | I99: 107 | J99: 124 | K99: 168.5 | L99: 165.4 | M99: 86.3 | N99: 134.4 | O99: 119.1 | P99: 132.3 | Q99: 131.5 | R99: 134.7 | S99: 124 | T99: 118.6 | U99: 123.2 | V99: 121.6 | W99: =IF(OR(V99="NA",V99="-"),V100,V99) -> 121.6 | X99: 115.1 | Y99: 120.4 | Z99: 117.1 | AA99: 109.1 | AB99: 117.3 | AC99: 126.5 | AD99: 112.9 | AE99: 116.2 | AF99: 123.5 | AG99: =SUM($E99:$Q99) -> 1664.8 | AH99: =SUM($S99:$U99) -> 365.8 | AI99: =SUM(W99,Y99,AC99) -> 368.5 | AJ99: =SUM(Z99,AD99) -> 230 | AK99: =SUM(X99,AA99) -> 224.2 | AL99: =SUM(AE99,R99,AB99) -> 368.2
A100: Rural+Urban | B100: 2015 | C100: September | D100: =B100&" "&C100 -> 2015 September | E100: 124.6 | F100: 130.4 | G100: 118.7 | H100: 128.9 | I100: 111.9 | J100: 128.4 | K100: 162.2 | L100: 150 | M100: 90.4 | N100: 128.4 | O100: 120.7 | P100: 132.5 | Q100: 131.2 | R100: 132 | S100: 127.9 | T100: 123.4 | U100: 127.2 | V100: 121.6 | W100: =IF(OR(V100="NA",V100="-"),V101,V100) -> 121.6 | X100: 120.4 | Y100: 122.6 | Z100: 119.8 | AA100: 111.3 | AB100: 118.3 | AC100: 125.7 | AD100: 113.4 | AE100: 117.5 | AF100: 125.4 | AG100: =SUM($E100:$Q100) -> 1658.3 | AH100: =SUM($S100:$U100) -> 378.5 | AI100: =SUM(W100,Y100,AC100) -> 369.9 | AJ100: =SUM(Z100,AD100) -> 233.2 | AK100: =SUM(X100,AA100) -> 231.7 | AL100: =SUM(AE100,R100,AB100) -> 367.8
...

Sheet 1.Broader Category Contribution
A1: BROADER CATEGORY CONTRIBUTION ANALYSIS
A3: SECTOR | B3: YEAR | C3: MONTH | D3: FOOD | E3: CLOTHING | F3: ESSENTIAL | G3: HEALTH | H3: ENERGY | I3: LUXURY
A4: Rural | B4: 2023 | C4: May | D4: {=INDEX('Updated DATA SET'!AG:AG,MATCH(1,('Updated DATA SET'!$A:$A=$A4) *('Updated DATA SET'!$B:$B=$B4) *('Updated DATA SET'!$C:$C=$C4),0))} -> 2290.7 | E4: {=INDEX('Updated DATA SET'!AH:AH,MATCH(1,('Updated DATA SET'!$A:$A=$A4) *('Updated DATA SET'!$B:$B=$B4) *('Updated DATA SET'!$C:$C=$C4),0))} -> 569.9 | F4: {=INDEX('Updated DATA SET'!AI:AI,MATCH(1,('Updated DATA SET'!$A:$A=$A4) *('Updated DATA SET'!$B:$B=$B4) *('Updated DATA SET'!$C:$C=$C4),0))} -> 535.7 | G4: {=INDEX('Updated DATA SET'!AJ:AJ,MATCH(1,('Updated DATA SET'!$A:$A=$A4) *('Updated DATA SET'!$B:$B=$B4) *('Updated DATA SET'!$C:$C=$C4),0))} -> 372.7 | H4: {=INDEX('Updated DATA SET'!AK:AK,MATCH(1,('Updated DATA SET'!$A:$A=$A4) *('Updated DATA SET'!$B:$B=$B4) *('Updated DATA SET'!$C:$C=$C4),0))} -> 352.2 | I4: {=INDEX('Updated DATA SET'!AL:AL,MATCH(1,('Updated DATA SET'!$A:$A=$A4) *('Updated DATA SET'!$B:$B=$B4) *('Updated DATA SET'!$C:$C=$C4),0))} -> 553.2
A5: Rural+Urban | B5: 2023 | C5: May | D5: {=INDEX('Updated DATA SET'!AG:AG,MATCH(1,('Updated DATA SET'!$A:$A=$A5) *('Updated DATA SET'!$B:$B=$B5) *('Updated DATA SET'!$C:$C=$C5),0))} -> 2306.9 | E5: {=INDEX('Updated DATA SET'!AH:AH,MATCH(1,('Updated DATA SET'!$A:$A=$A5) *('Updated DATA SET'!$B:$B=$B5) *('Updated DATA SET'!$C:$C=$C5),0))} -> 553.2 | F5: {=INDEX('Updated DATA SET'!AI:AI,MATCH(1,('Updated DATA SET'!$A:$A=$A5) *('Updated DATA SET'!$B:$B=$B5) *('Updated DATA SET'!$C:$C=$C5),0))} -> 527.9 | G5: {=INDEX('Updated DATA SET'!AJ:AJ,MATCH(1,('Updated DATA SET'!$A:$A=$A5) *('Updated DATA SET'!$B:$B=$B5) *('Updated DATA SET'!$C:$C=$C5),0))} -> 370.9 | H5: {=INDEX('Updated DATA SET'!AK:AK,MATCH(1,('Updated DATA SET'!$A:$A=$A5) *('Updated DATA SET'!$B:$B=$B5) *('Updated DATA SET'!$C:$C=$C5),0))} -> 347.6 | I5: {=INDEX('Updated DATA SET'!AL:AL,MATCH(1,('Updated DATA SET'!$A:$A=$A5) *('Updated DATA SET'!$B:$B=$B5) *('Updated DATA SET'!$C:$C=$C5),0))} -> 547.9
A6: Urban | B6: 2023 | C6: May | D6: {=INDEX('Updated DATA SET'!AG:AG,MATCH(1,('Updated DATA SET'!$A:$A=$A6) *('Updated DATA SET'!$B:$B=$B6) *('Updated DATA SET'!$C:$C=$C6),0))} -> 2335.1 | E6: {=INDEX('Updated DATA SET'!AH:AH,MATCH(1,('Updated DATA SET'!$A:$A=$A6) *('Updated DATA SET'!$B:$B=$B6) *('Updated DATA SET'!$C:$C=$C6),0))} -> 528.7 | F6: {=INDEX('Updated DATA SET'!AI:AI,MATCH(1,('Updated DATA SET'!$A:$A=$A6) *('Updated DATA SET'!$B:$B=$B6) *('Updated DATA SET'!$C:$C=$C6),0))} -> 520.5 | G6: {=INDEX('Updated DATA SET'!AJ:AJ,MATCH(1,('Updated DATA SET'!$A:$A=$A6) *('Updated DATA SET'!$B:$B=$B6) *('Updated DATA SET'!$C:$C=$C6),0))} -> 367.8 | H6: {=INDEX('Updated DATA SET'!AK:AK,MATCH(1,('Updated DATA SET'!$A:$A=$A6) *('Updated DATA SET'!$B:$B=$B6) *('Updated DATA SET'!$C:$C=$C6),0))} -> 343.8 | I6: {=INDEX('Updated DATA SET'!AL:AL,MATCH(1,('Updated DATA SET'!$A:$A=$A6) *('Updated DATA SET'!$B:$B=$B6) *('Updated DATA SET'!$C:$C=$C6),0))} -> 545
A7: Grand Total | D7: =SUM(D4:D6) -> 6932.7 | E7: =SUM(E4:E6) -> 1651.8 | F7: =SUM(F4:F6) -> 1584.1 | G7: =SUM(G4:G6) -> 1111.4 | H7: =SUM(H4:H6) -> 1043.6 | I7: =SUM(I4:I6) -> 1646.1
A8: Contribution Rate | D8: =D7/SUM($D$7:$I$7) -> 0.49626692 | E8: =E7/SUM($D$7:$I$7) -> 0.11824162 | F8: =F7/SUM($D$7:$I$7) -> 0.11339542 | G8: =G7/SUM($D$7:$I$7) -> 0.0795579 | H8: =H7/SUM($D$7:$I$7) -> 0.074704539 | I8: =I7/SUM($D$7:$I$7) -> 0.1178336
A9: Rural | B9: 2023 | C9: May
A10: Contribution of categories for sector
A11: CATEGORIES | B11: CPI VALUES | C11: CONTRIBUTION RATE
A12: Food | B12: {=INDEX('Updated DATA SET'!$AG:$AG,MATCH(1,('Updated DATA SET'!$A:$A=$A$9) *('Updated DATA SET'!$B:$B=$B$9) *('Updated DATA SET'!$C:$C=$C$9),0))} -> 2290.7 | C12: =B12/SUM($B$12:$B$17) -> 0.4900522
A13: Clothing | B13: {=INDEX('Updated DATA SET'!$AH:$AH,MATCH(1,('Updated DATA SET'!$A:$A=$A$9) *('Updated DATA SET'!$B:$B=$B$9) *('Updated DATA SET'!$C:$C=$C$9),0))} -> 569.9 | C13: =B13/SUM($B$12:$B$17) -> 0.12191939
A14: Essential | B14: {=INDEX('Updated DATA SET'!$AI:$AI,MATCH(1,('Updated DATA SET'!$A:$A=$A$9) *('Updated DATA SET'!$B:$B=$B$9) *('Updated DATA SET'!$C:$C=$C$9),0))} -> 535.7 | C14: =B14/SUM($B$12:$B$17) -> 0.11460294
A15: health | B15: {=INDEX('Updated DATA SET'!$AJ:$AJ,MATCH(1,('Updated DATA SET'!$A:$A=$A$9) *('Updated DATA SET'!$B:$B=$B$9) *('Updated DATA SET'!$C:$C=$C$9),0))} -> 372.7 | C15: =B15/SUM($B$12:$B$17) -> 0.079732158
A16: Energy | B16: {=INDEX('Updated DATA SET'!$AK:$AK,MATCH(1,('Updated DATA SET'!$A:$A=$A$9) *('Updated DATA SET'!$B:$B=$B$9) *('Updated DATA SET'!$C:$C=$C$9),0))} -> 352.2 | C16: =B16/SUM($B$12:$B$17) -> 0.075346569
A17: Luxury | B17: {=INDEX('Updated DATA SET'!$AL:$AL,MATCH(1,('Updated DATA SET'!$A:$A=$A$9) *('Updated DATA SET'!$B:$B=$B$9) *('Updated DATA SET'!$C:$C=$C$9),0))} -> 553.2 | C17: =B17/SUM($B$12:$B$17) -> 0.11834674
A18: SUM | B18: =SUM(B12:B17) -> 4674.4 | C18: =SUM(C12:C17) -> 1
A19: YEAR = | B19: =B9 -> 2023 | C19: MONTH = | D19: =C9 -> May | E19: SECTOR = | F19: =A9 -> Rural
A41: CATEGORIES | B41: CONTRIBUTION RATE FOR RURAL | C41: CONTRIBUTION RATE FOR RURAL+URBAN | D41: CONTRIBUTION RATE FOR URBAN
A42: FOOD | B42: =D4/SUM($D$4:$I$4) -> 0.4900522 | C42: =D5/SUM($D$5:$I$5) -> 0.49563854 | D42: =D6/SUM($D$6:$I$6) -> 0.50315672
A43: CLOTHING | B43: =E4/SUM($D$4:$I$4) -> 0.12191939 | C43: =E5/SUM($D$5:$I$5) -> 0.11885528 | D43: =E6/SUM($D$6:$I$6) -> 0.11392187
A44: ESSENTIAL | B44: =F4/SUM($D$4:$I$4) -> 0.11460294 | C44: =F5/SUM($D$5:$I$5) -> 0.11341956 | D44: =F6/SUM($D$6:$I$6) -> 0.11215497
A45: HEALTH | B45: =G4/SUM($D$4:$I$4) -> 0.079732158 | C45: =G5/SUM($D$5:$I$5) -> 0.079688037 | D45: =G6/SUM($D$6:$I$6) -> 0.079251869
A46: ENERGY | B46: =H4/SUM($D$4:$I$4) -> 0.075346569 | C46: =H5/SUM($D$5:$I$5) -> 0.074682021 | D46: =H6/SUM($D$6:$I$6) -> 0.074080459
A47: LUXURY | B47: =I4/SUM($D$4:$I$4) -> 0.11834674 | C47: =I5/SUM($D$5:$I$5) -> 0.11771657 | D47: =I6/SUM($D$6:$I$6) -> 0.11743412
A56: Sl. No. | B56: Key Observation | E56: Possible Reason
A57: 1 | B57: Food has the highest contribution (~50%) across Rural, Urban and Combined sectors. | E57: Food category has the highest CPI values (2290.7 Rural, 2292.7 Combined, 2335.1 Urban), significantly larger than all other categories.
A58: 2 | B58: Clothing maintains a stable contribution around 12% in all sectors. | E58: Clothing CPI values (Rural = 569.9, Combined = 553.2, Urban = 528.7) stay close to each other, showing uniform pricing and limited volatility.
A59: 3 | B59: Combined (Rural+Urban) contribution percentages closely follow Rural distribution. | E59: Combined CPI values are mostly near Rural values, showing similar expenditure pattern between both segments.

Sheet 2. YOY increase in CPI 
A1: YEAR OVER YEAR INCREASE ON OVERALL CPI INDEX
A3: Urban
A4: YEAR | B4: January | C4: December | D4: YOY INFLATION %
A5: 2012 | B5: =AVERAGEIFS('Updated DATA SET'!AF:AF,'Updated DATA SET'!$B:$B,'2. YOY increase in CPI '!$A5,'Updated DATA SET'!$C:$C,'2. YOY increase in CPI '!$B$4,'Updated DATA SET'!$A:$A,'2. YOY increase in CPI '!$A$3) -> #DIV/0! | C5: =AVERAGEIFS('Updated DATA SET'!AF:AF,'Updated DATA SET'!$B:$B,'2. YOY increase in CPI '!$A5,'Updated DATA SET'!$C:$C,'2. YOY increase in CPI '!$C$4,'Updated DATA SET'!$A:$A,'2. YOY increase in CPI '!$A$3) -> #DIV/0! | D5: =IFERROR((C5-B5)/B5,0) -> 0
A6: 2013 | B6: =AVERAGEIFS('Updated DATA SET'!AF:AF,'Updated DATA SET'!$B:$B,'2. YOY increase in CPI '!$A6,'Updated DATA SET'!$C:$C,'2. YOY increase in CPI '!$B$4,'Updated DATA SET'!$A:$A,'2. YOY increase in CPI '!$A$3) -> 104 | C6: =AVERAGEIFS('Updated DATA SET'!AF:AF,'Updated DATA SET'!$B:$B,'2. YOY increase in CPI '!$A6,'Updated DATA SET'!$C:$C,'2. YOY increase in CPI '!$C$4,'Updated DATA SET'!$A:$A,'2. YOY increase in CPI '!$A$3) -> 113.3 | D6: =IFERROR((C6-B6)/B6,0) -> 0.089423077
A7: 2014 | B7: =AVERAGEIFS('Updated DATA SET'!AF:AF,'Updated DATA SET'!$B:$B,'2. YOY increase in CPI '!$A7,'Updated DATA SET'!$C:$C,'2. YOY increase in CPI '!$B$4,'Updated DATA SET'!$A:$A,'2. YOY increase in CPI '!$A$3) -> 112.9 | C7: =AVERAGEIFS('Updated DATA SET'!AF:AF,'Updated DATA SET'!$B:$B,'2. YOY increase in CPI '!$A7,'Updated DATA SET'!$C:$C,'2. YOY increase in CPI '!$C$4,'Updated DATA SET'!$A:$A,'2. YOY increase in CPI '!$A$3) -> 118.4 | D7: =IFERROR((C7-B7)/B7,0) -> 0.048715678
A8: 2015 | B8: =AVERAGEIFS('Updated DATA SET'!AF:AF,'Updated DATA SET'!$B:$B,'2. YOY increase in CPI '!$A8,'Updated DATA SET'!$C:$C,'2. YOY increase in CPI '!$B$4,'Updated DATA SET'!$A:$A,'2. YOY increase in CPI '!$A$3) -> 118.5 | C8: =AVERAGEIFS('Updated DATA SET'!AF:AF,'Updated DATA SET'!$B:$B,'2. YOY increase in CPI '!$A8,'Updated DATA SET'!$C:$C,'2. YOY increase in CPI '!$C$4,'Updated DATA SET'!$A:$A,'2. YOY increase in CPI '!$A$3) -> 124 | D8: =IFERROR((C8-B8)/B8,0) -> 0.046413502
A9: 2016 | B9: =AVERAGEIFS('Updated DATA SET'!AF:AF,'Updated DATA SET'!$B:$B,'2. YOY increase in CPI '!$A9,'Updated DATA SET'!$C:$C,'2. YOY increase in CPI '!$B$4,'Updated DATA SET'!$A:$A,'2. YOY increase in CPI '!$A$3) -> 124.2 | C9: =AVERAGEIFS('Updated DATA SET'!AF:AF,'Updated DATA SET'!$B:$B,'2. YOY increase in CPI '!$A9,'Updated DATA SET'!$C:$C,'2. YOY increase in CPI '!$C$4,'Updated DATA SET'!$A:$A,'2. YOY increase in CPI '!$A$3) -> 127.6 | D9: =IFERROR((C9-B9)/B9,0) -> 0.027375201
A10: 2017 | B10: =AVERAGEIFS('Updated DATA SET'!AF:AF,'Updated DATA SET'!$B:$B,'2. YOY increase in CPI '!$A10,'Updated DATA SET'!$C:$C,'2. YOY increase in CPI '!$B$4,'Updated DATA SET'!$A:$A,'2. YOY increase in CPI '!$A$3) -> 127.8 | C10: =AVERAGEIFS('Updated DATA SET'!AF:AF,'Updated DATA SET'!$B:$B,'2. YOY increase in CPI '!$A10,'Updated DATA SET'!$C:$C,'2. YOY increase in CPI '!$C$4,'Updated DATA SET'!$A:$A,'2. YOY increase in CPI '!$A$3) -> 134.1 | D10: =IFERROR((C10-B10)/B10,0) -> 0.049295775
A11: 2018 | B11: =AVERAGEIFS('Updated DATA SET'!AF:AF,'Updated DATA SET'!$B:$B,'2. YOY increase in CPI '!$A11,'Updated DATA SET'!$C:$C,'2. YOY increase in CPI '!$B$4,'Updated DATA SET'!$A:$A,'2. YOY increase in CPI '!$A$3) -> 134.1 | C11: =AVERAGEIFS('Updated DATA SET'!AF:AF,'Updated DATA SET'!$B:$B,'2. YOY increase in CPI '!$A11,'Updated DATA SET'!$C:$C,'2. YOY increase in CPI '!$C$4,'Updated DATA SET'!$A:$A,'2. YOY increase in CPI '!$A$3) -> 138 | D11: =IFERROR((C11-B11)/B11,0) -> 0.029082774
A12: 2019 | B12: =AVERAGEIFS('Updated DATA SET'!AF:AF,'Updated DATA SET'!$B:$B,'2. YOY increase in CPI '!$A12,'Updated DATA SET'!$C:$C,'2. YOY increase in CPI '!$B$4,'Updated DATA SET'!$A:$A,'2. YOY increase in CPI '!$A$3) -> 138 | C12: =AVERAGEIFS('Updated DATA SET'!AF:AF,'Updated DATA SET'!$B:$B,'2. YOY increase in CPI '!$A12,'Updated DATA SET'!$C:$C,'2. YOY increase in CPI '!$C$4,'Updated DATA SET'!$A:$A,'2. YOY increase in CPI '!$A$3) -> 148.3 | D12: =IFERROR((C12-B12)/B12,0) -> 0.074637681
A13: 2020 | B13: =AVERAGEIFS('Updated DATA SET'!AF:AF,'Updated DATA SET'!$B:$B,'2. YOY increase in CPI '!$A13,'Updated DATA SET'!$C:$C,'2. YOY increase in CPI '!$B$4,'Updated DATA SET'!$A:$A,'2. YOY increase in CPI '!$A$3) -> 148.2 | C13: =AVERAGEIFS('Updated DATA SET'!AF:AF,'Updated DATA SET'!$B:$B,'2. YOY increase in CPI '!$A13,'Updated DATA SET'!$C:$C,'2. YOY increase in CPI '!$C$4,'Updated DATA SET'!$A:$A,'2. YOY increase in CPI '!$A$3) -> 156.9 | D13: =IFERROR((C13-B13)/B13,0) -> 0.058704453
A14: 2021 | B14: =AVERAGEIFS('Updated DATA SET'!AF:AF,'Updated DATA SET'!$B:$B,'2. YOY increase in CPI '!$A14,'Updated DATA SET'!$C:$C,'2. YOY increase in CPI '!$B$4,'Updated DATA SET'!$A:$A,'2. YOY increase in CPI '!$A$3) -> 156 | C14: =AVERAGEIFS('Updated DATA SET'!AF:AF,'Updated DATA SET'!$B:$B,'2. YOY increase in CPI '!$A14,'Updated DATA SET'!$C:$C,'2. YOY increase in CPI '!$C$4,'Updated DATA SET'!$A:$A,'2. YOY increase in CPI '!$A$3) -> 165.2 | D14: =IFERROR((C14-B14)/B14,0) -> 0.058974359
A15: 2022 | B15: =AVERAGEIFS('Updated DATA SET'!AF:AF,'Updated DATA SET'!$B:$B,'2. YOY increase in CPI '!$A15,'Updated DATA SET'!$C:$C,'2. YOY increase in CPI '!$B$4,'Updated DATA SET'!$A:$A,'2. YOY increase in CPI '!$A$3) -> 165 | C15: =AVERAGEIFS('Updated DATA SET'!AF:AF,'Updated DATA SET'!$B:$B,'2. YOY increase in CPI '!$A15,'Updated DATA SET'!$C:$C,'2. YOY increase in CPI '!$C$4,'Updated DATA SET'!$A:$A,'2. YOY increase in CPI '!$A$3) -> 174.1 | D15: =IFERROR((C15-B15)/B15,0) -> 0.055151515
A16: 2023 | B16: =AVERAGEIFS('Updated DATA SET'!AF:AF,'Updated DATA SET'!$B:$B,'2. YOY increase in CPI '!$A16,'Updated DATA SET'!$C:$C,'2. YOY increase in CPI '!$B$4,'Updated DATA SET'!$A:$A,'2. YOY increase in CPI '!$A$3) -> 174.9 | C16: =AVERAGEIFS('Updated DATA SET'!AF:AF,'Updated DATA SET'!$B:$B,'2. YOY increase in CPI '!$A16,'Updated DATA SET'!$C:$C,'2. YOY increase in CPI '!$C$4,'Updated DATA SET'!$A:$A,'2. YOY increase in CPI '!$A$3) -> #DIV/0! | D16: =IFERROR((C16-B16)/B16,0) -> 0
A20: YEAR | B20: MONTH | C20: FOOD | D20: CLOTHING | E20: ESSENTIAL | F20: HEALTH | G20: ENERGY | H20: LUXURY
A21: 2019 | B21: January | C21: =AVERAGEIFS('Updated DATA SET'!AG:AG,'Updated DATA SET'!$B:$B,'2. YOY increase in CPI '!$A21,'Updated DATA SET'!$C:$C,'2. YOY increase in CPI '!$B21) -> 1752.4333 | D21: =AVERAGEIFS('Updated DATA SET'!AH:AH,'Updated DATA SET'!$B:$B,'2. YOY increase in CPI '!$A21,'Updated DATA SET'!$C:$C,'2. YOY increase in CPI '!$B21) -> 431.03333 | E21: =AVERAGEIFS('Updated DATA SET'!AI:AI,'Updated DATA SET'!$B:$B,'2. YOY increase in CPI '!$A21,'Updated DATA SET'!$C:$C,'2. YOY increase in CPI '!$B21) -> 441.7 | F21: =AVERAGEIFS('Updated DATA SET'!AJ:AJ,'Updated DATA SET'!$B:$B,'2. YOY increase in CPI '!$A21,'Updated DATA SET'!$C:$C,'2. YOY increase in CPI '!$B21) -> 276.83333 | G21: =AVERAGEIFS('Updated DATA SET'!AK:AK,'Updated DATA SET'!$B:$B,'2. YOY increase in CPI '!$A21,'Updated DATA SET'!$C:$C,'2. YOY increase in CPI '!$B21) -> 261.6 | H21: =AVERAGEIFS('Updated DATA SET'!AL:AL,'Updated DATA SET'!$B:$B,'2. YOY increase in CPI '!$A21,'Updated DATA SET'!$C:$C,'2. YOY increase in CPI '!$B21) -> 437.5
A22: 2019 | B22: December | C22: =AVERAGEIFS('Updated DATA SET'!AG:AG,'Updated DATA SET'!$B:$B,'2. YOY increase in CPI '!$A22,'Updated DATA SET'!$C:$C,'2. YOY increase in CPI '!$B22) -> 1947.9333 | D22: =AVERAGEIFS('Updated DATA SET'!AH:AH,'Updated DATA SET'!$B:$B,'2. YOY increase in CPI '!$A22,'Updated DATA SET'!$C:$C,'2. YOY increase in CPI '!$B22) -> 438.86667 | E22: =AVERAGEIFS('Updated DATA SET'!AI:AI,'Updated DATA SET'!$B:$B,'2. YOY increase in CPI '!$A22,'Updated DATA SET'!$C:$C,'2. YOY increase in CPI '!$B22) -> 454.63333 | F22: =AVERAGEIFS('Updated DATA SET'!AJ:AJ,'Updated DATA SET'!$B:$B,'2. YOY increase in CPI '!$A22,'Updated DATA SET'!$C:$C,'2. YOY increase in CPI '!$B22) -> 289.86667 | G22: =AVERAGEIFS('Updated DATA SET'!AK:AK,'Updated DATA SET'!$B:$B,'2. YOY increase in CPI '!$A22,'Updated DATA SET'!$C:$C,'2. YOY increase in CPI '!$B22) -> 272.4 | H22: =AVERAGEIFS('Updated DATA SET'!AL:AL,'Updated DATA SET'!$B:$B,'2. YOY increase in CPI '!$A22,'Updated DATA SET'!$C:$C,'2. YOY increase in CPI '!$B22) -> 454.2
A23: Inflation | C23: =(C22-C21)/C21 -> 0.11155917 | D23: =(D22-D21)/D21 -> 0.018173382 | E23: =(E22-E21)/E21 -> 0.029280809 | F23: =(F22-F21)/F21 -> 0.047080072 | G23: =(G22-G21)/G21 -> 0.041284404 | H23: =(H22-H21)/H21 -> 0.038171429
A26: Sl. No. | B26: Key Insight | E26: Reasons
A27: 1 | B27: YOY inflation peaked in 2019 at 7.46%, the highest across the displayed years. | E27: Significant rise from Jan to Dec index values indicating stronger price increase during that year.
A28: 2 | B28: YOY Inflation shows a declining trend after 2020, stabilizing at ~5.5% by 2023. | E28: Price movements after 2020 appear more controlled, as seen from smaller YOY % changes in the following years.
A29: 3 | B29: Food recorded the highest category inflation in 2019, showing strong price pressure. | E29: Strong rise in Food index from Jan (1752.43) to Dec (1947.93) explains high annual inflation.

Sheet 3. MOM inflation in food catego
A1: MONTH OVER MONTH INLFATION OVER FOOD CATEGORIES
A3: TIME FRAME | B3: =UPPER("Average of Food and beverages") -> AVERAGE OF FOOD AND BEVERAGES | C3: =UPPER("Inflation/Deflation Rate") -> INFLATION/DEFLATION RATE
A4: 2022 May | B4: =AVERAGEIF('Updated DATA SET'!$D:$D,'3. MOM inflation in food catego'!A4,'Updated DATA SET'!$Q:$Q) -> 173.86667
A5: 2022 June | B5: =AVERAGEIF('Updated DATA SET'!$D:$D,'3. MOM inflation in food catego'!A5,'Updated DATA SET'!$Q:$Q) -> 175.53333 | C5: =(B5-B4)/B4 -> 0.0095858896
A6: 2022 July | B6: =AVERAGEIF('Updated DATA SET'!$D:$D,'3. MOM inflation in food catego'!A6,'Updated DATA SET'!$Q:$Q) -> 175.63333 | C6: =(B6-B5)/B5 -> 0.00056969237
A7: 2022 August | B7: =AVERAGEIF('Updated DATA SET'!$D:$D,'3. MOM inflation in food catego'!A7,'Updated DATA SET'!$Q:$Q) -> 176.86667 | C7: =(B7-B6)/B6 -> 0.0070222054
A8: 2022 September | B8: =AVERAGEIF('Updated DATA SET'!$D:$D,'3. MOM inflation in food catego'!A8,'Updated DATA SET'!$Q:$Q) -> 178.36667 | C8: =(B8-B7)/B7 -> 0.0084809649
A9: 2022 October | B9: =AVERAGEIF('Updated DATA SET'!$D:$D,'3. MOM inflation in food catego'!A9,'Updated DATA SET'!$Q:$Q) -> 180.1 | C9: =(B9-B8)/B8 -> 0.0097178098
A10: 2022 November | B10: =AVERAGEIF('Updated DATA SET'!$D:$D,'3. MOM inflation in food catego'!A10,'Updated DATA SET'!$Q:$Q) -> 178.73333 | C10: =(B10-B9)/B9 -> -0.0075883768
A11: 2022 December | B11: =AVERAGEIF('Updated DATA SET'!$D:$D,'3. MOM inflation in food catego'!A11,'Updated DATA SET'!$Q:$Q) -> 176.3 | C11: =(B11-B10)/B10 -> -0.013614323
A12: 2023 January | B12: =AVERAGEIF('Updated DATA SET'!$D:$D,'3. MOM inflation in food catego'!A12,'Updated DATA SET'!$Q:$Q) -> 177.06667 | C12: =(B12-B11)/B11 -> 0.0043486481
A13: 2023 February | B13: =AVERAGEIF('Updated DATA SET'!$D:$D,'3. MOM inflation in food catego'!A13,'Updated DATA SET'!$Q:$Q) -> 177.5 | C13: =(B13-B12)/B12 -> 0.0024472892
A14: 2023 March | B14: =AVERAGEIF('Updated DATA SET'!$D:$D,'3. MOM inflation in food catego'!A14,'Updated DATA SET'!$Q:$Q) -> 177.53333 | C14: =(B14-B13)/B13 -> 0.00018779343
A15: 2023 April | B15: =AVERAGEIF('Updated DATA SET'!$D:$D,'3. MOM inflation in food catego'!A15,'Updated DATA SET'!$Q:$Q) -> 178.5 | C15: =(B15-B14)/B14 -> 0.0054449869
A16: 2023 May | B16: =AVERAGEIF('Updated DATA SET'!$D:$D,'3. MOM inflation in food catego'!A16,'Updated DATA SET'!$Q:$Q) -> 179.66667 | C16: =(B16-B15)/B15 -> 0.0065359477
A18: Highest Inflation rate Month | B18: =INDEX(A5:A16,MATCH(MAX(C5:C16),C5:C16,0)) -> 2022 October
A19: Lowest Inflation rate Month | B19: =INDEX(A5:A16,MATCH(MIN(C5:C16),C5:C16,0)) -> 2022 December
A20: Time Frame | B20: Cereals and products | C20: Meat and fish | D20: Egg | E20: Milk and products | F20: Oils and fats | G20: Fruits | H20: Vegetables | I20: Pulses and products | J20: Sugar and Confectionery | K20: Spices | L20: Non-alcoholic beverages | M20: Prepared meals, snacks, sweets etc.
A21: 2022 June | B21: =AVERAGEIF('Updated DATA SET'!$D:$D,'3. MOM inflation in food catego'!$A21,'Updated DATA SET'!E:E) -> 155.43333 | C21: =AVERAGEIF('Updated DATA SET'!$D:$D,'3. MOM inflation in food catego'!$A21,'Updated DATA SET'!F:F) -> 220 | D21: =AVERAGEIF('Updated DATA SET'!$D:$D,'3. MOM inflation in food catego'!$A21,'Updated DATA SET'!G:G) -> 171.06667 | E21: =AVERAGEIF('Updated DATA SET'!$D:$D,'3. MOM inflation in food catego'!$A21,'Updated DATA SET'!H:H) -> 165.86667 | F21: =AVERAGEIF('Updated DATA SET'!$D:$D,'3. MOM inflation in food catego'!$A21,'Updated DATA SET'!I:I) -> 199.2 | G21: =AVERAGEIF('Updated DATA SET'!$D:$D,'3. MOM inflation in food catego'!$A21,'Updated DATA SET'!J:J) -> 169.86667 | H21: =AVERAGEIF('Updated DATA SET'!$D:$D,'3. MOM inflation in food catego'!$A21,'Updated DATA SET'!K:K) -> 187.03333 | I21: =AVERAGEIF('Updated DATA SET'!$D:$D,'3. MOM inflation in food catego'!$A21,'Updated DATA SET'!L:L) -> 164.16667 | J21: =AVERAGEIF('Updated DATA SET'!$D:$D,'3. MOM inflation in food catego'!$A21,'Updated DATA SET'!M:M) -> 120.13333 | K21: =AVERAGEIF('Updated DATA SET'!$D:$D,'3. MOM inflation in food catego'!$A21,'Updated DATA SET'!N:N) -> 186.5 | L21: =AVERAGEIF('Updated DATA SET'!$D:$D,'3. MOM inflation in food catego'!$A21,'Updated DATA SET'!O:O) -> 167.06667 | M21: =AVERAGEIF('Updated DATA SET'!$D:$D,'3. MOM inflation in food catego'!$A21,'Updated DATA SET'!P:P) -> 184.03333
A22: 2023 May | B22: =AVERAGEIF('Updated DATA SET'!$D:$D,'3. MOM inflation in food catego'!$A22,'Updated DATA SET'!E:E) -> 173.86667 | C22: =AVERAGEIF('Updated DATA SET'!$D:$D,'3. MOM inflation in food catego'!$A22,'Updated DATA SET'!F:F) -> 215.06667 | D22: =AVERAGEIF('Updated DATA SET'!$D:$D,'3. MOM inflation in food catego'!$A22,'Updated DATA SET'!G:G) -> 173.63333 | E22: =AVERAGEIF('Updated DATA SET'!$D:$D,'3. MOM inflation in food catego'!$A22,'Updated DATA SET'!H:H) -> 179.5 | F22: =AVERAGEIF('Updated DATA SET'!$D:$D,'3. MOM inflation in food catego'!$A22,'Updated DATA SET'!I:I) -> 169.23333 | G22: =AVERAGEIF('Updated DATA SET'!$D:$D,'3. MOM inflation in food catego'!$A22,'Updated DATA SET'!J:J) -> 172.33333 | H22: =AVERAGEIF('Updated DATA SET'!$D:$D,'3. MOM inflation in food catego'!$A22,'Updated DATA SET'!K:K) -> 164.9 | I22: =AVERAGEIF('Updated DATA SET'!$D:$D,'3. MOM inflation in food catego'!$A22,'Updated DATA SET'!L:L) -> 175.8 | J22: =AVERAGEIF('Updated DATA SET'!$D:$D,'3. MOM inflation in food catego'!$A22,'Updated DATA SET'!M:M) -> 122.93333 | K22: =AVERAGEIF('Updated DATA SET'!$D:$D,'3. MOM inflation in food catego'!$A22,'Updated DATA SET'!N:N) -> 216.96667 | L22: =AVERAGEIF('Updated DATA SET'!$D:$D,'3. MOM inflation in food catego'!$A22,'Updated DATA SET'!O:O) -> 172.66667 | M22: =AVERAGEIF('Updated DATA SET'!$D:$D,'3. MOM inflation in food catego'!$A22,'Updated DATA SET'!P:P) -> 194.33333
A24: FOOD CATEGORY | B24: 2022 JUNE | C24: 2023 MAY | D24: =UPPER("Absolute Inflation Rate") -> ABSOLUTE INFLATION RATE
A25: Spices | B25: =HLOOKUP(A25,$B$20:$M$22,2,0) -> 186.5 | C25: =HLOOKUP(A25,$B$20:$M$22,3,0) -> 216.96667 | D25: =(C25-B25)/B25 -> 0.16336014
A26: Cereals and products | B26: =HLOOKUP(A26,$B$20:$M$22,2,0) -> 155.43333 | C26: =HLOOKUP(A26,$B$20:$M$22,3,0) -> 173.86667 | D26: =(C26-B26)/B26 -> 0.11859318
A27: Milk and products | B27: =HLOOKUP(A27,$B$20:$M$22,2,0) -> 165.86667 | C27: =HLOOKUP(A27,$B$20:$M$22,3,0) -> 179.5 | D27: =(C27-B27)/B27 -> 0.082194534
A28: Pulses and products | B28: =HLOOKUP(A28,$B$20:$M$22,2,0) -> 164.16667 | C28: =HLOOKUP(A28,$B$20:$M$22,3,0) -> 175.8 | D28: =(C28-B28)/B28 -> 0.070862944
A29: Prepared meals, snacks, sweets etc. | B29: =HLOOKUP(A29,$B$20:$M$22,2,0) -> 184.03333 | C29: =HLOOKUP(A29,$B$20:$M$22,3,0) -> 194.33333 | D29: =(C29-B29)/B29 -> 0.055968122
A30: Non-alcoholic beverages | B30: =HLOOKUP(A30,$B$20:$M$22,2,0) -> 167.06667 | C30: =HLOOKUP(A30,$B$20:$M$22,3,0) -> 172.66667 | D30: =(C30-B30)/B30 -> 0.033519553
A31: Sugar and Confectionery | B31: =HLOOKUP(A31,$B$20:$M$22,2,0) -> 120.13333 | C31: =HLOOKUP(A31,$B$20:$M$22,3,0) -> 122.93333 | D31: =(C31-B31)/B31 -> 0.023307436
A32: Egg | B32: =HLOOKUP(A32,$B$20:$M$22,2,0) -> 171.06667 | C32: =HLOOKUP(A32,$B$20:$M$22,3,0) -> 173.63333 | D32: =(C32-B32)/B32 -> 0.015003897
A33: Fruits | B33: =HLOOKUP(A33,$B$20:$M$22,2,0) -> 169.86667 | C33: =HLOOKUP(A33,$B$20:$M$22,3,0) -> 172.33333 | D33: =(C33-B33)/B33 -> 0.014521193
A34: Meat and fish | B34: =HLOOKUP(A34,$B$20:$M$22,2,0) -> 220 | C34: =HLOOKUP(A34,$B$20:$M$22,3,0) -> 215.06667 | D34: =(C34-B34)/B34 -> -0.022424242
A35: Vegetables | B35: =HLOOKUP(A35,$B$20:$M$22,2,0) -> 187.03333 | C35: =HLOOKUP(A35,$B$20:$M$22,3,0) -> 164.9 | D35: =(C35-B35)/B35 -> -0.11833898
A36: Oils and fats | B36: =HLOOKUP(A36,$B$20:$M$22,2,0) -> 199.2 | C36: =HLOOKUP(A36,$B$20:$M$22,3,0) -> 169.23333 | D36: =(C36-B36)/B36 -> -0.15043507
A41: Sl. No. | B41: Observation | E41: Reason
A42: 1 | B42: Highest MOM inflation occurred in October 2022 (0.97%). | E42: Average food index rose from 178.37 (Sep 2022) to 180.10 (Oct 2022), showing the strongest monthly rise.
A43: 2 | B43: December 2022 recorded the lowest MOM inflation (-1.36%), indicating deflation. | E43: Index fell sharply from 178.70 (Nov) to 176.30 (Dec), leading to the most negative change in the period.
A44: 3 | B44: Spices show the highest absolute inflation (16.34%) between June 2022 and May 2023. | E44: Spices index increased significantly from 186.50 → 216.97, the largest positive change among categories.
A45: 4 | B45: Oils & fats experienced a major deflation (-15.04%). | E45: Index dropped from 199.20 → 169.23, showing sharp decline due to easing global edible oil prices.

Sheet 4 Pre Post Pandemic
A1: CATEGORY WISE INFLATION OVER COVID PERIODS
B3: Rural+Urban
A4: Tenure Label | B4: Year | C4: Month | D4: Food | E4: Clothing | F4: Essential | G4: Health | H4: Energy | I4: Luxury
A5: Start | B5: 2019 | C5: March | D5: {=INDEX('Updated DATA SET'!AG:AG,MATCH(1,('Updated DATA SET'!$A:$A='4 Pre Post Pandemic'!$B$3)*('Updated DATA SET'!$B:$B='4 Pre Post Pandemic'!$B5)*('Updated DATA SET'!$C:$C='4 Pre Post Pandemic'!$C5),0))} -> 1762.9 | E5: {=INDEX('Updated DATA SET'!AH:AH,MATCH(1,('Updated DATA SET'!$A:$A='4 Pre Post Pandemic'!$B$3)*('Updated DATA SET'!$B:$B='4 Pre Post Pandemic'!$B5)*('Updated DATA SET'!$C:$C='4 Pre Post Pandemic'!$C5),0))} -> 434.5 | F5: {=INDEX('Updated DATA SET'!AI:AI,MATCH(1,('Updated DATA SET'!$A:$A='4 Pre Post Pandemic'!$B$3)*('Updated DATA SET'!$B:$B='4 Pre Post Pandemic'!$B5)*('Updated DATA SET'!$C:$C='4 Pre Post Pandemic'!$C5),0))} -> 443.1 | G5: {=INDEX('Updated DATA SET'!AJ:AJ,MATCH(1,('Updated DATA SET'!$A:$A='4 Pre Post Pandemic'!$B$3)*('Updated DATA SET'!$B:$B='4 Pre Post Pandemic'!$B5)*('Updated DATA SET'!$C:$C='4 Pre Post Pandemic'!$C5),0))} -> 279.6 | H5: {=INDEX('Updated DATA SET'!AK:AK,MATCH(1,('Updated DATA SET'!$A:$A='4 Pre Post Pandemic'!$B$3)*('Updated DATA SET'!$B:$B='4 Pre Post Pandemic'!$B5)*('Updated DATA SET'!$C:$C='4 Pre Post Pandemic'!$C5),0))} -> 264.3 | I5: {=INDEX('Updated DATA SET'!AL:AL,MATCH(1,('Updated DATA SET'!$A:$A='4 Pre Post Pandemic'!$B$3)*('Updated DATA SET'!$B:$B='4 Pre Post Pandemic'!$B5)*('Updated DATA SET'!$C:$C='4 Pre Post Pandemic'!$C5),0))} -> 438.9
A6: End | B6: 2020 | C6: February | D6: {=INDEX('Updated DATA SET'!AG:AG,MATCH(1,('Updated DATA SET'!$A:$A='4 Pre Post Pandemic'!$B$3)*('Updated DATA SET'!$B:$B='4 Pre Post Pandemic'!$B6)*('Updated DATA SET'!$C:$C='4 Pre Post Pandemic'!$C6),0))} -> 1911.6 | E6: {=INDEX('Updated DATA SET'!AH:AH,MATCH(1,('Updated DATA SET'!$A:$A='4 Pre Post Pandemic'!$B$3)*('Updated DATA SET'!$B:$B='4 Pre Post Pandemic'!$B6)*('Updated DATA SET'!$C:$C='4 Pre Post Pandemic'!$C6),0))} -> 442 | F6: {=INDEX('Updated DATA SET'!AI:AI,MATCH(1,('Updated DATA SET'!$A:$A='4 Pre Post Pandemic'!$B$3)*('Updated DATA SET'!$B:$B='4 Pre Post Pandemic'!$B6)*('Updated DATA SET'!$C:$C='4 Pre Post Pandemic'!$C6),0))} -> 457.4 | G6: {=INDEX('Updated DATA SET'!AJ:AJ,MATCH(1,('Updated DATA SET'!$A:$A='4 Pre Post Pandemic'!$B$3)*('Updated DATA SET'!$B:$B='4 Pre Post Pandemic'!$B6)*('Updated DATA SET'!$C:$C='4 Pre Post Pandemic'!$C6),0))} -> 295.1 | H6: {=INDEX('Updated DATA SET'!AK:AK,MATCH(1,('Updated DATA SET'!$A:$A='4 Pre Post Pandemic'!$B$3)*('Updated DATA SET'!$B:$B='4 Pre Post Pandemic'!$B6)*('Updated DATA SET'!$C:$C='4 Pre Post Pandemic'!$C6),0))} -> 277.5 | I6: {=INDEX('Updated DATA SET'!AL:AL,MATCH(1,('Updated DATA SET'!$A:$A='4 Pre Post Pandemic'!$B$3)*('Updated DATA SET'!$B:$B='4 Pre Post Pandemic'!$B6)*('Updated DATA SET'!$C:$C='4 Pre Post Pandemic'!$C6),0))} -> 456.9
A7: Start | B7: 2020 | C7: March | D7: {=INDEX('Updated DATA SET'!AG:AG,MATCH(1,('Updated DATA SET'!$A:$A='4 Pre Post Pandemic'!$B$3)*('Updated DATA SET'!$B:$B='4 Pre Post Pandemic'!$B7)*('Updated DATA SET'!$C:$C='4 Pre Post Pandemic'!$C7),0))} -> 1895.4 | E7: {=INDEX('Updated DATA SET'!AH:AH,MATCH(1,('Updated DATA SET'!$A:$A='4 Pre Post Pandemic'!$B$3)*('Updated DATA SET'!$B:$B='4 Pre Post Pandemic'!$B7)*('Updated DATA SET'!$C:$C='4 Pre Post Pandemic'!$C7),0))} -> 442.9 | F7: {=INDEX('Updated DATA SET'!AI:AI,MATCH(1,('Updated DATA SET'!$A:$A='4 Pre Post Pandemic'!$B$3)*('Updated DATA SET'!$B:$B='4 Pre Post Pandemic'!$B7)*('Updated DATA SET'!$C:$C='4 Pre Post Pandemic'!$C7),0))} -> 457 | G7: {=INDEX('Updated DATA SET'!AJ:AJ,MATCH(1,('Updated DATA SET'!$A:$A='4 Pre Post Pandemic'!$B$3)*('Updated DATA SET'!$B:$B='4 Pre Post Pandemic'!$B7)*('Updated DATA SET'!$C:$C='4 Pre Post Pandemic'!$C7),0))} -> 297.5 | H7: {=INDEX('Updated DATA SET'!AK:AK,MATCH(1,('Updated DATA SET'!$A:$A='4 Pre Post Pandemic'!$B$3)*('Updated DATA SET'!$B:$B='4 Pre Post Pandemic'!$B7)*('Updated DATA SET'!$C:$C='4 Pre Post Pandemic'!$C7),0))} -> 278.8 | I7: {=INDEX('Updated DATA SET'!AL:AL,MATCH(1,('Updated DATA SET'!$A:$A='4 Pre Post Pandemic'!$B$3)*('Updated DATA SET'!$B:$B='4 Pre Post Pandemic'!$B7)*('Updated DATA SET'!$C:$C='4 Pre Post Pandemic'!$C7),0))} -> 458.7
A8: End | B8: 2021 | C8: February | D8: {=INDEX('Updated DATA SET'!AG:AG,MATCH(1,('Updated DATA SET'!$A:$A='4 Pre Post Pandemic'!$B$3)*('Updated DATA SET'!$B:$B='4 Pre Post Pandemic'!$B8)*('Updated DATA SET'!$C:$C='4 Pre Post Pandemic'!$C8),0))} -> 2039.3 | E8: {=INDEX('Updated DATA SET'!AH:AH,MATCH(1,('Updated DATA SET'!$A:$A='4 Pre Post Pandemic'!$B$3)*('Updated DATA SET'!$B:$B='4 Pre Post Pandemic'!$B8)*('Updated DATA SET'!$C:$C='4 Pre Post Pandemic'!$C8),0))} -> 460.4 | F8: {=INDEX('Updated DATA SET'!AI:AI,MATCH(1,('Updated DATA SET'!$A:$A='4 Pre Post Pandemic'!$B$3)*('Updated DATA SET'!$B:$B='4 Pre Post Pandemic'!$B8)*('Updated DATA SET'!$C:$C='4 Pre Post Pandemic'!$C8),0))} -> 470.2 | G8: {=INDEX('Updated DATA SET'!AJ:AJ,MATCH(1,('Updated DATA SET'!$A:$A='4 Pre Post Pandemic'!$B$3)*('Updated DATA SET'!$B:$B='4 Pre Post Pandemic'!$B8)*('Updated DATA SET'!$C:$C='4 Pre Post Pandemic'!$C8),0))} -> 317.1 | H8: {=INDEX('Updated DATA SET'!AK:AK,MATCH(1,('Updated DATA SET'!$A:$A='4 Pre Post Pandemic'!$B$3)*('Updated DATA SET'!$B:$B='4 Pre Post Pandemic'!$B8)*('Updated DATA SET'!$C:$C='4 Pre Post Pandemic'!$C8),0))} -> 297.5 | I8: {=INDEX('Updated DATA SET'!AL:AL,MATCH(1,('Updated DATA SET'!$A:$A='4 Pre Post Pandemic'!$B$3)*('Updated DATA SET'!$B:$B='4 Pre Post Pandemic'!$B8)*('Updated DATA SET'!$C:$C='4 Pre Post Pandemic'!$C8),0))} -> 493.2
A9: Start | B9: 2021 | C9: March | D9: {=INDEX('Updated DATA SET'!AG:AG,MATCH(1,('Updated DATA SET'!$A:$A='4 Pre Post Pandemic'!$B$3)*('Updated DATA SET'!$B:$B='4 Pre Post Pandemic'!$B9)*('Updated DATA SET'!$C:$C='4 Pre Post Pandemic'!$C9),0))} -> 2039.4 | E9: {=INDEX('Updated DATA SET'!AH:AH,MATCH(1,('Updated DATA SET'!$A:$A='4 Pre Post Pandemic'!$B$3)*('Updated DATA SET'!$B:$B='4 Pre Post Pandemic'!$B9)*('Updated DATA SET'!$C:$C='4 Pre Post Pandemic'!$C9),0))} -> 462.1 | F9: {=INDEX('Updated DATA SET'!AI:AI,MATCH(1,('Updated DATA SET'!$A:$A='4 Pre Post Pandemic'!$B$3)*('Updated DATA SET'!$B:$B='4 Pre Post Pandemic'!$B9)*('Updated DATA SET'!$C:$C='4 Pre Post Pandemic'!$C9),0))} -> 471.3 | G9: {=INDEX('Updated DATA SET'!AJ:AJ,MATCH(1,('Updated DATA SET'!$A:$A='4 Pre Post Pandemic'!$B$3)*('Updated DATA SET'!$B:$B='4 Pre Post Pandemic'!$B9)*('Updated DATA SET'!$C:$C='4 Pre Post Pandemic'!$C9),0))} -> 315.5 | H9: {=INDEX('Updated DATA SET'!AK:AK,MATCH(1,('Updated DATA SET'!$A:$A='4 Pre Post Pandemic'!$B$3)*('Updated DATA SET'!$B:$B='4 Pre Post Pandemic'!$B9)*('Updated DATA SET'!$C:$C='4 Pre Post Pandemic'!$C9),0))} -> 301.7 | I9: {=INDEX('Updated DATA SET'!AL:AL,MATCH(1,('Updated DATA SET'!$A:$A='4 Pre Post Pandemic'!$B$3)*('Updated DATA SET'!$B:$B='4 Pre Post Pandemic'!$B9)*('Updated DATA SET'!$C:$C='4 Pre Post Pandemic'!$C9),0))} -> 494.5
A10: End | B10: 2022 | C10: February | D10: {=INDEX('Updated DATA SET'!AG:AG,MATCH(1,('Updated DATA SET'!$A:$A='4 Pre Post Pandemic'!$B$3)*('Updated DATA SET'!$B:$B='4 Pre Post Pandemic'!$B10)*('Updated DATA SET'!$C:$C='4 Pre Post Pandemic'!$C10),0))} -> 2161.2 | E10: {=INDEX('Updated DATA SET'!AH:AH,MATCH(1,('Updated DATA SET'!$A:$A='4 Pre Post Pandemic'!$B$3)*('Updated DATA SET'!$B:$B='4 Pre Post Pandemic'!$B10)*('Updated DATA SET'!$C:$C='4 Pre Post Pandemic'!$C10),0))} -> 502.8 | F10: {=INDEX('Updated DATA SET'!AI:AI,MATCH(1,('Updated DATA SET'!$A:$A='4 Pre Post Pandemic'!$B$3)*('Updated DATA SET'!$B:$B='4 Pre Post Pandemic'!$B10)*('Updated DATA SET'!$C:$C='4 Pre Post Pandemic'!$C10),0))} -> 492.7 | G10: {=INDEX('Updated DATA SET'!AJ:AJ,MATCH(1,('Updated DATA SET'!$A:$A='4 Pre Post Pandemic'!$B$3)*('Updated DATA SET'!$B:$B='4 Pre Post Pandemic'!$B10)*('Updated DATA SET'!$C:$C='4 Pre Post Pandemic'!$C10),0))} -> 336.6 | H10: {=INDEX('Updated DATA SET'!AK:AK,MATCH(1,('Updated DATA SET'!$A:$A='4 Pre Post Pandemic'!$B$3)*('Updated DATA SET'!$B:$B='4 Pre Post Pandemic'!$B10)*('Updated DATA SET'!$C:$C='4 Pre Post Pandemic'!$C10),0))} -> 322.6 | I10: {=INDEX('Updated DATA SET'!AL:AL,MATCH(1,('Updated DATA SET'!$A:$A='4 Pre Post Pandemic'!$B$3)*('Updated DATA SET'!$B:$B='4 Pre Post Pandemic'!$B10)*('Updated DATA SET'!$C:$C='4 Pre Post Pandemic'!$C10),0))} -> 518.4
A12: Period ↓ Category → | B12: Food | C12: Clothing | D12: Essential | E12: Health | F12: Energy | G12: Luxury
A13: Before COVID (Mar19 → Feb20) | B13: =(D6-D5)/D5 -> 0.084349651 | C13: =(E6-E5)/E5 -> 0.01726122 | D13: =(F6-F5)/F5 -> 0.032272625 | E13: =(G6-G5)/G5 -> 0.055436338 | F13: =(H6-H5)/H5 -> 0.049943246 | G13: =(I6-I5)/I5 -> 0.04101162
A14: COVID Year (Mar20 → Feb21) | B14: =(D8-D7)/D7 -> 0.07592065 | C14: =(E8-E7)/E7 -> 0.039512305 | D14: =(F8-F7)/F7 -> 0.028884026 | E14: =(G8-G7)/G7 -> 0.065882353 | F14: =(H8-H7)/H7 -> 0.067073171 | G14: =(I8-I7)/I7 -> 0.075212557
A15: AFTER COVID Year (Mar21 → Feb22) | B15: =(D10-D9)/D9 -> 0.059723448 | C15: =(E10-E9)/E9 -> 0.088076174 | D15: =(F10-F9)/F9 -> 0.045406323 | E15: =(G10-G9)/G9 -> 0.066877971 | F15: =(H10-H9)/H9 -> 0.069274113 | G15: =(I10-I9)/I9 -> 0.048331648
A32: Sl. No. | B32: Observation | E32: Reason
A33: 1 | B33: Food inflation was highest Before COVID (8.43%) and declined during and after COVID. | E33: Food index grew sharply from Mar’19 → Feb’20, but the rise slowed in COVID (7.59%) and fell further post-COVID (5.97%).
A34: 2 | B34: Clothing inflation peaked After COVID (8.81%), showing strong recovery and increased consumer spending. | E34: Clothing growth was low pre-COVID (1.73%) and moderate during COVID (3.95%), then surged post-COVID as demand returned.
A35: 3 | B35: Essential category inflation increased steadily across all three periods. | E35: Essential inflation rose from 2.32% → 2.89% → 3.81%, indicating continuous demand for basic goods regardless of disruptions.
A36: 4 | B36: Health inflation jumped significantly during COVID (6.59%). | E36: Health index rose sharply due to higher medical spending, increased healthcare demand, and pandemic-driven costs.

Sheet Data Validation Lookup
A1: Solution 1
A2: Sector | B2: Year | C2: Month
A3: Rural | B3: 2013 | C3: January
A4: Urban | B4: 2014 | C4: February
A5: Rural+Urban | B5: 2015 | C5: March
B6: 2016 | C6: April
B7: 2017 | C7: May
B8: 2018 | C8: June
B9: 2019 | C9: July
B10: 2020 | C10: August
B11: 2021 | C11: September
B12: 2022 | C12: October
B13: 2023 | C13: November
C14: December

Sheet Crude Oil DataSet
A2: Year | B2: Month | C2: CRUDE OIL
A3: 2020 | B3: December
A4: 2021 | B4: January | C4: 66695.479
A5: 2021 | B5: February | C5: 60965.591
A6: 2021 | B6: March | C6: 75470.774
A7: 2021 | B7: April | C7: 74207.645
A8: 2021 | B8: May | C8: 70046.397
A9: 2021 | B9: June | C9: 71679.349
A10: 2021 | B10: July | C10: 72860.439
A11: 2021 | B11: August | C11: 80983.016
A12: 2021 | B12: September | C12: 83035.174
A13: 2021 | B13: October | C13: 91471.514
A14: 2021 | B14: November | C14: 95105.452
A15: 2021 | B15: December | C15: 100380.53
... A32: 2023 | B32: May | C32: 103486.67

Sheet 5 Oil Impact on CPI
A1: IMPACT OF CRUDE OIL WITH ALL CATEGORIES AND CORRELATION
A3: Sector | B3: Year | C3: Month | D3: Cereals and products | E3: Meat and fish | F3: Egg | G3: Milk and products | H3: Oils and fats | I3: Fruits | J3: Vegetables | K3: Pulses and products | L3: Sugar and Confectionery | M3: Spices | N3: Non-alcoholic beverages | O3: Prepared meals, snacks, sweets etc. | P3: Food and beverages | Q3: Pan, tobacco and intoxicants | R3: Clothing | S3: Footwear | T3: Clothing and footwear | U3: Housing | V3: NEW HOUSING | W3: Fuel and light | X3: Household goods and services | Y3: Health | Z3: Transport and communication | AA3: Recreation and amusement | AB3: Education | AC3: Personal care and effects | AD3: Miscellaneous | AE3: General index | AF3: Crude Oil
